Workbook
Name POWER_USER_LINK_1C8468DF_3981_452A_988B_B237ACC8F15D: '[1]Financing Baseline'!$C$128:$P$134
Name POWER_USER_LINK_1E1BD091_4625_4444_97D5_A6FF49E7A790: '[1]Financing Baseline'!$D$109:$P$115
Name POWER_USER_LINK_5C354A30_39B7_4BC2_A1BC_772102FD5A07: '[1]Financing Baseline'!$D$109:$P$115
Name POWER_USER_LINK_660DD32F_20D2_4943_85B4_C2277CFD14E1: '[1]Financing Baseline'!$D$109:$P$115
Name POWER_USER_LINK_82AA7F52_0AA6_445C_99A0_BCDBE6072606: '[1]Financing Baseline'!$C$128:$P$134
Name POWER_USER_LINK_8811B919_6076_4DE1_8A8A_1591D1C3F1D3: '[1]Financing Baseline'!$D$109:$P$115
Name POWER_USER_LINK_88A461FD_7EA7_42BC_9FB8_413E38E7215B: '[1]Financing Baseline'!$D$101:$P$107
Name POWER_USER_LINK_8BD0C2AE_99B7_4293_8693_DF676F2E4705: '[1]Financing Baseline'!$D$93:$P$99
Name POWER_USER_LINK_9E537006_98B2_46EC_8819_DD41353322F7: '[1]Financing Baseline'!$C$128:$P$134
Name POWER_USER_LINK_A4EC7F36_8FF3_4488_B633_885239D87E7F: '[1]Financing Baseline'!$D$93:$P$99
Name POWER_USER_LINK_C0E51312_0DE1_43B3_B0BB_32513878B4D0: '[1]Financing Baseline'!$C$128:$P$134
Name POWER_USER_LINK_C40E531F_E888_434D_B256_633316EE9B99: '[1]Financing Baseline'!$D$109:$P$115
Name POWER_USER_LINK_C670BFA9_1E80_4883_8B1D_2D7BF8BEB301: '[1]Financing Baseline'!$C$128:$P$134
Name POWER_USER_LINK_C8E7FDEE_D21E_4649_A767_4F5C55FA2FC8: '[1]Financing Baseline'!$D$101:$P$107
Name POWER_USER_LINK_C904F0C4_2D79_4048_B89A_3A3D35880395: '[1]Financing Baseline'!$D$101:$P$107
Name POWER_USER_LINK_CB729846_7F59_4903_A12A_D4277681E321: '[1]Financing Baseline'!$D$93:$J$99
Name POWER_USER_LINK_E7C2DD64_3477_4661_87F3_FF98A191BC47: '[1]Financing Baseline'!$D$101:$P$107
Name POWER_USER_LINK_ECA9A96E_360E_419C_ABD3_88BEB06ADB97: '[1]Financing Baseline'!$D$101:$P$107

Sheet Definitions
B3: MINFin
B4: Model for Informated National Financing
B7: MINFin Input File - Guide | E7: MINFin is a sectoral cashflow model ….......
B9: Document structure
B11: Parameter Constraints
B12: Financing Baseline
B13: Funding Baseline
B15: Parameter Constraints | E15: Financing Baseline | H15: Funding Baseline | K15: Technologies
B16: Name | C16: Description | E16: Name | F16: Description | H16: Name | I16: Description | K16: Name | L16: Description | M16: Classification
B17: CurrencyExchangeRate | D17: - | E17: Name of Project | G17: - | H17: Name | J17: - | K17: PWRBIO001 | L17: Biomass power plant | M17: Biomass
B18: GDPGrowth | C18: The parameter defines annual percentage growth rate of GDP. | D18: - | E18: Name of Financier | G18: - | H18: Name of Financier | J18: - | K18: PWRCOA001 | L18: Coal power plant | M18: Coal
B19: AnnualGDP | D19: - | E19: Technology | G19: - | H19: Technology | I19: The technology parameter encompasses different power-generation technologies. | J19: - | K19: PWRGEO | L19: Geothermal power plant | M19: Geothermal
B20: Elasticity of energy demand | D20: - | E20: Source | G20: - | H20: Source | J20: - | K20: PWROHC001 | L20: Light fuel oil power plant | M20: Oil
B21: CAGR of real energy price | D21: - | E21: Financing Source | G21: - | H21: Volume of Finance | I21: The parameter volume of finance refers to the sum of money involved in financial transactions from a financier to a project, expressed in millions of units of the local currency. | J21: - | K21: PWROHC002 | L21: Oil fired gas turbine - SCGT | M21: Oil
B22: DiscountRate | C22: The discount rate parameter represents the percentage rate used to discount future cash flows to their present value. | D22: - | E22: Type of Finance | G22: - | H22: GovShare | J22: - | K22: PWRNGS001 | L22: Natural gas power plant - CCGT | M22: Gas
B23: AnnualLoanRepayments | D23: - | E23: Financing Sector | G23: - | H23: Year | J23: - | K23: PWRNGS002 | L23: Nautral gas power plant - SCGT | M23: Gas
B24: BuildTime | C24: The build time parameter refers to the duration, in years, required for the construction of a power plant from the project's start to its completion and operational readiness. | D24: - | E24: Financial Institution | G24: - | H24: Currency | J24: - | K24: PWRSOL001 | L24: Solar PV - Utility scale | M24: Solar PV
B25: Weighting | C25: The weighting parameter indicates the relative contribution of four finance categories (DomesticCommercial, DomesticConcessional, InternationalCommercial, InternationalConcessional) to the total financing of each technology. The sum of these contributions from the four categories should equal 1 for each technology. | D25: - | E25: Origin of Finance | G25: - | J25: - | K25: PWRCSP001 | L25: CSP - Without storage | M25: CSP
B26: WACC | C26: The Weighted Average Cost of Capital (WACC) parameter reflects the combined cost of capital from various sources, including both debt and equity. It should be determined by weighting the cost of each capital type based on its proportion of the total capital and then summing them together. | D26: - | E26: Volume of Finance | G26: - | J26: - | K26: PWRCSP002 | L26: CSP - With storage | M26: CSP
B27: GracePeriod | C27: The grace period parameter represents the duration, measured in years, from the loan's issuance to the initial repayment of principal. | D27: - | E27: Rate | G27: - | J27: - | K27: PWRHYD001 | L27: Hydropower plant - Large dam (>100MW) | M27: Hydropower
B28: Term | C28: The parameter "term" denotes the duration, in years, of a loan or, in the case of equity, the lifespan of the project being financed. | D28: - | E28: Term | F28: The parameter "term" denotes the duration, in years, of a loan or, in the case of equity, the lifespan of the project being financed. | G28: - | J28: - | K28: PWRHYD002 | L28: Hydropower plant - Medium (10-100MW) | M28: Hydropower
B29: CAGRGovtSpending | C29: The Compound Annual Growth Rate (CAGR) of Government Spending parameter defines the annualised percentage rate of growth of government budget funding over the modelled period. XXX Should be considered. Downstream oil and gas spending should not be included. | D29: - | E29: Grace period | F29: The grace period parameter represents the duration, measured in years, from the loan's issuance to the initial repayment of principal. | G29: - | J29: - | K29: PWRHYD003 | L29: Hydropower plant - Small (<10MW) | M29: Hydropower
B30: CAGRSOECashflow | D30: - | E30: Schedule | G30: - | J30: - | K30: PWRWND001 | L30: Wind farm - Onshore | M30: Onshore Wind
B31: CAGRGrants | C31: The Compound Annual Growth Rate (CAGR) of grants parameter defines the annualised percentage rate of growth for grant funding over the modelled period. | D31: - | E31: Project Close | F31: This parameter marks financial closure, indicating the year when the procurement phase ends with the signing of the PPP contract, meeting financing prerequisites, and securing funds for Project Company to start construction. | G31: - | J31: - | K31: PWRWND002 | L31: Wind farm - Offshore | M31: Offshore Wind
D32: - | E32: Start Year | F32: The Start Year parameter specifies the year when financing repayment begins, initiating from loan year 0. | G32: - | J32: - | K32: PWRNUC | L32: Nuclear power plant | M32: Nuclear
B33: Currencies | E33: Currency | G33: - | K33: PWRTRN | L33: Electricity transmission | M33: Transmission
B34: Code | C34: Currency | G34: - | K34: PWRDIST | L34: Electricity distribution | M34: Distribution
B35: USD | C35: US Dollar | G35: - | K35: PWROHC003 | L35: Light fuel oil standalone generator (1kW) | M35: Oil
B36: CAD | C36: Canadian Dollar | E36: Scenarios | G36: - | K36: PWRSOL002 | L36: Solar PV - distributed with storage | M36: Solar PV
B37: CNY | C37: Chinese Renminbi | E37: Name | F37: Description | G37: - | K37: PWRHYD004 | L37: Hydropower plant - Off-grid | M37: Hydropower
B38: GBP | C38: British Pound | E38: NetZero | F38: Scenario Name 1 (More ambitious) | G38: - | K38: PWRSOL001S | L38: Solar PV - Utility with 2-hour storage | M38: Solar PV
B39: INR | C39: Indian Rupee | E39: LeastCost | F39: Scenario Name 2 (Less ambitious) | G39: - | K39: PWRWND001S | L39: Onshore wind with storage | M39: Onshore Wind
B40: JPY | C40: Japanese Yen | G40: - | K40: BESS | L40: Battery | M40: Other
G41: -
G42: -
G43: -
G44: -
G45: -

Sheet Visualisation Dashboard
A1: MINFin
A2: Visualisation Dashboard
A4: MINFin Projections
A33: Financing Needs Projections
AD37: Net Benefits
AD38: Year | AE38: 2025 | AF38: 2030 | AG38: 2035 | AH38: 2040 | AI38: 2045 | AJ38: 2050 | AK38: 2055 | AL38: 2060 | AM38: 2065
AD39: Net1 | AE39: {=TRANSPOSE('OSeMOSYS (Input)'!$AG$143:$AG$151)+TRANSPOSE('OSeMOSYS (Input)'!$AC$143:$AC$151)+TRANSPOSE('OSeMOSYS (Input)'!$Z$143:$Z$151)+TRANSPOSE('OSeMOSYS (Input)'!$AF$143:$AF$151)} -> -9.1619022 | AF39: 20.411886 | AG39: 57.943075 | AH39: 7.0658643 | AI39: -16.931267 | AJ39: 66.697634 | AK39: 170.8762 | AL39: 215.17897 | AM39: 300.19716
AD40: Net2 | AE40: {=TRANSPOSE('OSeMOSYS (Input)'!$AG$143:$AG$151)+TRANSPOSE('OSeMOSYS (Input)'!$AC$143:$AC$151)+TRANSPOSE('OSeMOSYS (Input)'!$Z$143:$Z$151)+TRANSPOSE('OSeMOSYS (Input)'!$AF$143:$AF$151)} -> -9.1619022 | AF40: 20.411886 | AG40: 57.943075 | AH40: 7.0658643 | AI40: -16.931267 | AJ40: 66.697634 | AK40: 170.8762 | AL40: 215.17897 | AM40: 300.19716
AD41: Pos1 | AE41: 1 | AF41: =AE42+1 -> 5 | AG41: =AF42+1 -> 9 | AH41: =AG42+1 -> 13 | AI41: =AH42+1 -> 17 | AJ41: =AI42+1 -> 21 | AK41: =AJ42+1 -> 25 | AL41: =AK42+1 -> 29 | AM41: =AL42+1 -> 33
AD42: Pos2 | AE42: =AE41+$AE$43 -> 4 | AF42: =AF41+$AE$43 -> 8 | AG42: =AG41+$AE$43 -> 12 | AH42: =AH41+$AE$43 -> 16 | AI42: =AI41+$AE$43 -> 20 | AJ42: =AJ41+$AE$43 -> 24 | AK42: =AK41+$AE$43 -> 28 | AL42: =AL41+$AE$43 -> 32 | AM42: =AM41+$AE$43 -> 36
AD43: Spacing | AE43: 3
E66: FFRM | F66: NZ Cost (Million US$)
E67: Coal | F67: =SUM('Investment Needs'!C172:AV172) -> 0
E68: Gas | F68: =SUM('Investment Needs'!C175:AV175) -> 0
E69: Oil | F69: =SUM('Investment Needs'!C178:AV178) -> 0
A87: Funding Availability Projections
A117: Historic Financing
M120: rank | N120: source | O120: vol | P120: market
M121: =5-RANK(P121,$P$121:$P$124) -> 2 | N121: Conc Dom | O121: =SUMIFS('Financing Baseline'!K49:K516,'Financing Baseline'!F49:F516,"Conc_DPS",'Financing Baseline'!G49:G516,"Loan") -> 205.98 | P121: {=IFERROR(SUMPRODUCT(IF('Financing Baseline'!F49:F516="Conc_DPS",1,0),IF('Financing Baseline'!G49:G516="Loan",1,0),'Financing Baseline'!K49:K516,'Financing Baseline'!X49:X516)/'Visualisation Dashboard'!O121,0)} -> 0.22868714
M122: =5-RANK(P122,$P$121:$P$124) -> 1 | N122: Conc Intl | O122: =SUMIFS('Financing Baseline'!K49:K516,'Financing Baseline'!F49:F516,"Conc_IFI",'Financing Baseline'!G49:G516,"Loan") -> 8033.9146 | P122: {=IFERROR( SUMPRODUCT(IF('Financing Baseline'!F49:F516="Conc_IFI",1,0),IF('Financing Baseline'!G49:G516="Loan",1,0),'Financing Baseline'!K49:K516,'Financing Baseline'!X49:X516)/ 'Visualisation Dashboard'!O122, 0)} -> 0.19386327
M123: =5-RANK(P123,$P$121:$P$124) -> 4 | N123: Com Dom | O123: =SUMIFS('Financing Baseline'!K49:K516,'Financing Baseline'!G49:G516,"Loan",'Financing Baseline'!F49:F516,"Comm_Dom") -> 51.4 | P123: {=IFERROR(SUMPRODUCT(IF('Financing Baseline'!F49:F516="Comm_Dom",1,0),IF('Financing Baseline'!G49:G516="Loan",1,0),'Financing Baseline'!K49:K516,'Financing Baseline'!X49:X516)/'Visualisation Dashboard'!O123,0)} -> 0.7523873
D124: Provider | E124: Instrument | F124: Origin | G124: Source | M124: =5-RANK(P124,$P$121:$P$124) -> 3 | N124: Com Intl | O124: =SUMIFS('Financing Baseline'!K49:K516,'Financing Baseline'!G49:G516,"Loan",'Financing Baseline'!F49:F516,"Comm_Intl") -> 484.02 | P124: {=IFERROR(SUMPRODUCT(IF('Financing Baseline'!F49:F516="Comm_Intl",1,0),IF('Financing Baseline'!G49:G516="Loan",1,0),'Financing Baseline'!K49:K516,'Financing Baseline'!X49:X516)/'Visualisation Dashboard'!O124,0)} -> 0.66103185
C125: 1 | D125: ='Financing Baseline'!L31 -> 0.86302412 | E125: ='Financing Baseline'!K16 -> 0.79897797 | F125: ='Financing Baseline'!L33 -> 0.13437369 | G125: ='High Level Dashboard'!F53 -> 0.74381344 | M125: =IFERROR(VLOOKUP(1,$M$121:$N$124,2,FALSE),"") -> Conc Intl | N125: =IFERROR(VLOOKUP(2,$M$121:$N$124,2,FALSE),"") -> Conc Dom | O125: =IFERROR(VLOOKUP(3,$M$121:$N$124,2,FALSE),"") -> Com Intl | P125: =IFERROR(VLOOKUP(4,$M$121:$N$124,2,FALSE),"") -> Com Dom
C126: 2 | D126: ='Financing Baseline'!L32 -> 0.13697588 | E126: ='Financing Baseline'!L16 -> 0.20102203 | F126: ='Financing Baseline'!L34 -> 0.86562631 | G126: ='High Level Dashboard'!F54 -> 0.11109827 | M126: =IFERROR(VLOOKUP(M125,$N$121:$O$124,2,FALSE),0) -> 8033.9146 | N126: =IFERROR(VLOOKUP(N125,$N$121:$O$124,2,FALSE),0) -> 205.98 | O126: =IFERROR(VLOOKUP(O125,$N$121:$O$124,2,FALSE),0) -> 484.02 | P126: =IFERROR(VLOOKUP(P125,$N$121:$O$124,2,FALSE),0) -> 51.4
C127: 3 | D127: 0 | E127: 0 | F127: 0 | G127: ='High Level Dashboard'!F55 -> 0.12181287 | L127: 0 | M127: =IFERROR(VLOOKUP(1,$M$121:$P$124,4,FALSE),"") -> 0.19386327
C128: 4 | D128: 0 | E128: 0 | F128: 0 | G128: ='High Level Dashboard'!F56 -> 0.02327542 | L128: =IFERROR(VLOOKUP(1,$M$121:$O$124,3,FALSE),0) -> 8033.9146 | M128: =IFERROR(VLOOKUP(1,$M$121:$P$124,4,FALSE),"") -> 0.19386327
L129: =IFERROR(VLOOKUP(1,$M$121:$O$124,3,FALSE),0) -> 8033.9146
L130: =IFERROR(VLOOKUP(1,$M$121:$O$124,3,FALSE),0) -> 8033.9146 | N130: =IFERROR(VLOOKUP(2,$M$121:$P$124,4,FALSE),"") -> 0.22868714
L131: =IFERROR(VLOOKUP(2,$M$121:$O$124,3,FALSE)+$L$128,0) -> 8239.8946 | N131: =IFERROR(VLOOKUP(2,$M$121:$P$124,4,FALSE),"") -> 0.22868714
L132: =IFERROR(VLOOKUP(2,$M$121:$O$124,3,FALSE)+$L$128,0) -> 8239.8946
L133: =IFERROR(VLOOKUP(2,$M$121:$O$124,3,FALSE)+$L$128,0) -> 8239.8946 | O133: =IFERROR(VLOOKUP(3,$M$121:$P$124,4,FALSE),"") -> 0.66103185
L134: =IFERROR(VLOOKUP(3,$M$121:$O$124,3,FALSE)+$L$131,0) -> 8723.9146 | O134: =IFERROR(VLOOKUP(3,$M$121:$P$124,4,FALSE),"") -> 0.66103185
L135: =IFERROR(VLOOKUP(3,$M$121:$O$124,3,FALSE)+$L$131,0) -> 8723.9146
L136: =IFERROR(VLOOKUP(3,$M$121:$O$124,3,FALSE)+$L$131,0) -> 8723.9146 | P136: =IFERROR(VLOOKUP(4,$M$121:$P$124,4,FALSE),"") -> 0.7523873
L137: =IFERROR(VLOOKUP(4,$M$121:$O$124,3,FALSE)+$L$134,0) -> 8775.3146 | P137: =IFERROR(VLOOKUP(4,$M$121:$P$124,4,FALSE),"") -> 0.7523873
D148: Financing Sources | AF148: WACC Calculation
C149: Conc IFI (Debt) | D149: ='Financing Baseline'!B32 -> 8033.9146 | AD149: Rank | AE149: Technology | AF149: IRR | AG149: Share of Equity | AH149: Interest Rate | AI149: Share of Debt | AJ149: Volume of Finance | AK149: WACC
C150: Conc DPS (Debt) | D150: ='Financing Baseline'!B33 -> 205.98 | AD150: =IFERROR(RANK($AK150,$AK$150:$AK$159,1)+COUNTIF(AK150:$AK$159,AK150)-1,"") -> 7 | AE150: {=IF(_xlfn.UNIQUE('Financing Baseline'!$C$49:$C$516)=0,"",_xlfn.UNIQUE('Financing Baseline'!$C$49:$C$516))} -> Geothermal | AF150: =IFERROR(AVERAGEIFS('Financing Baseline'!$P$49:$P$516, 'Financing Baseline'!$C$49:$C$516, AE150, 'Financing Baseline'!$G$49:$G$516, "Equity"),0) -> 0.18721296 | AG150: =IFERROR((SUMIFS('Financing Baseline'!$N$49:$N$516, 'Financing Baseline'!$C$49:$C$516, $AE150, 'Financing Baseline'!$G$49:$G$516, "Equity"))/$AJ150,0) -> 0.25579778 | AH150: =IFERROR(AVERAGEIFS('Financing Baseline'!$P$46:$P$513, 'Financing Baseline'!$C$46:$C$513, AE150, 'Financing Baseline'!$G$46:$G$513, "Loan"),0) -> 0.032753269 | AI150: =IFERROR(SUMIFS('Financing Baseline'!$N$49:$N$516, 'Financing Baseline'!$C$49:$C$516, AE150, 'Financing Baseline'!$G$49:$G$516, "Loan")/$AJ150,0) -> 0.74420222 | AJ150: =SUMIF('Financing Baseline'!$C$49:$C$516, AE150, 'Financing Baseline'!$N$49:$N$516) -> 4410.8409 | AK150: =IFERROR( (AF150*(AG150/(AG150+AI150)))+ (AH150*(AI150/(AG150+AI150))), "") -> 0.072263716
C151: Comm Intl (Debt) | D151: ='Financing Baseline'!B34 -> 484.02 | AD151: =IFERROR(RANK($AK151,$AK$150:$AK$159,1)+COUNTIF(AK151:$AK$159,AK151)-1,"") -> 3 | AE151: Solar | AF151: =IFERROR(AVERAGEIFS('Financing Baseline'!$P$49:$P$516, 'Financing Baseline'!$C$49:$C$516, AE151, 'Financing Baseline'!$G$49:$G$516, "Equity"),0) -> 0.053 | AG151: =IFERROR((SUMIFS('Financing Baseline'!$N$49:$N$516, 'Financing Baseline'!$C$49:$C$516, $AE151, 'Financing Baseline'!$G$49:$G$516, "Equity"))/$AJ151,0) -> 0.25080298 | AH151: =IFERROR(AVERAGEIFS('Financing Baseline'!$P$46:$P$513, 'Financing Baseline'!$C$46:$C$513, AE151, 'Financing Baseline'!$G$46:$G$513, "Loan"),0) -> 0.036277944 | AI151: =IFERROR(SUMIFS('Financing Baseline'!$N$49:$N$516, 'Financing Baseline'!$C$49:$C$516, AE151, 'Financing Baseline'!$G$49:$G$516, "Loan")/$AJ151,0) -> 0.74919702 | AJ151: =SUMIF('Financing Baseline'!$C$49:$C$516, AE151, 'Financing Baseline'!$N$49:$N$516) -> 783.025 | AK151: =IFERROR( (AF151*(AG151/(AG151+AI151)))+ (AH151*(AI151/(AG151+AI151))), "") -> 0.040471885
C152: Comm Dom (Debt) | D152: ='Financing Baseline'!B35 -> 51.4 | M152: Market Elements by Financier | T152: Market Elements by Financier | AD152: =IFERROR(RANK($AK152,$AK$150:$AK$159,1)+COUNTIF(AK152:$AK$159,AK152)-1,"") -> 8 | AE152: Biomass | AF152: =IFERROR(AVERAGEIFS('Financing Baseline'!$P$49:$P$516, 'Financing Baseline'!$C$49:$C$516, AE152, 'Financing Baseline'!$G$49:$G$516, "Equity"),0) -> 0.12 | AG152: =IFERROR((SUMIFS('Financing Baseline'!$N$49:$N$516, 'Financing Baseline'!$C$49:$C$516, $AE152, 'Financing Baseline'!$G$49:$G$516, "Equity"))/$AJ152,0) -> 0.38427948 | AH152: =IFERROR(AVERAGEIFS('Financing Baseline'!$P$46:$P$513, 'Financing Baseline'!$C$46:$C$513, AE152, 'Financing Baseline'!$G$46:$G$513, "Loan"),0) -> 0.06152105 | AI152: =IFERROR(SUMIFS('Financing Baseline'!$N$49:$N$516, 'Financing Baseline'!$C$49:$C$516, AE152, 'Financing Baseline'!$G$49:$G$516, "Loan")/$AJ152,0) -> 0.61572052 | AJ152: =SUMIF('Financing Baseline'!$C$49:$C$516, AE152, 'Financing Baseline'!$N$49:$N$516) -> 229 | AK152: =IFERROR( (AF152*(AG152/(AG152+AI152)))+ (AH152*(AI152/(AG152+AI152))), "") -> 0.08399331
C153: Conc IFI (Equity) | D153: ='Financing Baseline'!B24 -> 135.51833 | M153: {=_xlfn._xlws.FILTER(_xlfn._xlws.SORT(_xlfn.UNIQUE('Financing Baseline'!$I$49:$I$516)),_xlfn._xlws.SORT(_xlfn.UNIQUE('Financing Baseline'!$I$49:$I$516))<>0)} -> Bilateral Agency | N153: =IFERROR(AVERAGEIFS('Financing Baseline'!$X$49:$X$516,'Financing Baseline'!$I$49:$I$516,M153,'Financing Baseline'!$G$49:$G$516,"<>"&"Equity"), 0) -> 0.25680087 | O153: =_xlfn.RANK.EQ(N153, N$153:N$159) + COUNTIF(N$153:N153, N153) - 1 -> 5 | P153: =IF(_xlfn.XLOOKUP(R153,$O$153:$O$159,$M$153:$M$159,"")=0,"",_xlfn.XLOOKUP(R153,$O$153:$O$159,$M$153:$M$159,"")) -> Private Equity Fund | Q153: =_xlfn.XLOOKUP(R153,$O$153:$O$159,$N$153:$N$159) -> 1 | R153: 1 | T153: {=_xlfn._xlws.FILTER(_xlfn._xlws.SORT(_xlfn.UNIQUE('Financing Baseline'!$F$49:$F$516)),_xlfn._xlws.SORT(_xlfn.UNIQUE('Financing Baseline'!$F$49:$F$516))<>0)} -> Comm_Dom | U153: =IFERROR(AVERAGEIFS('Financing Baseline'!$X$49:$X$516,'Financing Baseline'!$F$49:$F$516,T153,'Financing Baseline'!$G$49:$G$516,"<>"&"Equity"), 0) -> 0.5757569 | V153: =RANK(U153,$U$153:$U$156,1) -> 3 | W153: =IF(_xlfn.XLOOKUP(Y153,$V$153:$V$156,$T$153:$T$156,"")=0,"",_xlfn.XLOOKUP(Y153,$V$153:$V$156,$T$153:$T$156,"")) -> Conc_IFI | X153: =_xlfn.XLOOKUP(Y153,$V$153:$V$156,$U$153:$U$156) -> 0.24232832 | Y153: 1 | AD153: =IFERROR(RANK($AK153,$AK$150:$AK$159,1)+COUNTIF(AK153:$AK$159,AK153)-1,"") -> 2 | AE153: Transmission | AF153: =IFERROR(AVERAGEIFS('Financing Baseline'!$P$49:$P$516, 'Financing Baseline'!$C$49:$C$516, AE153, 'Financing Baseline'!$G$49:$G$516, "Equity"),0) -> 0.14368333 | AG153: =IFERROR((SUMIFS('Financing Baseline'!$N$49:$N$516, 'Financing Baseline'!$C$49:$C$516, $AE153, 'Financing Baseline'!$G$49:$G$516, "Equity"))/$AJ153,0) -> 0.13267199 | AH153: =IFERROR(AVERAGEIFS('Financing Baseline'!$P$46:$P$513, 'Financing Baseline'!$C$46:$C$513, AE153, 'Financing Baseline'!$G$46:$G$513, "Loan"),0) -> 0.015296291 | AI153: =IFERROR(SUMIFS('Financing Baseline'!$N$49:$N$516, 'Financing Baseline'!$C$49:$C$516, AE153, 'Financing Baseline'!$G$49:$G$516, "Loan")/$AJ153,0) -> 0.86732801 | AJ153: =SUMIF('Financing Baseline'!$C$49:$C$516, AE153, 'Financing Baseline'!$N$49:$N$516) -> 1977.3709 | AK153: =IFERROR( (AF153*(AG153/(AG153+AI153)))+ (AH153*(AI153/(AG153+AI153))), "") -> 0.032329656
C154: Conc DPS (Equity) | D154: ='Financing Baseline'!B25 -> 1014.2317 | M154: Climate Funds | N154: =IFERROR(AVERAGEIFS('Financing Baseline'!$X$49:$X$516,'Financing Baseline'!$I$49:$I$516,M154,'Financing Baseline'!$G$49:$G$516,"<>"&"Equity" ), 0) -> 0.48022816 | O154: =_xlfn.RANK.EQ(N154, N$153:N$159) + COUNTIF(N$153:N154, N154) - 1 -> 3 | P154: =IF(_xlfn.XLOOKUP(R154,$O$153:$O$159,$M$153:$M$159,"")=0,"",_xlfn.XLOOKUP(R154,$O$153:$O$159,$M$153:$M$159,"")) -> Commercial Bank | Q154: =_xlfn.XLOOKUP(R154,$O$153:$O$159,$N$153:$N$159) -> 0.549836 | R154: 2 | T154: Comm_Intl | U154: =IFERROR(AVERAGEIFS('Financing Baseline'!$X$49:$X$516,'Financing Baseline'!$F$49:$F$516,T154,'Financing Baseline'!$G$49:$G$516,"<>"&"Equity"), 0) -> 0.63366061 | V154: =RANK(U154,$U$153:$U$156,1) -> 4 | W154: =IF(_xlfn.XLOOKUP(Y154,$V$153:$V$156,$T$153:$T$156,"")=0,"",_xlfn.XLOOKUP(Y154,$V$153:$V$156,$T$153:$T$156,"")) -> Conc_DPS | X154: =_xlfn.XLOOKUP(Y154,$V$153:$V$156,$U$153:$U$156) -> 0.3379696 | Y154: 2 | AD154: =IFERROR(RANK($AK154,$AK$150:$AK$159,1)+COUNTIF(AK154:$AK$159,AK154)-1,"") -> 9 | AE154: Non-Renewable | AF154: =IFERROR(AVERAGEIFS('Financing Baseline'!$P$49:$P$516, 'Financing Baseline'!$C$49:$C$516, AE154, 'Financing Baseline'!$G$49:$G$516, "Equity"),0) -> 0.099333333 | AG154: =IFERROR((SUMIFS('Financing Baseline'!$N$49:$N$516, 'Financing Baseline'!$C$49:$C$516, $AE154, 'Financing Baseline'!$G$49:$G$516, "Equity"))/$AJ154,0) -> 0.14921208 | AH154: =IFERROR(AVERAGEIFS('Financing Baseline'!$P$46:$P$513, 'Financing Baseline'!$C$46:$C$513, AE154, 'Financing Baseline'!$G$46:$G$513, "Loan"),0) -> 0.095966667 | AI154: =IFERROR(SUMIFS('Financing Baseline'!$N$49:$N$516, 'Financing Baseline'!$C$49:$C$516, AE154, 'Financing Baseline'!$G$49:$G$516, "Loan")/$AJ154,0) -> 0.85078792 | AJ154: =SUMIF('Financing Baseline'!$C$49:$C$516, AE154, 'Financing Baseline'!$N$49:$N$516) -> 304.6 | AK154: =IFERROR( (AF154*(AG154/(AG154+AI154)))+ (AH154*(AI154/(AG154+AI154))), "") -> 0.096469014
C155: Comm Intl (Equity) | D155: ='Financing Baseline'!B26 -> 853.872 | M155: Commercial Bank | N155: =IFERROR(AVERAGEIFS('Financing Baseline'!$X$49:$X$516,'Financing Baseline'!$I$49:$I$516,M155,'Financing Baseline'!$G$49:$G$516,"<>"&"Equity" ), 0) -> 0.549836 | O155: =_xlfn.RANK.EQ(N155, N$153:N$159) + COUNTIF(N$153:N155, N155) - 1 -> 2 | P155: =IF(_xlfn.XLOOKUP(R155,$O$153:$O$159,$M$153:$M$159,"")=0,"",_xlfn.XLOOKUP(R155,$O$153:$O$159,$M$153:$M$159,"")) -> Climate Funds | Q155: =_xlfn.XLOOKUP(R155,$O$153:$O$159,$N$153:$N$159) -> 0.48022816 | R155: 3 | T155: Conc_DPS | U155: =IFERROR(AVERAGEIFS('Financing Baseline'!$X$49:$X$516,'Financing Baseline'!$F$49:$F$516,T155,'Financing Baseline'!$G$49:$G$516,"<>"&"Equity"), 0) -> 0.3379696 | V155: =RANK(U155,$U$153:$U$156,1) -> 2 | W155: =IF(_xlfn.XLOOKUP(Y155,$V$153:$V$156,$T$153:$T$156,"")=0,"",_xlfn.XLOOKUP(Y155,$V$153:$V$156,$T$153:$T$156,"")) -> Comm_Dom | X155: =_xlfn.XLOOKUP(Y155,$V$153:$V$156,$U$153:$U$156) -> 0.5757569 | Y155: 3 | AD155: =IFERROR(RANK($AK155,$AK$150:$AK$159,1)+COUNTIF(AK155:$AK$159,AK155)-1,"") -> 10 | AE155: Oil | AF155: =IFERROR(AVERAGEIFS('Financing Baseline'!$P$49:$P$516, 'Financing Baseline'!$C$49:$C$516, AE155, 'Financing Baseline'!$G$49:$G$516, "Equity"),0) -> 0.185 | AG155: =IFERROR((SUMIFS('Financing Baseline'!$N$49:$N$516, 'Financing Baseline'!$C$49:$C$516, $AE155, 'Financing Baseline'!$G$49:$G$516, "Equity"))/$AJ155,0) -> 0.25 | AH155: =IFERROR(AVERAGEIFS('Financing Baseline'!$P$46:$P$513, 'Financing Baseline'!$C$46:$C$513, AE155, 'Financing Baseline'!$G$46:$G$513, "Loan"),0) -> 0.073025 | AI155: =IFERROR(SUMIFS('Financing Baseline'!$N$49:$N$516, 'Financing Baseline'!$C$49:$C$516, AE155, 'Financing Baseline'!$G$49:$G$516, "Loan")/$AJ155,0) -> 0.75 | AJ155: =SUMIF('Financing Baseline'!$C$49:$C$516, AE155, 'Financing Baseline'!$N$49:$N$516) -> 108 | AK155: =IFERROR( (AF155*(AG155/(AG155+AI155)))+ (AH155*(AI155/(AG155+AI155))), "") -> 0.10101875
C156: Comm Dom (Equity) | D156: ='Financing Baseline'!B27 -> 204.238 | M156: Foreign Government | N156: =IFERROR(AVERAGEIFS('Financing Baseline'!$X$49:$X$516,'Financing Baseline'!$I$49:$I$516,M156,'Financing Baseline'!$G$49:$G$516,"<>"&"Equity" ), 0) -> 0.093944254 | O156: =_xlfn.RANK.EQ(N156, N$153:N$159) + COUNTIF(N$153:N156, N156) - 1 -> 7 | P156: =IF(_xlfn.XLOOKUP(R156,$O$153:$O$159,$M$153:$M$159,"")=0,"",_xlfn.XLOOKUP(R156,$O$153:$O$159,$M$153:$M$159,"")) -> National Government | Q156: =_xlfn.XLOOKUP(R156,$O$153:$O$159,$N$153:$N$159) -> 0.33762497 | R156: 4 | T156: Conc_IFI | U156: =IFERROR(AVERAGEIFS('Financing Baseline'!$X$49:$X$516,'Financing Baseline'!$F$49:$F$516,T156,'Financing Baseline'!$G$49:$G$516,"<>"&"Equity"), 0) -> 0.24232832 | V156: =RANK(U156,$U$153:$U$156,1) -> 1 | W156: =IF(_xlfn.XLOOKUP(Y156,$V$153:$V$156,$T$153:$T$156,"")=0,"",_xlfn.XLOOKUP(Y156,$V$153:$V$156,$T$153:$T$156,"")) -> Comm_Intl | X156: =_xlfn.XLOOKUP(Y156,$V$153:$V$156,$U$153:$U$156) -> 0.63366061 | Y156: 4 | AD156: =IFERROR(RANK($AK156,$AK$150:$AK$159,1)+COUNTIF(AK156:$AK$159,AK156)-1,"") -> 1 | AE156: Distribution | AF156: =IFERROR(AVERAGEIFS('Financing Baseline'!$P$49:$P$516, 'Financing Baseline'!$C$49:$C$516, AE156, 'Financing Baseline'!$G$49:$G$516, "Equity"),0) -> 0.092177778 | AG156: =IFERROR((SUMIFS('Financing Baseline'!$N$49:$N$516, 'Financing Baseline'!$C$49:$C$516, $AE156, 'Financing Baseline'!$G$49:$G$516, "Equity"))/$AJ156,0) -> 0.026133775 | AH156: =IFERROR(AVERAGEIFS('Financing Baseline'!$P$46:$P$513, 'Financing Baseline'!$C$46:$C$513, AE156, 'Financing Baseline'!$G$46:$G$513, "Loan"),0) -> 0.023167424 | AI156: =IFERROR(SUMIFS('Financing Baseline'!$N$49:$N$516, 'Financing Baseline'!$C$49:$C$516, AE156, 'Financing Baseline'!$G$49:$G$516, "Loan")/$AJ156,0) -> 0.97386622 | AJ156: =SUMIF('Financing Baseline'!$C$49:$C$516, AE156, 'Financing Baseline'!$N$49:$N$516) -> 1769.3578 | AK156: =IFERROR( (AF156*(AG156/(AG156+AI156)))+ (AH156*(AI156/(AG156+AI156))), "") -> 0.024970925
M157: Multilateral Agency | N157: =IFERROR(AVERAGEIFS('Financing Baseline'!$X$49:$X$516,'Financing Baseline'!$I$49:$I$516,M157,'Financing Baseline'!$G$49:$G$516,"<>"&"Equity" ), 0) -> 0.20947145 | O157: =_xlfn.RANK.EQ(N157, N$153:N$159) + COUNTIF(N$153:N157, N157) - 1 -> 6 | P157: =IF(_xlfn.XLOOKUP(R157,$O$153:$O$159,$M$153:$M$159,"")=0,"",_xlfn.XLOOKUP(R157,$O$153:$O$159,$M$153:$M$159,"")) -> Bilateral Agency | Q157: =_xlfn.XLOOKUP(R157,$O$153:$O$159,$N$153:$N$159) -> 0.25680087 | R157: 5 | AD157: =IFERROR(RANK($AK157,$AK$150:$AK$159,1)+COUNTIF(AK157:$AK$159,AK157)-1,"") -> 5 | AE157: Wind | AF157: =IFERROR(AVERAGEIFS('Financing Baseline'!$P$49:$P$516, 'Financing Baseline'!$C$49:$C$516, AE157, 'Financing Baseline'!$G$49:$G$516, "Equity"),0) -> 0.15333333 | AG157: =IFERROR((SUMIFS('Financing Baseline'!$N$49:$N$516, 'Financing Baseline'!$C$49:$C$516, $AE157, 'Financing Baseline'!$G$49:$G$516, "Equity"))/$AJ157,0) -> 0.20041532 | AH157: =IFERROR(AVERAGEIFS('Financing Baseline'!$P$46:$P$513, 'Financing Baseline'!$C$46:$C$513, AE157, 'Financing Baseline'!$G$46:$G$513, "Loan"),0) -> 0.032505911 | AI157: =IFERROR(SUMIFS('Financing Baseline'!$N$49:$N$516, 'Financing Baseline'!$C$49:$C$516, AE157, 'Financing Baseline'!$G$49:$G$516, "Loan")/$AJ157,0) -> 0.79958468 | AJ157: =SUMIF('Financing Baseline'!$C$49:$C$516, AE157, 'Financing Baseline'!$N$49:$N$516) -> 1165.38 | AK157: =IFERROR( (AF157*(AG157/(AG157+AI157)))+ (AH157*(AI157/(AG157+AI157))), "") -> 0.056721577
M158: National Government | N158: =IFERROR(AVERAGEIFS('Financing Baseline'!$X$49:$X$516,'Financing Baseline'!$I$49:$I$516,M158,'Financing Baseline'!$G$49:$G$516,"<>"&"Equity" ), 0) -> 0.33762497 | O158: =_xlfn.RANK.EQ(N158, N$153:N$159) + COUNTIF(N$153:N158, N158) - 1 -> 4 | P158: =IF(_xlfn.XLOOKUP(R158,$O$153:$O$159,$M$153:$M$159,"")=0,"",_xlfn.XLOOKUP(R158,$O$153:$O$159,$M$153:$M$159,"")) -> Multilateral Agency | Q158: =_xlfn.XLOOKUP(R158,$O$153:$O$159,$N$153:$N$159) -> 0.20947145 | R158: 6 | AD158: =IFERROR(RANK($AK158,$AK$150:$AK$159,1)+COUNTIF(AK158:$AK$159,AK158)-1,"") -> 4 | AE158: Hydro | AF158: =IFERROR(AVERAGEIFS('Financing Baseline'!$P$49:$P$516, 'Financing Baseline'!$C$49:$C$516, AE158, 'Financing Baseline'!$G$49:$G$516, "Equity"),0) -> 0.053 | AG158: =IFERROR((SUMIFS('Financing Baseline'!$N$49:$N$516, 'Financing Baseline'!$C$49:$C$516, $AE158, 'Financing Baseline'!$G$49:$G$516, "Equity"))/$AJ158,0) -> 0.35747664 | AH158: =IFERROR(AVERAGEIFS('Financing Baseline'!$P$46:$P$513, 'Financing Baseline'!$C$46:$C$513, AE158, 'Financing Baseline'!$G$46:$G$513, "Loan"),0) -> 0.05225 | AI158: =IFERROR(SUMIFS('Financing Baseline'!$N$49:$N$516, 'Financing Baseline'!$C$49:$C$516, AE158, 'Financing Baseline'!$G$49:$G$516, "Loan")/$AJ158,0) -> 0.64252336 | AJ158: =SUMIF('Financing Baseline'!$C$49:$C$516, AE158, 'Financing Baseline'!$N$49:$N$516) -> 85.6 | AK158: =IFERROR( (AF158*(AG158/(AG158+AI158)))+ (AH158*(AI158/(AG158+AI158))), "") -> 0.052518107
M159: Private Equity Fund | N159: =IFERROR(AVERAGEIFS('Financing Baseline'!$X$49:$X$516,'Financing Baseline'!$I$49:$I$516,M159,'Financing Baseline'!$G$49:$G$516,"<>"&"Equity" ), 0) -> 1 | O159: =_xlfn.RANK.EQ(N159, N$153:N$159) + COUNTIF(N$153:N159, N159) - 1 -> 1 | P159: =IF(_xlfn.XLOOKUP(R159,$O$153:$O$159,$M$153:$M$159,"")=0,"",_xlfn.XLOOKUP(R159,$O$153:$O$159,$M$153:$M$159,"")) -> Foreign Government | Q159: =_xlfn.XLOOKUP(R159,$O$153:$O$159,$N$153:$N$159) -> 0.093944254 | R159: 7 | AD159: =IFERROR(RANK($AK159,$AK$150:$AK$159,1)+COUNTIF(AK159:$AK$159,AK159)-1,"") -> 6 | AE159: Battery | AF159: =IFERROR(AVERAGEIFS('Financing Baseline'!$P$49:$P$516, 'Financing Baseline'!$C$49:$C$516, AE159, 'Financing Baseline'!$G$49:$G$516, "Equity"),0) -> 0.067333333 | AG159: =IFERROR((SUMIFS('Financing Baseline'!$N$49:$N$516, 'Financing Baseline'!$C$49:$C$516, $AE159, 'Financing Baseline'!$G$49:$G$516, "Equity"))/$AJ159,0) -> 1 | AH159: =IFERROR(AVERAGEIFS('Financing Baseline'!$P$46:$P$513, 'Financing Baseline'!$C$46:$C$513, AE159, 'Financing Baseline'!$G$46:$G$513, "Loan"),0) -> 0 | AI159: =IFERROR(SUMIFS('Financing Baseline'!$N$49:$N$516, 'Financing Baseline'!$C$49:$C$516, AE159, 'Financing Baseline'!$G$49:$G$516, "Loan")/$AJ159,0) -> 0 | AJ159: =SUMIF('Financing Baseline'!$C$49:$C$516, AE159, 'Financing Baseline'!$N$49:$N$516) -> 150 | AK159: =IFERROR( (AF159*(AG159/(AG159+AI159)))+ (AH159*(AI159/(AG159+AI159))), "") -> 0.067333333
AF160: RANKED
AE161: Technology | AF161: IRR | AG161: Share of Equity | AH161: Interest Rate | AI161: Share of Debt | AJ161: Volume of Finance | AK161: WACC
AD162: 1 | AE162: =IFERROR(VLOOKUP($AD162,$AD$150:$AK$159,2,FALSE),"") -> Distribution | AF162: =IFERROR(VLOOKUP($AD162,$AD$150:$AK$159,3,FALSE),"-") -> 0.092177778 | AG162: =IFERROR(VLOOKUP($AD162,$AD$150:$AK$159,4,FALSE),"-") -> 0.026133775 | AH162: =IFERROR(VLOOKUP($AD162,$AD$150:$AK$159,5,FALSE),"-") -> 0.023167424 | AI162: =IFERROR(VLOOKUP($AD162,$AD$150:$AK$159,6,FALSE),"-") -> 0.97386622 | AJ162: =IFERROR(VLOOKUP($AD162,$AD$150:$AK$159,7,FALSE),"-") -> 1769.3578 | AK162: =IFERROR(VLOOKUP($AD162,$AD$150:$AK$159,8,FALSE),"-") -> 0.024970925
AD163: 2 | AE163: =IFERROR(VLOOKUP($AD163,$AD$150:$AK$159,2,FALSE),"") -> Transmission | AF163: =IFERROR(VLOOKUP($AD163,$AD$150:$AK$159,3,FALSE),"-") -> 0.14368333 | AG163: =IFERROR(VLOOKUP($AD163,$AD$150:$AK$159,4,FALSE),"-") -> 0.13267199 | AH163: =IFERROR(VLOOKUP($AD163,$AD$150:$AK$159,5,FALSE),"-") -> 0.015296291 | AI163: =IFERROR(VLOOKUP($AD163,$AD$150:$AK$159,6,FALSE),"-") -> 0.86732801 | AJ163: =IFERROR(VLOOKUP($AD163,$AD$150:$AK$159,7,FALSE),"-") -> 1977.3709 | AK163: =IFERROR(VLOOKUP($AD163,$AD$150:$AK$159,8,FALSE),"-") -> 0.032329656
AD164: 3 | AE164: =IFERROR(VLOOKUP($AD164,$AD$150:$AK$159,2,FALSE),"") -> Solar | AF164: =IFERROR(VLOOKUP($AD164,$AD$150:$AK$159,3,FALSE),"-") -> 0.053 | AG164: =IFERROR(VLOOKUP($AD164,$AD$150:$AK$159,4,FALSE),"-") -> 0.25080298 | AH164: =IFERROR(VLOOKUP($AD164,$AD$150:$AK$159,5,FALSE),"-") -> 0.036277944 | AI164: =IFERROR(VLOOKUP($AD164,$AD$150:$AK$159,6,FALSE),"-") -> 0.74919702 | AJ164: =IFERROR(VLOOKUP($AD164,$AD$150:$AK$159,7,FALSE),"-") -> 783.025 | AK164: =IFERROR(VLOOKUP($AD164,$AD$150:$AK$159,8,FALSE),"-") -> 0.040471885
AD165: 4 | AE165: =IFERROR(VLOOKUP($AD165,$AD$150:$AK$159,2,FALSE),"") -> Hydro | AF165: =IFERROR(VLOOKUP($AD165,$AD$150:$AK$159,3,FALSE),"-") -> 0.053 | AG165: =IFERROR(VLOOKUP($AD165,$AD$150:$AK$159,4,FALSE),"-") -> 0.35747664 | AH165: =IFERROR(VLOOKUP($AD165,$AD$150:$AK$159,5,FALSE),"-") -> 0.05225 | AI165: =IFERROR(VLOOKUP($AD165,$AD$150:$AK$159,6,FALSE),"-") -> 0.64252336 | AJ165: =IFERROR(VLOOKUP($AD165,$AD$150:$AK$159,7,FALSE),"-") -> 85.6 | AK165: =IFERROR(VLOOKUP($AD165,$AD$150:$AK$159,8,FALSE),"-") -> 0.052518107
AD166: 5 | AE166: =IFERROR(VLOOKUP($AD166,$AD$150:$AK$159,2,FALSE),"") -> Wind | AF166: =IFERROR(VLOOKUP($AD166,$AD$150:$AK$159,3,FALSE),"-") -> 0.15333333 | AG166: =IFERROR(VLOOKUP($AD166,$AD$150:$AK$159,4,FALSE),"-") -> 0.20041532 | AH166: =IFERROR(VLOOKUP($AD166,$AD$150:$AK$159,5,FALSE),"-") -> 0.032505911 | AI166: =IFERROR(VLOOKUP($AD166,$AD$150:$AK$159,6,FALSE),"-") -> 0.79958468 | AJ166: =IFERROR(VLOOKUP($AD166,$AD$150:$AK$159,7,FALSE),"-") -> 1165.38 | AK166: =IFERROR(VLOOKUP($AD166,$AD$150:$AK$159,8,FALSE),"-") -> 0.056721577
AD167: 6 | AE167: =IFERROR(VLOOKUP($AD167,$AD$150:$AK$159,2,FALSE),"") -> Battery | AF167: =IFERROR(VLOOKUP($AD167,$AD$150:$AK$159,3,FALSE),"-") -> 0.067333333 | AG167: =IFERROR(VLOOKUP($AD167,$AD$150:$AK$159,4,FALSE),"-") -> 1 | AH167: =IFERROR(VLOOKUP($AD167,$AD$150:$AK$159,5,FALSE),"-") -> 0 | AI167: =IFERROR(VLOOKUP($AD167,$AD$150:$AK$159,6,FALSE),"-") -> 0 | AJ167: =IFERROR(VLOOKUP($AD167,$AD$150:$AK$159,7,FALSE),"-") -> 150 | AK167: =IFERROR(VLOOKUP($AD167,$AD$150:$AK$159,8,FALSE),"-") -> 0.067333333
AD168: 7 | AE168: =IFERROR(VLOOKUP($AD168,$AD$150:$AK$159,2,FALSE),"") -> Geothermal | AF168: =IFERROR(VLOOKUP($AD168,$AD$150:$AK$159,3,FALSE),"-") -> 0.18721296 | AG168: =IFERROR(VLOOKUP($AD168,$AD$150:$AK$159,4,FALSE),"-") -> 0.25579778 | AH168: =IFERROR(VLOOKUP($AD168,$AD$150:$AK$159,5,FALSE),"-") -> 0.032753269 | AI168: =IFERROR(VLOOKUP($AD168,$AD$150:$AK$159,6,FALSE),"-") -> 0.74420222 | AJ168: =IFERROR(VLOOKUP($AD168,$AD$150:$AK$159,7,FALSE),"-") -> 4410.8409 | AK168: =IFERROR(VLOOKUP($AD168,$AD$150:$AK$159,8,FALSE),"-") -> 0.072263716
AD169: 8 | AE169: =IFERROR(VLOOKUP($AD169,$AD$150:$AK$159,2,FALSE),"") -> Biomass | AF169: =IFERROR(VLOOKUP($AD169,$AD$150:$AK$159,3,FALSE),"-") -> 0.12 | AG169: =IFERROR(VLOOKUP($AD169,$AD$150:$AK$159,4,FALSE),"-") -> 0.38427948 | AH169: =IFERROR(VLOOKUP($AD169,$AD$150:$AK$159,5,FALSE),"-") -> 0.06152105 | AI169: =IFERROR(VLOOKUP($AD169,$AD$150:$AK$159,6,FALSE),"-") -> 0.61572052 | AJ169: =IFERROR(VLOOKUP($AD169,$AD$150:$AK$159,7,FALSE),"-") -> 229 | AK169: =IFERROR(VLOOKUP($AD169,$AD$150:$AK$159,8,FALSE),"-") -> 0.08399331
AD170: 9 | AE170: =IFERROR(VLOOKUP($AD170,$AD$150:$AK$159,2,FALSE),"") -> Non-Renewable | AF170: =IFERROR(VLOOKUP($AD170,$AD$150:$AK$159,3,FALSE),"-") -> 0.099333333 | AG170: =IFERROR(VLOOKUP($AD170,$AD$150:$AK$159,4,FALSE),"-") -> 0.14921208 | AH170: =IFERROR(VLOOKUP($AD170,$AD$150:$AK$159,5,FALSE),"-") -> 0.095966667 | AI170: =IFERROR(VLOOKUP($AD170,$AD$150:$AK$159,6,FALSE),"-") -> 0.85078792 | AJ170: =IFERROR(VLOOKUP($AD170,$AD$150:$AK$159,7,FALSE),"-") -> 304.6 | AK170: =IFERROR(VLOOKUP($AD170,$AD$150:$AK$159,8,FALSE),"-") -> 0.096469014
AD171: 10 | AE171: =IFERROR(VLOOKUP($AD171,$AD$150:$AK$159,2,FALSE),"") -> Oil | AF171: =IFERROR(VLOOKUP($AD171,$AD$150:$AK$159,3,FALSE),"-") -> 0.185 | AG171: =IFERROR(VLOOKUP($AD171,$AD$150:$AK$159,4,FALSE),"-") -> 0.25 | AH171: =IFERROR(VLOOKUP($AD171,$AD$150:$AK$159,5,FALSE),"-") -> 0.073025 | AI171: =IFERROR(VLOOKUP($AD171,$AD$150:$AK$159,6,FALSE),"-") -> 0.75 | AJ171: =IFERROR(VLOOKUP($AD171,$AD$150:$AK$159,7,FALSE),"-") -> 108 | AK171: =IFERROR(VLOOKUP($AD171,$AD$150:$AK$159,8,FALSE),"-") -> 0.10101875
AG173: Technology | AH173: Loan | AI173: Equity | AK173: Debt | AL173: Equity
B174: Terms of Debt Finance | M174: Source | N174: Loan | O174: Equity | Q174: Debt | R174: Equity | U174: Source | V174: Loan | W174: Equity | Y174: Debt | Z174: Equity | AE174: 1 | AF174: =_xlfn.RANK.EQ(AH174, AH$174:AH$183) + COUNTIF(AH$174:AH174, AH174) - 1 -> 7 | AG174: {=IF(_xlfn.UNIQUE('Financing Baseline'!$C$49:$C$516)=0,"",_xlfn.UNIQUE('Financing Baseline'!$C$49:$C$516))} -> Geothermal | AH174: =IFERROR(SUMIFS('Financing Baseline'!$N$49:$N$516,'Financing Baseline'!$C$49:$C$516,'Visualisation Dashboard'!$AG174,'Financing Baseline'!$G$49:$G$516,'Visualisation Dashboard'!AH$173)/ SUMIFS('Financing Baseline'!$N$49:$N$516,'Financing Baseline'!$C$49:$C$516,'Visualisation Dashboard'!$AG174),"") -> 0.74420222 | AI174: =IFERROR(SUMIFS('Financing Baseline'!$N$49:$N$516,'Financing Baseline'!$C$49:$C$516,'Visualisation Dashboard'!$AG174,'Financing Baseline'!$G$49:$G$516,'Visualisation Dashboard'!AI$173)/ SUMIFS('Financing Baseline'!$N$49:$N$516,'Financing Baseline'!$C$49:$C$516,'Visualisation Dashboard'!$AG174),"") -> 0.25579778 | AJ174: =IF(_xlfn.XLOOKUP(AE174,$AF$174:$AF$183,$AG$174:$AG$183,"")=0,"",_xlfn.XLOOKUP(AE174,$AF$174:$AF$183,$AG$174:$AG$183,"")) -> Distribution | AK174: =_xlfn.XLOOKUP(AE174,$AF$174:$AF$183,$AH$174:$AH$183) -> 0.97386622 | AL174: =_xlfn.XLOOKUP(AE174,$AF$174:$AF$183,$AI$174:$AI$183) -> 0.026133775
K175: 1 | L175: =_xlfn.RANK.EQ(N175, N$175:N$181) + COUNTIF(N$175:N175, N175) - 1 -> 4 | M175: {=_xlfn._xlws.FILTER(_xlfn._xlws.SORT(_xlfn.UNIQUE('Financing Baseline'!$I$49:$I$516)),_xlfn._xlws.SORT(_xlfn.UNIQUE('Financing Baseline'!$I$49:$I$516))<>0)} -> Bilateral Agency | N175: =IFERROR(SUMIFS('Financing Baseline'!$N$49:$N$516,'Financing Baseline'!$I$49:$I$516,'Visualisation Dashboard'!$M175,'Financing Baseline'!$G$49:$G$516,'Visualisation Dashboard'!N$174)/ SUMIFS('Financing Baseline'!$N$49:$N$516,'Financing Baseline'!$I$49:$I$516,'Visualisation Dashboard'!$M175),"") -> 0.97833371 | O175: =IFERROR(SUMIFS('Financing Baseline'!$N$49:$N$516,'Financing Baseline'!$I$49:$I$516,'Visualisation Dashboard'!$M175,'Financing Baseline'!$G$49:$G$516,'Visualisation Dashboard'!O$174)/ SUMIFS('Financing Baseline'!$N$49:$N$516,'Financing Baseline'!$I$49:$I$516,'Visualisation Dashboard'!$M175),"") -> 0.02166629 | P175: =IF(_xlfn.XLOOKUP(K175,$L$175:$L$181,$M$175:$M$181,"")=0,"",_xlfn.XLOOKUP(K175,$L$175:$L$181,$M$175:$M$181,"")) -> Commercial Bank | Q175: =_xlfn.XLOOKUP(K175,$L$175:$L$181,$N$175:$N$181) -> 1 | R175: =_xlfn.XLOOKUP(K175,$L$175:$L$181,$O$175:$O$181) -> 0 | S175: 1 | T175: =_xlfn.RANK.EQ(V175, V$175:V$178) + COUNTIF(V$175:V175, V175) - 1 -> 3 | U175: {=_xlfn._xlws.FILTER(_xlfn._xlws.SORT(_xlfn.UNIQUE('Financing Baseline'!$F$49:$F$516)),_xlfn._xlws.SORT(_xlfn.UNIQUE('Financing Baseline'!$F$49:$F$516))<>0)} -> Comm_Dom | V175: =IFERROR(SUMIFS('Financing Baseline'!$N$49:$N$516,'Financing Baseline'!$F$49:$F$516,'Visualisation Dashboard'!$U175,'Financing Baseline'!$G$49:$G$516,'Visualisation Dashboard'!V$174)/ SUMIFS('Financing Baseline'!$N$49:$N$516,'Financing Baseline'!$F$49:$F$516,'Visualisation Dashboard'!$U175),"") -> 0.20106557 | W175: =IFERROR(SUMIFS('Financing Baseline'!$N$49:$N$516,'Financing Baseline'!$F$49:$F$516,'Visualisation Dashboard'!$U175,'Financing Baseline'!$G$49:$G$516,'Visualisation Dashboard'!W$174)/ SUMIFS('Financing Baseline'!$N$49:$N$516,'Financing Baseline'!$F$49:$F$516,'Visualisation Dashboard'!$U175),"") -> 0.79893443 | X175: =IF(_xlfn.XLOOKUP(S175,$T$175:$T$178,$U$175:$U$178,"")=0,"",_xlfn.XLOOKUP(S175,$T$175:$T$178,$U$175:$U$178,"")) -> Conc_IFI | Y175: =_xlfn.XLOOKUP(S175,$T$175:$T$178,$V$175:$V$178) -> 0.98341154 | Z175: =_xlfn.XLOOKUP(S175,$T$175:$T$178,$W$175:$W$178) -> 0.016588463 | AE175: 2 | AF175: =_xlfn.RANK.EQ(AH175, AH$174:AH$183) + COUNTIF(AH$174:AH175, AH175) - 1 -> 6 | AG175: Solar | AH175: =IFERROR(SUMIFS('Financing Baseline'!$N$49:$N$516,'Financing Baseline'!$C$49:$C$516,'Visualisation Dashboard'!$AG175,'Financing Baseline'!$G$49:$G$516,'Visualisation Dashboard'!AH$173)/ SUMIFS('Financing Baseline'!$N$49:$N$516,'Financing Baseline'!$C$49:$C$516,'Visualisation Dashboard'!$AG175),"") -> 0.74919702 | AI175: =IFERROR(SUMIFS('Financing Baseline'!$N$49:$N$516,'Financing Baseline'!$C$49:$C$516,'Visualisation Dashboard'!$AG175,'Financing Baseline'!$G$49:$G$516,'Visualisation Dashboard'!AI$173)/ SUMIFS('Financing Baseline'!$N$49:$N$516,'Financing Baseline'!$C$49:$C$516,'Visualisation Dashboard'!$AG175),"") -> 0.25080298 | AJ175: =IF(_xlfn.XLOOKUP(AE175,$AF$174:$AF$183,$AG$174:$AG$183,"")=0,"",_xlfn.XLOOKUP(AE175,$AF$174:$AF$183,$AG$174:$AG$183,"")) -> Transmission | AK175: =_xlfn.XLOOKUP(AE175,$AF$174:$AF$183,$AH$174:$AH$183) -> 0.86732801 | AL175: =_xlfn.XLOOKUP(AE175,$AF$174:$AF$183,$AI$174:$AI$183) -> 0.13267199
D176: Conc Intl | E176: Conc Dom | F176: Comm Dom | G176: Comm Intl | H176: Average | K176: 2 | L176: =_xlfn.RANK.EQ(N176, N$175:N$181) + COUNTIF(N$175:N176, N176) - 1 -> 5 | M176: Climate Funds | N176: =IFERROR(SUMIFS('Financing Baseline'!$N$49:$N$516,'Financing Baseline'!$I$49:$I$516,'Visualisation Dashboard'!$M176,'Financing Baseline'!$G$49:$G$516,'Visualisation Dashboard'!N$174)/ SUMIFS('Financing Baseline'!$N$49:$N$516,'Financing Baseline'!$I$49:$I$516,'Visualisation Dashboard'!$M176),"") -> 0.79122801 | O176: =IFERROR(SUMIFS('Financing Baseline'!$N$49:$N$516,'Financing Baseline'!$I$49:$I$516,'Visualisation Dashboard'!$M176,'Financing Baseline'!$G$49:$G$516,'Visualisation Dashboard'!O$174)/ SUMIFS('Financing Baseline'!$N$49:$N$516,'Financing Baseline'!$I$49:$I$516,'Visualisation Dashboard'!$M176),"") -> 0.20877199 | P176: =IF(_xlfn.XLOOKUP(K176,$L$175:$L$181,$M$175:$M$181,"")=0,"",_xlfn.XLOOKUP(K176,$L$175:$L$181,$M$175:$M$181,"")) -> Foreign Government | Q176: =_xlfn.XLOOKUP(K176,$L$175:$L$181,$N$175:$N$181) -> 1 | R176: =_xlfn.XLOOKUP(K176,$L$175:$L$181,$O$175:$O$181) -> 0 | S176: 2 | T176: =_xlfn.RANK.EQ(V176, V$175:V$178) + COUNTIF(V$175:V176, V176) - 1 -> 2 | U176: Comm_Intl | V176: =IFERROR(SUMIFS('Financing Baseline'!$N$49:$N$516,'Financing Baseline'!$F$49:$F$516,'Visualisation Dashboard'!$U176,'Financing Baseline'!$G$49:$G$516,'Visualisation Dashboard'!V$174)/ SUMIFS('Financing Baseline'!$N$49:$N$516,'Financing Baseline'!$F$49:$F$516,'Visualisation Dashboard'!$U176),"") -> 0.36177808 | W176: =IFERROR(SUMIFS('Financing Baseline'!$N$49:$N$516,'Financing Baseline'!$F$49:$F$516,'Visualisation Dashboard'!$U176,'Financing Baseline'!$G$49:$G$516,'Visualisation Dashboard'!W$174)/ SUMIFS('Financing Baseline'!$N$49:$N$516,'Financing Baseline'!$F$49:$F$516,'Visualisation Dashboard'!$U176),"") -> 0.63822192 | X176: =IF(_xlfn.XLOOKUP(S176,$T$175:$T$178,$U$175:$U$178,"")=0,"",_xlfn.XLOOKUP(S176,$T$175:$T$178,$U$175:$U$178,"")) -> Comm_Intl | Y176: =_xlfn.XLOOKUP(S176,$T$175:$T$178,$V$175:$V$178) -> 0.36177808 | Z176: =_xlfn.XLOOKUP(S176,$T$175:$T$178,$W$175:$W$178) -> 0.63822192 | AE176: 3 | AF176: =_xlfn.RANK.EQ(AH176, AH$174:AH$183) + COUNTIF(AH$174:AH176, AH176) - 1 -> 9 | AG176: Biomass | AH176: =IFERROR(SUMIFS('Financing Baseline'!$N$49:$N$516,'Financing Baseline'!$C$49:$C$516,'Visualisation Dashboard'!$AG176,'Financing Baseline'!$G$49:$G$516,'Visualisation Dashboard'!AH$173)/ SUMIFS('Financing Baseline'!$N$49:$N$516,'Financing Baseline'!$C$49:$C$516,'Visualisation Dashboard'!$AG176),"") -> 0.61572052 | AI176: =IFERROR(SUMIFS('Financing Baseline'!$N$49:$N$516,'Financing Baseline'!$C$49:$C$516,'Visualisation Dashboard'!$AG176,'Financing Baseline'!$G$49:$G$516,'Visualisation Dashboard'!AI$173)/ SUMIFS('Financing Baseline'!$N$49:$N$516,'Financing Baseline'!$C$49:$C$516,'Visualisation Dashboard'!$AG176),"") -> 0.38427948 | AJ176: =IF(_xlfn.XLOOKUP(AE176,$AF$174:$AF$183,$AG$174:$AG$183,"")=0,"",_xlfn.XLOOKUP(AE176,$AF$174:$AF$183,$AG$174:$AG$183,"")) -> Non-Renewable | AK176: =_xlfn.XLOOKUP(AE176,$AF$174:$AF$183,$AH$174:$AH$183) -> 0.85078792 | AL176: =_xlfn.XLOOKUP(AE176,$AF$174:$AF$183,$AI$174:$AI$183) -> 0.14921208
B177: Average Interest Rate (%) | D177: =IFERROR(AVERAGEIFS('Financing Baseline'!P49:P230, 'Financing Baseline'!F49:F230, "Conc_IFI", 'Financing Baseline'!G49:G230, "Loan"), 0) -> 0.027410893 | E177: =IFERROR(AVERAGEIFS('Financing Baseline'!P49:P230, 'Financing Baseline'!F49:F230, "Conc_DPS", 'Financing Baseline'!G49:G230, "Loan"), 0) -> 0.024758333 | F177: =IFERROR(AVERAGEIFS('Financing Baseline'!P49:P230, 'Financing Baseline'!F49:F230, "Comm_Dom", 'Financing Baseline'!G49:G230, "Loan"), 0) -> 0.13016488 | G177: =IFERROR(AVERAGEIFS('Financing Baseline'!P49:P230, 'Financing Baseline'!F49:F230, "Comm_Intl", 'Financing Baseline'!G49:G230, "Loan"), 0) -> 0.090307141 | H177: =IFERROR(SUMPRODUCT($D$181:$G$181,D177:G177)/SUM($D$181:$G$181), 0) -> 0.031419664 | K177: 3 | L177: =_xlfn.RANK.EQ(N177, N$175:N$181) + COUNTIF(N$175:N177, N177) - 1 -> 1 | M177: Commercial Bank | N177: =IFERROR(SUMIFS('Financing Baseline'!$N$49:$N$516,'Financing Baseline'!$I$49:$I$516,'Visualisation Dashboard'!$M177,'Financing Baseline'!$G$49:$G$516,'Visualisation Dashboard'!N$174)/ SUMIFS('Financing Baseline'!$N$49:$N$516,'Financing Baseline'!$I$49:$I$516,'Visualisation Dashboard'!$M177),"") -> 1 | O177: =IFERROR(SUMIFS('Financing Baseline'!$N$49:$N$516,'Financing Baseline'!$I$49:$I$516,'Visualisation Dashboard'!$M177,'Financing Baseline'!$G$49:$G$516,'Visualisation Dashboard'!O$174)/ SUMIFS('Financing Baseline'!$N$49:$N$516,'Financing Baseline'!$I$49:$I$516,'Visualisation Dashboard'!$M177),"") -> 0 | P177: =IF(_xlfn.XLOOKUP(K177,$L$175:$L$181,$M$175:$M$181,"")=0,"",_xlfn.XLOOKUP(K177,$L$175:$L$181,$M$175:$M$181,"")) -> Multilateral Agency | Q177: =_xlfn.XLOOKUP(K177,$L$175:$L$181,$N$175:$N$181) -> 0.98859528 | R177: =_xlfn.XLOOKUP(K177,$L$175:$L$181,$O$175:$O$181) -> 0.011404724 | S177: 3 | T177: =_xlfn.RANK.EQ(V177, V$175:V$178) + COUNTIF(V$175:V177, V177) - 1 -> 4 | U177: Conc_DPS | V177: =IFERROR(SUMIFS('Financing Baseline'!$N$49:$N$516,'Financing Baseline'!$F$49:$F$516,'Visualisation Dashboard'!$U177,'Financing Baseline'!$G$49:$G$516,'Visualisation Dashboard'!V$174)/ SUMIFS('Financing Baseline'!$N$49:$N$516,'Financing Baseline'!$F$49:$F$516,'Visualisation Dashboard'!$U177),"") -> 0.16880677 | W177: =IFERROR(SUMIFS('Financing Baseline'!$N$49:$N$516,'Financing Baseline'!$F$49:$F$516,'Visualisation Dashboard'!$U177,'Financing Baseline'!$G$49:$G$516,'Visualisation Dashboard'!W$174)/ SUMIFS('Financing Baseline'!$N$49:$N$516,'Financing Baseline'!$F$49:$F$516,'Visualisation Dashboard'!$U177),"") -> 0.83119323 | X177: =IF(_xlfn.XLOOKUP(S177,$T$175:$T$178,$U$175:$U$178,"")=0,"",_xlfn.XLOOKUP(S177,$T$175:$T$178,$U$175:$U$178,"")) -> Comm_Dom | Y177: =_xlfn.XLOOKUP(S177,$T$175:$T$178,$V$175:$V$178) -> 0.20106557 | Z177: =_xlfn.XLOOKUP(S177,$T$175:$T$178,$W$175:$W$178) -> 0.79893443 | AE177: 4 | AF177: =_xlfn.RANK.EQ(AH177, AH$174:AH$183) + COUNTIF(AH$174:AH177, AH177) - 1 -> 2 | AG177: Transmission | AH177: =IFERROR(SUMIFS('Financing Baseline'!$N$49:$N$516,'Financing Baseline'!$C$49:$C$516,'Visualisation Dashboard'!$AG177,'Financing Baseline'!$G$49:$G$516,'Visualisation Dashboard'!AH$173)/ SUMIFS('Financing Baseline'!$N$49:$N$516,'Financing Baseline'!$C$49:$C$516,'Visualisation Dashboard'!$AG177),"") -> 0.86732801 | AI177: =IFERROR(SUMIFS('Financing Baseline'!$N$49:$N$516,'Financing Baseline'!$C$49:$C$516,'Visualisation Dashboard'!$AG177,'Financing Baseline'!$G$49:$G$516,'Visualisation Dashboard'!AI$173)/ SUMIFS('Financing Baseline'!$N$49:$N$516,'Financing Baseline'!$C$49:$C$516,'Visualisation Dashboard'!$AG177),"") -> 0.13267199 | AJ177: =IF(_xlfn.XLOOKUP(AE177,$AF$174:$AF$183,$AG$174:$AG$183,"")=0,"",_xlfn.XLOOKUP(AE177,$AF$174:$AF$183,$AG$174:$AG$183,"")) -> Wind | AK177: =_xlfn.XLOOKUP(AE177,$AF$174:$AF$183,$AH$174:$AH$183) -> 0.79958468 | AL177: =_xlfn.XLOOKUP(AE177,$AF$174:$AF$183,$AI$174:$AI$183) -> 0.20041532
B178: Average Grace Period (years) | D178: =IFERROR(AVERAGEIFS('Financing Baseline'!S49:S230, 'Financing Baseline'!F49:F230, "Conc_IFI", 'Financing Baseline'!G49:G230, "Loan"), 0) -> 6.2217904 | E178: =IFERROR(AVERAGEIFS('Financing Baseline'!S49:S230, 'Financing Baseline'!F49:F230, "Conc_DPS", 'Financing Baseline'!G49:G230, "Loan"), 0) -> 5.9166667 | F178: =IFERROR(AVERAGEIFS('Financing Baseline'!S49:S230, 'Financing Baseline'!F49:F230, "Comm_Dom", 'Financing Baseline'!G49:G230, "Loan"), 0) -> 5.75 | G178: =IFERROR(AVERAGEIFS('Financing Baseline'!S49:S230, 'Financing Baseline'!F49:F230, "Comm_Intl", 'Financing Baseline'!G49:G230, "Loan"), 0) -> 2.2727273 | H178: =IFERROR(SUMPRODUCT($D$181:$G$181,D178:G178)/SUM($D$181:$G$181), 0) -> 5.9940464 | K178: 4 | L178: =_xlfn.RANK.EQ(N178, N$175:N$181) + COUNTIF(N$175:N178, N178) - 1 -> 2 | M178: Foreign Government | N178: =IFERROR(SUMIFS('Financing Baseline'!$N$49:$N$516,'Financing Baseline'!$I$49:$I$516,'Visualisation Dashboard'!$M178,'Financing Baseline'!$G$49:$G$516,'Visualisation Dashboard'!N$174)/ SUMIFS('Financing Baseline'!$N$49:$N$516,'Financing Baseline'!$I$49:$I$516,'Visualisation Dashboard'!$M178),"") -> 1 | O178: =IFERROR(SUMIFS('Financing Baseline'!$N$49:$N$516,'Financing Baseline'!$I$49:$I$516,'Visualisation Dashboard'!$M178,'Financing Baseline'!$G$49:$G$516,'Visualisation Dashboard'!O$174)/ SUMIFS('Financing Baseline'!$N$49:$N$516,'Financing Baseline'!$I$49:$I$516,'Visualisation Dashboard'!$M178),"") -> 0 | P178: =IF(_xlfn.XLOOKUP(K178,$L$175:$L$181,$M$175:$M$181,"")=0,"",_xlfn.XLOOKUP(K178,$L$175:$L$181,$M$175:$M$181,"")) -> Bilateral Agency | Q178: =_xlfn.XLOOKUP(K178,$L$175:$L$181,$N$175:$N$181) -> 0.97833371 | R178: =_xlfn.XLOOKUP(K178,$L$175:$L$181,$O$175:$O$181) -> 0.02166629 | S178: 4 | T178: =_xlfn.RANK.EQ(V178, V$175:V$178) + COUNTIF(V$175:V178, V178) - 1 -> 1 | U178: Conc_IFI | V178: =IFERROR(SUMIFS('Financing Baseline'!$N$49:$N$516,'Financing Baseline'!$F$49:$F$516,'Visualisation Dashboard'!$U178,'Financing Baseline'!$G$49:$G$516,'Visualisation Dashboard'!V$174)/ SUMIFS('Financing Baseline'!$N$49:$N$516,'Financing Baseline'!$F$49:$F$516,'Visualisation Dashboard'!$U178),"") -> 0.98341154 | W178: =IFERROR(SUMIFS('Financing Baseline'!$N$49:$N$516,'Financing Baseline'!$F$49:$F$516,'Visualisation Dashboard'!$U178,'Financing Baseline'!$G$49:$G$516,'Visualisation Dashboard'!W$174)/ SUMIFS('Financing Baseline'!$N$49:$N$516,'Financing Baseline'!$F$49:$F$516,'Visualisation Dashboard'!$U178),"") -> 0.016588463 | X178: =IF(_xlfn.XLOOKUP(S178,$T$175:$T$178,$U$175:$U$178,"")=0,"",_xlfn.XLOOKUP(S178,$T$175:$T$178,$U$175:$U$178,"")) -> Conc_DPS | Y178: =_xlfn.XLOOKUP(S178,$T$175:$T$178,$V$175:$V$178) -> 0.16880677 | Z178: =_xlfn.XLOOKUP(S178,$T$175:$T$178,$W$175:$W$178) -> 0.83119323 | AE178: 5 | AF178: =_xlfn.RANK.EQ(AH178, AH$174:AH$183) + COUNTIF(AH$174:AH178, AH178) - 1 -> 3 | AG178: Non-Renewable | AH178: =IFERROR(SUMIFS('Financing Baseline'!$N$49:$N$516,'Financing Baseline'!$C$49:$C$516,'Visualisation Dashboard'!$AG178,'Financing Baseline'!$G$49:$G$516,'Visualisation Dashboard'!AH$173)/ SUMIFS('Financing Baseline'!$N$49:$N$516,'Financing Baseline'!$C$49:$C$516,'Visualisation Dashboard'!$AG178),"") -> 0.85078792 | AI178: =IFERROR(SUMIFS('Financing Baseline'!$N$49:$N$516,'Financing Baseline'!$C$49:$C$516,'Visualisation Dashboard'!$AG178,'Financing Baseline'!$G$49:$G$516,'Visualisation Dashboard'!AI$173)/ SUMIFS('Financing Baseline'!$N$49:$N$516,'Financing Baseline'!$C$49:$C$516,'Visualisation Dashboard'!$AG178),"") -> 0.14921208 | AJ178: =IF(_xlfn.XLOOKUP(AE178,$AF$174:$AF$183,$AG$174:$AG$183,"")=0,"",_xlfn.XLOOKUP(AE178,$AF$174:$AF$183,$AG$174:$AG$183,"")) -> Oil | AK178: =_xlfn.XLOOKUP(AE178,$AF$174:$AF$183,$AH$174:$AH$183) -> 0.75 | AL178: =_xlfn.XLOOKUP(AE178,$AF$174:$AF$183,$AI$174:$AI$183) -> 0.25 | AP178: =IFERROR(VLOOKUP(#REF!,$M$187:$T$200,8,FALSE),"-") -> -
B179: Average Term of Loan (years) | D179: =IFERROR(AVERAGEIFS('Financing Baseline'!Q49:Q230, 'Financing Baseline'!F49:F230, "Conc_IFI", 'Financing Baseline'!G49:G230, "Loan"), 0) -> 24.861465 | E179: =IFERROR(AVERAGEIFS('Financing Baseline'!Q49:Q230, 'Financing Baseline'!F49:F230, "Conc_DPS", 'Financing Baseline'!G49:G230, "Loan"), 0) -> 17.883333 | F179: =IFERROR(AVERAGEIFS('Financing Baseline'!Q49:Q230, 'Financing Baseline'!F49:F230, "Comm_Dom", 'Financing Baseline'!G49:G230, "Loan"), 0) -> 17.5 | G179: =IFERROR(AVERAGEIFS('Financing Baseline'!Q49:Q230, 'Financing Baseline'!F49:F230, "Comm_Intl", 'Financing Baseline'!G49:G230, "Loan"), 0) -> 15.454545 | H179: =IFERROR(SUMPRODUCT($D$181:$G$181,D179:G179)/SUM($D$181:$G$181), 0) -> 24.135693 | K179: 5 | L179: =_xlfn.RANK.EQ(N179, N$175:N$181) + COUNTIF(N$175:N179, N179) - 1 -> 3 | M179: Multilateral Agency | N179: =IFERROR(SUMIFS('Financing Baseline'!$N$49:$N$516,'Financing Baseline'!$I$49:$I$516,'Visualisation Dashboard'!$M179,'Financing Baseline'!$G$49:$G$516,'Visualisation Dashboard'!N$174)/ SUMIFS('Financing Baseline'!$N$49:$N$516,'Financing Baseline'!$I$49:$I$516,'Visualisation Dashboard'!$M179),"") -> 0.98859528 | O179: =IFERROR(SUMIFS('Financing Baseline'!$N$49:$N$516,'Financing Baseline'!$I$49:$I$516,'Visualisation Dashboard'!$M179,'Financing Baseline'!$G$49:$G$516,'Visualisation Dashboard'!O$174)/ SUMIFS('Financing Baseline'!$N$49:$N$516,'Financing Baseline'!$I$49:$I$516,'Visualisation Dashboard'!$M179),"") -> 0.011404724 | P179: =IF(_xlfn.XLOOKUP(K179,$L$175:$L$181,$M$175:$M$181,"")=0,"",_xlfn.XLOOKUP(K179,$L$175:$L$181,$M$175:$M$181,"")) -> Climate Funds | Q179: =_xlfn.XLOOKUP(K179,$L$175:$L$181,$N$175:$N$181) -> 0.79122801 | R179: =_xlfn.XLOOKUP(K179,$L$175:$L$181,$O$175:$O$181) -> 0.20877199 | AE179: 6 | AF179: =_xlfn.RANK.EQ(AH179, AH$174:AH$183) + COUNTIF(AH$174:AH179, AH179) - 1 -> 5 | AG179: Oil | AH179: =IFERROR(SUMIFS('Financing Baseline'!$N$49:$N$516,'Financing Baseline'!$C$49:$C$516,'Visualisation Dashboard'!$AG179,'Financing Baseline'!$G$49:$G$516,'Visualisation Dashboard'!AH$173)/ SUMIFS('Financing Baseline'!$N$49:$N$516,'Financing Baseline'!$C$49:$C$516,'Visualisation Dashboard'!$AG179),"") -> 0.75 | AI179: =IFERROR(SUMIFS('Financing Baseline'!$N$49:$N$516,'Financing Baseline'!$C$49:$C$516,'Visualisation Dashboard'!$AG179,'Financing Baseline'!$G$49:$G$516,'Visualisation Dashboard'!AI$173)/ SUMIFS('Financing Baseline'!$N$49:$N$516,'Financing Baseline'!$C$49:$C$516,'Visualisation Dashboard'!$AG179),"") -> 0.25 | AJ179: =IF(_xlfn.XLOOKUP(AE179,$AF$174:$AF$183,$AG$174:$AG$183,"")=0,"",_xlfn.XLOOKUP(AE179,$AF$174:$AF$183,$AG$174:$AG$183,"")) -> Solar | AK179: =_xlfn.XLOOKUP(AE179,$AF$174:$AF$183,$AH$174:$AH$183) -> 0.74919702 | AL179: =_xlfn.XLOOKUP(AE179,$AF$174:$AF$183,$AI$174:$AI$183) -> 0.25080298
B180: Average Grant Element | D180: ='Financing Baseline'!J32 -> 0.80599981 | E180: ='Financing Baseline'!J33 -> 0.77131286 | F180: ='Financing Baseline'!J35 -> 0.2476127 | G180: ='Financing Baseline'!J34 -> 0.33896815 | H180: =IFERROR(SUMPRODUCT($D$181:$G$181,D180:G180)/SUM($D$181:$G$181), 0) -> 0.77615489 | K180: 6 | L180: =_xlfn.RANK.EQ(N180, N$175:N$181) + COUNTIF(N$175:N180, N180) - 1 -> 6 | M180: National Government | N180: =IFERROR(SUMIFS('Financing Baseline'!$N$49:$N$516,'Financing Baseline'!$I$49:$I$516,'Visualisation Dashboard'!$M180,'Financing Baseline'!$G$49:$G$516,'Visualisation Dashboard'!N$174)/ SUMIFS('Financing Baseline'!$N$49:$N$516,'Financing Baseline'!$I$49:$I$516,'Visualisation Dashboard'!$M180),"") -> 0.12179404 | O180: =IFERROR(SUMIFS('Financing Baseline'!$N$49:$N$516,'Financing Baseline'!$I$49:$I$516,'Visualisation Dashboard'!$M180,'Financing Baseline'!$G$49:$G$516,'Visualisation Dashboard'!O$174)/ SUMIFS('Financing Baseline'!$N$49:$N$516,'Financing Baseline'!$I$49:$I$516,'Visualisation Dashboard'!$M180),"") -> 0.87820596 | P180: =IF(_xlfn.XLOOKUP(K180,$L$175:$L$181,$M$175:$M$181,"")=0,"",_xlfn.XLOOKUP(K180,$L$175:$L$181,$M$175:$M$181,"")) -> National Government | Q180: =_xlfn.XLOOKUP(K180,$L$175:$L$181,$N$175:$N$181) -> 0.12179404 | R180: =_xlfn.XLOOKUP(K180,$L$175:$L$181,$O$175:$O$181) -> 0.87820596 | AE180: 7 | AF180: =_xlfn.RANK.EQ(AH180, AH$174:AH$183) + COUNTIF(AH$174:AH180, AH180) - 1 -> 1 | AG180: Distribution | AH180: =IFERROR(SUMIFS('Financing Baseline'!$N$49:$N$516,'Financing Baseline'!$C$49:$C$516,'Visualisation Dashboard'!$AG180,'Financing Baseline'!$G$49:$G$516,'Visualisation Dashboard'!AH$173)/ SUMIFS('Financing Baseline'!$N$49:$N$516,'Financing Baseline'!$C$49:$C$516,'Visualisation Dashboard'!$AG180),"") -> 0.97386622 | AI180: =IFERROR(SUMIFS('Financing Baseline'!$N$49:$N$516,'Financing Baseline'!$C$49:$C$516,'Visualisation Dashboard'!$AG180,'Financing Baseline'!$G$49:$G$516,'Visualisation Dashboard'!AI$173)/ SUMIFS('Financing Baseline'!$N$49:$N$516,'Financing Baseline'!$C$49:$C$516,'Visualisation Dashboard'!$AG180),"") -> 0.026133775 | AJ180: =IF(_xlfn.XLOOKUP(AE180,$AF$174:$AF$183,$AG$174:$AG$183,"")=0,"",_xlfn.XLOOKUP(AE180,$AF$174:$AF$183,$AG$174:$AG$183,"")) -> Geothermal | AK180: =_xlfn.XLOOKUP(AE180,$AF$174:$AF$183,$AH$174:$AH$183) -> 0.74420222 | AL180: =_xlfn.XLOOKUP(AE180,$AF$174:$AF$183,$AI$174:$AI$183) -> 0.25579778
B181: Total Financing Volume (US $M) | D181: =SUMIFS('Financing Baseline'!$N$49:$N$516,'Financing Baseline'!$F$49:$F$516,"Conc_IFI",'Financing Baseline'!$G$49:$G$516,"Loan") -> 8033.9146 | E181: =SUMIFS('Financing Baseline'!$N$49:$N$516,'Financing Baseline'!$F$49:$F$516,"Conc_DPS",'Financing Baseline'!$G$49:$G$516,"Loan") -> 205.98 | F181: =SUMIFS('Financing Baseline'!$N$49:$N$516,'Financing Baseline'!$F$49:$F$516,"Comm_Dom",'Financing Baseline'!$G$49:$G$516,"Loan") -> 51.4 | G181: =SUMIFS('Financing Baseline'!$N$49:$N$516,'Financing Baseline'!$F$49:$F$516,"Comm_Intl",'Financing Baseline'!$G$49:$G$516,"Loan") -> 484.02 | H181: =SUM(D181:G181) -> 8775.3146 | K181: 7 | L181: =_xlfn.RANK.EQ(N181, N$175:N$181) + COUNTIF(N$175:N181, N181) - 1 -> 7 | M181: Private Equity Fund | N181: =IFERROR(SUMIFS('Financing Baseline'!$N$49:$N$516,'Financing Baseline'!$I$49:$I$516,'Visualisation Dashboard'!$M181,'Financing Baseline'!$G$49:$G$516,'Visualisation Dashboard'!N$174)/ SUMIFS('Financing Baseline'!$N$49:$N$516,'Financing Baseline'!$I$49:$I$516,'Visualisation Dashboard'!$M181),"") -> 0.096182903 | O181: =IFERROR(SUMIFS('Financing Baseline'!$N$49:$N$516,'Financing Baseline'!$I$49:$I$516,'Visualisation Dashboard'!$M181,'Financing Baseline'!$G$49:$G$516,'Visualisation Dashboard'!O$174)/ SUMIFS('Financing Baseline'!$N$49:$N$516,'Financing Baseline'!$I$49:$I$516,'Visualisation Dashboard'!$M181),"") -> 0.9038171 | P181: =IF(_xlfn.XLOOKUP(K181,$L$175:$L$181,$M$175:$M$181,"")=0,"",_xlfn.XLOOKUP(K181,$L$175:$L$181,$M$175:$M$181,"")) -> Private Equity Fund | Q181: =_xlfn.XLOOKUP(K181,$L$175:$L$181,$N$175:$N$181) -> 0.096182903 | R181: =_xlfn.XLOOKUP(K181,$L$175:$L$181,$O$175:$O$181) -> 0.9038171 | AE181: 8 | AF181: =_xlfn.RANK.EQ(AH181, AH$174:AH$183) + COUNTIF(AH$174:AH181, AH181) - 1 -> 4 | AG181: Wind | AH181: =IFERROR(SUMIFS('Financing Baseline'!$N$49:$N$516,'Financing Baseline'!$C$49:$C$516,'Visualisation Dashboard'!$AG181,'Financing Baseline'!$G$49:$G$516,'Visualisation Dashboard'!AH$173)/ SUMIFS('Financing Baseline'!$N$49:$N$516,'Financing Baseline'!$C$49:$C$516,'Visualisation Dashboard'!$AG181),"") -> 0.79958468 | AI181: =IFERROR(SUMIFS('Financing Baseline'!$N$49:$N$516,'Financing Baseline'!$C$49:$C$516,'Visualisation Dashboard'!$AG181,'Financing Baseline'!$G$49:$G$516,'Visualisation Dashboard'!AI$173)/ SUMIFS('Financing Baseline'!$N$49:$N$516,'Financing Baseline'!$C$49:$C$516,'Visualisation Dashboard'!$AG181),"") -> 0.20041532 | AJ181: =IF(_xlfn.XLOOKUP(AE181,$AF$174:$AF$183,$AG$174:$AG$183,"")=0,"",_xlfn.XLOOKUP(AE181,$AF$174:$AF$183,$AG$174:$AG$183,"")) -> Hydro | AK181: =_xlfn.XLOOKUP(AE181,$AF$174:$AF$183,$AH$174:$AH$183) -> 0.64252336 | AL181: =_xlfn.XLOOKUP(AE181,$AF$174:$AF$183,$AI$174:$AI$183) -> 0.35747664
AE182: 9 | AF182: =_xlfn.RANK.EQ(AH182, AH$174:AH$183) + COUNTIF(AH$174:AH182, AH182) - 1 -> 8 | AG182: Hydro | AH182: =IFERROR(SUMIFS('Financing Baseline'!$N$49:$N$516,'Financing Baseline'!$C$49:$C$516,'Visualisation Dashboard'!$AG182,'Financing Baseline'!$G$49:$G$516,'Visualisation Dashboard'!AH$173)/ SUMIFS('Financing Baseline'!$N$49:$N$516,'Financing Baseline'!$C$49:$C$516,'Visualisation Dashboard'!$AG182),"") -> 0.64252336 | AI182: =IFERROR(SUMIFS('Financing Baseline'!$N$49:$N$516,'Financing Baseline'!$C$49:$C$516,'Visualisation Dashboard'!$AG182,'Financing Baseline'!$G$49:$G$516,'Visualisation Dashboard'!AI$173)/ SUMIFS('Financing Baseline'!$N$49:$N$516,'Financing Baseline'!$C$49:$C$516,'Visualisation Dashboard'!$AG182),"") -> 0.35747664 | AJ182: =IF(_xlfn.XLOOKUP(AE182,$AF$174:$AF$183,$AG$174:$AG$183,"")=0,"",_xlfn.XLOOKUP(AE182,$AF$174:$AF$183,$AG$174:$AG$183,"")) -> Biomass | AK182: =_xlfn.XLOOKUP(AE182,$AF$174:$AF$183,$AH$174:$AH$183) -> 0.61572052 | AL182: =_xlfn.XLOOKUP(AE182,$AF$174:$AF$183,$AI$174:$AI$183) -> 0.38427948
AE183: 10 | AF183: =_xlfn.RANK.EQ(AH183, AH$174:AH$183) + COUNTIF(AH$174:AH183, AH183) - 1 -> 10 | AG183: Battery | AH183: =IFERROR(SUMIFS('Financing Baseline'!$N$49:$N$516,'Financing Baseline'!$C$49:$C$516,'Visualisation Dashboard'!$AG183,'Financing Baseline'!$G$49:$G$516,'Visualisation Dashboard'!AH$173)/ SUMIFS('Financing Baseline'!$N$49:$N$516,'Financing Baseline'!$C$49:$C$516,'Visualisation Dashboard'!$AG183),"") -> 0 | AI183: =IFERROR(SUMIFS('Financing Baseline'!$N$49:$N$516,'Financing Baseline'!$C$49:$C$516,'Visualisation Dashboard'!$AG183,'Financing Baseline'!$G$49:$G$516,'Visualisation Dashboard'!AI$173)/ SUMIFS('Financing Baseline'!$N$49:$N$516,'Financing Baseline'!$C$49:$C$516,'Visualisation Dashboard'!$AG183),"") -> 1 | AJ183: =IF(_xlfn.XLOOKUP(AE183,$AF$174:$AF$183,$AG$174:$AG$183,"")=0,"",_xlfn.XLOOKUP(AE183,$AF$174:$AF$183,$AG$174:$AG$183,"")) -> Battery | AK183: =_xlfn.XLOOKUP(AE183,$AF$174:$AF$183,$AH$174:$AH$183) -> 0 | AL183: =_xlfn.XLOOKUP(AE183,$AF$174:$AF$183,$AI$174:$AI$183) -> 1
M184: =IFERROR(RANK(T184,$T$184:$T$188),"-") -> - | O184: =IFERROR(AVERAGEIFS('Financing Baseline'!$P$49:$P$516, 'Financing Baseline'!$C$49:$C$516, N184, 'Financing Baseline'!$G$49:$G$516, "Equity"),0) -> 0 | P184: =IFERROR((SUMIFS('Financing Baseline'!$K$49:$K$516, 'Financing Baseline'!$C$49:$C$516, N184, 'Financing Baseline'!$G$49:$G$516, "Equity"))/S184,0) -> 0 | Q184: =IFERROR(AVERAGEIFS('Financing Baseline'!$P$49:$P$516, 'Financing Baseline'!$C$49:$C$516, N184, 'Financing Baseline'!$G$49:$G$516, "Loan"),0) -> 0 | R184: =IFERROR((SUMIFS('Financing Baseline'!$K$49:$K$516, 'Financing Baseline'!$C$49:$C$516, N184, 'Financing Baseline'!$G$49:$G$516, "Loan"))/S184,0) -> 0 | S184: =SUMIF('Financing Baseline'!C54:C526, N184, 'Financing Baseline'!K54:K526) -> 0 | T184: =IFERROR( (O184*(P184/(P184+R184)))+ (Q184*(R184/(P184+R184))), "")
A185: Future Financing Needs Projections

Sheet Financial Instruments
A1: MINFin
A2: Financial Instruments
A4: Discount Rate Donor | B4: 0.04
A5: Discount Rate Recipient | B5: 0.0533
A7: ='High Level Dashboard'!A62 -> Scenario | B7: ='High Level Dashboard'!C62 -> Net Zero
B9: Total Over Modelling Period | C9: 2025 | D9: 2026 | E9: 2027 | F9: 2028 | G9: 2029 | H9: 2030 | I9: 2031 | J9: 2032 | K9: 2033 | L9: 2034 | M9: 2035 | N9: 2036 | O9: 2037 | P9: 2038 | Q9: 2039 | R9: 2040 | S9: 2041 | T9: 2042 | U9: 2043 | V9: 2044 | W9: 2045 | X9: 2046 | Y9: 2047 | Z9: 2048 | AA9: 2049 | AB9: 2050 | AC9: 2051 | AD9: 2052 | AE9: 2053 | AF9: 2054 | AG9: 2055 | AH9: 2056 | AI9: 2057 | AJ9: 2058 | AK9: 2059 | AL9: 2060 | AM9: 2061 | AN9: 2062 | AO9: 2063 | AP9: 2064 | AQ9: 2065 | AR9: 2066 | AS9: 2067 | AT9: 2068 | AU9: 2069 | AV9: 2070
A10: 1. Grants
A11: 1a. Undiscounted | B11: =SUM(C11:AV11) -> 829.8024 | C11: =C17 -> 300 | D11: =D17 -> 0 | E11: =E17 -> 40.8221 | F11: =F17 -> 8.4931 | G11: =G17 -> 9.2837 | H11: =H17 -> -63.3406 | I11: =I17 -> -167.113 | J11: =J17 -> 20.2359 | ... AV11: =AV17 -> 128.2393
A12: 1a. Donor | B12: =SUM(C12:AV12) -> -129.16168 | C12: =-C11/(1+$B$4)^(C$9-$C$9+1) -> -288.46154 | D12: =-D11/(1+$B$4)^(D$9-$C$9+1) -> 0 | E12: =-E11/(1+$B$4)^(E$9-$C$9+1) -> -36.290698 | F12: =-F11/(1+$B$4)^(F$9-$C$9+1) -> -7.2599375 | G12: =-G11/(1+$B$4)^(G$9-$C$9+1) -> -7.6305247 | H12: =-H11/(1+$B$4)^(H$9-$C$9+1) -> 50.058996 | I12: =-I11/(1+$B$4)^(I$9-$C$9+1) -> 126.99215 | J12: =-J11/(1+$B$4)^(J$9-$C$9+1) -> -14.786174 | ... AV12: =-AV11/(1+$B$4)^(AV$9-$C$9+1) -> -21.109966
A13: 1a. Recipient | B13: =SUM(C13:AV13) -> 88.846657 | C13: =C11/(1+$B$5)^(C$9-$C$9+1) -> 284.81914 | D13: =D11/(1+$B$5)^(D$9-$C$9+1) -> 0 | E13: =E11/(1+$B$5)^(E$9-$C$9+1) -> 34.933258 | F13: =F11/(1+$B$5)^(F$9-$C$9+1) -> 6.90014 | G13: =G11/(1+$B$5)^(G$9-$C$9+1) -> 7.1607857 | H13: =H11/(1+$B$5)^(H$9-$C$9+1) -> -46.384157 | I13: =I11/(1+$B$5)^(I$9-$C$9+1) -> -116.18382 | J13: =J11/(1+$B$5)^(J$9-$C$9+1) -> 13.356905 | ... AV13: =AV11/(1+$B$5)^(AV$9-$C$9+1) -> 11.765903
B14: =SUM(C17:AB17) -> -552.6454
A15: 1a - Without FF Savings
A16: Cumulative Grant Requirement (Million US$) | B16: =SUM(C17:AV17) -> 829.8024
A17: Annual Grant Requirement (Million US$) | C17: =SUM(C18:C21) -> 300 | D17: =SUM(D18:D21) -> 0 | E17: =SUM(E18:E21) -> 40.8221 | F17: =SUM(F18:F21) -> 8.4931 | G17: =SUM(G18:G21) -> 9.2837 | H17: =SUM(H18:H21) -> -63.3406 | I17: =SUM(I18:I21) -> -167.113 | J17: =SUM(J18:J21) -> 20.2359 | ... AV17: =SUM(AV18:AV21) -> 128.2393
A18: New Power Generation ($ Million) | C18: ='Investment Needs'!C12 -> 300 | D18: ='Investment Needs'!D12 -> 0 | E18: ='Investment Needs'!E12 -> 32.4531 | F18: ='Investment Needs'!F12 -> 0 | G18: ='Investment Needs'!G12 -> 0 | H18: ='Investment Needs'!H12 -> -56.4066 | I18: ='Investment Needs'!I12 -> -164.8087 | J18: ='Investment Needs'!J12 -> 23.3282 | ... AV18: ='Investment Needs'!AV12 -> 97.0504
A19: Stranded Power Generation ($ Million) | C19: {=TRANSPOSE('FFRM (Input)'!D9:D54)+TRANSPOSE('FFRM (Input)'!G9:G54)+TRANSPOSE('FFRM (Input)'!J9:J54)} -> 0 | D19: 0 | E19: 0 | F19: 0 | G19: 0 | H19: 0 | I19: 0 | J19: 0 | K19: 0 | L19: 0 | M19: 0 | N19: 0 | O19: 0 | P19: 0 | Q19: 0 | R19: 0 | S19: 0 | T19: 0 | U19: 0 | V19: 0 | W19: 0 | X19: 0 | Y19: 0 | Z19: 0 | AA19: 0 | AB19: 0 | AC19: 0 | AD19: 0 | AE19: 0 | AF19: 0 | AG19: 0 | AH19: 0 | AI19: 0 | AJ19: 0 | AK19: 0 | AL19: 0 | AM19: 0 | AN19: 0 | AO19: 0 | AP19: 0 | AQ19: 0 | AR19: 0 | AS19: 0 | AT19: 0 | AU19: 0 | AV19: 0
A20: Variable Cost ($ Million) | C20: {=(TRANSPOSE('OSeMOSYS (Input)'!D139:D184)-TRANSPOSE('OSeMOSYS (Input)'!E139:E184))-(TRANSPOSE('OSeMOSYS (Input)'!AN21:AN66)-TRANSPOSE('OSeMOSYS (Input)'!AN85:AN130))} -> 0 | D20: 0 | E20: 13.1888 | F20: 13.294 | G20: 14.0657 | H20: -10.4501 | I20: -6.4782 | J20: -6.582 | K20: -7.4456 | L20: -3.3494 | M20: 7.9877 | N20: 7.2762 | O20: 9.0172 | P20: 9.5765 | Q20: 10.6065 | R20: -3.8046 | S20: -3.3119 | T20: -3.9718 | U20: -0.1177 | V20: 1.6779 | W20: 2.3954 | X20: 4.0938 | Y20: -2.5669 | Z20: -9.0584 | AA20: -11.9149 | AB20: -26.5211 | AC20: -26.7989 | AD20: -16.3997 | AE20: 2.3588 | AF20: 3.3959 | AG20: 8.6545 | AH20: 12.4842 | AI20: 13.1178 | AJ20: 15.9512 | AK20: 18.7876 | AL20: 21.2555 | AM20: 25.9574 | AN20: 30.2909 | AO20: 33.5319 | AP20: 37.4442 | AQ20: 41.8637 | AR20: 46.1619 | AS20: 49.9377 | AT20: 53.9304 | AU20: 57.441 | AV20: 61.4528
A21: Fixed Cost ($ Million) | C21: {=TRANSPOSE('OSeMOSYS (Input)'!F139:F184)-TRANSPOSE('OSeMOSYS (Input)'!G139:G184)} -> 0 | D21: 0 | E21: -4.8198 | F21: -4.8009 | G21: -4.782 | H21: 3.5161 | I21: 4.1739 | J21: 3.4897 | K21: 7.5471 | L21: 4.4254 | M21: -1.1876 | N21: -1.5333 | O21: -2.3244 | P21: -1.3549 | Q21: -0.6722 | R21: 2.754 | S21: 1.6884 | T21: 2.503 | U21: 1.411 | V21: 0.9583 | W21: 0.6896 | X21: 0.0473 | Y21: 1.025 | Z21: 3.992 | AA21: 5.0913 | AB21: 16.1775 | AC21: 20.3635 | AD21: 15.8004 | AE21: 6.1335 | AF21: 3.4804 | AG21: -0.6052 | AH21: -1.4916 | AI21: -2.165 | AJ21: -3.6073 | AK21: -5.1275 | AL21: -8.8193 | AM21: -10.5586 | AN21: -12.8217 | AO21: -14.293 | AP21: -16.5002 | AQ21: -19.3835 | AR21: -22.2029 | AS21: -24.2338 | AT21: -26.6588 | AU21: -28.399 | AV21: -30.2639
A23: 1b - With FF Savings
A24: Cumulative Grant Requirement Considering FF Savings (Million US$) | B24: =SUM(C25:AV25) -> -946.7667
A25: Annual Grant Requirement Considering FF Savings(Million US$) | C25: =C17-C26 -> 300 | D25: =D17-D26 -> 0 | E25: =E17-E26 -> 45.4373 | F25: =F17-F26 -> 13.003 | G25: =G17-G26 -> 12.875 | H25: =H17-H26 -> -65.97 | I25: =I17-I26 -> -169.0689 | J25: =J17-J26 -> 17.7666 | ... AV25: =AV17-AV26 -> -24.3048
A26: Fossil Fuel Savings (Million US$) | C26: {=TRANSPOSE('OSeMOSYS (Input)'!AN85:AN130)-TRANSPOSE('OSeMOSYS (Input)'!AN21:AN66)} -> 0 | D26: 0 | E26: -4.6152 | F26: -4.5099 | G26: -3.5913 | H26: 2.6294 | I26: 1.9559 | J26: 2.4693 | K26: 9.7175 | L26: 3.7868 | M26: 6.1791 | N26: 3.7812 | O26: 5.2467 | P26: 5.8192 | Q26: 7.9206 | R26: 5.5285 | S26: 6.678 | T26: 8.8512 | U26: 7.9744 | V26: 7.9916 | W26: 8.8247 | X26: 8.4078 | Y26: 6.9456 | Z26: 12.4458 | AA26: 14.673 | AB26: 25.6271 | AC26: 21.3545 | AD26: 22.676 | AE26: 26.0347 | AF26: 30.4391 | AG26: 34.9411 | AH26: 43.3815 | AI26: 52.6015 | AJ26: 59.5598 | AK26: 67.4945 | AL26: 76.245 | AM26: 84.4713 | AN26: 93.6008 | AO26: 103.1902 | AP26: 111.2738 | AQ26: 116.1024 | AR26: 121.4919 | AS26: 129.0093 | AT26: 135.4324 | AU26: 143.9882 | AV26: 152.5441
A28: 1c - With FF and Carbon Savings
A29: Cumulative Grant Requirement Considering FF and Carbon Savings (Million US$) | B29: =SUM(C30:AB30) -> -981.40209
A30: Annual Grant Requirement Considering FF and Carbon Savings(Million US$) | C30: =C25-C31 -> 300 | D30: =D25-D31 -> 0 | E30: =E25-E31 -> 48.66236 | F30: =F25-F31 -> 16.22905 | G30: =G25-G31 -> 15.49914 | H30: =H25-H31 -> -67.9275 | I30: =I25-I31 -> -170.33429 | J30: =J25-J31 -> 16.174877 | ... AV30: =AV25-AV31 -> -370.97378
A31: Carbon Savings (Million US$) | C31: {=(TRANSPOSE('OSeMOSYS (Input)'!S139:S184)-TRANSPOSE('OSeMOSYS (Input)'!R139:R184))*C32:AV32} -> 0 | D31: 0 | E31: -3.22506 | F31: -3.22605 | G31: -2.62414 | H31: 1.9575 | I31: 1.265385 | J31: 1.591723 | K31: 12.059072 | L31: 2.443004 | M31: 3.629839 | N31: 1.997043 | O31: 6.22244 | P31: 8.396457 | Q31: 9.749432 | R31: 8.600742 | S31: 9.46504 | T31: 10.95081 | U31: 10.657024 | V31: 10.875942 | W31: 11.57156 | X31: 11.531439 | Y31: 10.827572 | Z31: 32.01484 | AA31: 41.560426 | AB31: 79.727648 | AC31: 81.25593 | AD31: 86.38616 | AE31: 93.001696 | AF31: 100.54019 | AG31: 108.44149 | AH31: 120.04062 | AI31: 132.93072 | AJ31: 146.73411 | AK31: 162.55103 | AL31: 178.33476 | AM31: 193.33542 | AN31: 210.80923 | AO31: 229.97982 | AP31: 246.52291 | AQ31: 257.58318 | AR31: 270.18453 | AS31: 288.10435 | AT31: 304.22264 | AU31: 325.05268 | AV31: 346.66898
A32: Carbon Price ($/Ton CO2e) | C32: 67.06 | D32: 68.57 | E32: 70.11 | F32: 71.69 | G32: 73.3 | H32: 75 | I32: 76.69 | J32: 78.41 | K32: 80.18 | L32: 81.98 | M32: 83.83 | N32: 85.71 | O32: 87.64 | P32: 89.61 | Q32: 91.63 | R32: 93.69 | S32: 95.8 | T32: 97.95 | U32: 100.16 | V32: 102.41 | W32: 104.72 | X32: 107.07 | Y32: 109.48 | Z32: 111.94 | AA32: 114.46 | AB32: 117.04 | AC32: 119.67 | AD32: 122.36 | AE32: 125.12 | AF32: 127.93 | AG32: 130.81 | AH32: 133.75 | AI32: 136.76 | AJ32: 139.84 | AK32: 142.99 | AL32: 146.2 | AM32: 149.49 | AN32: 152.86 | AO32: 156.3 | AP32: 159.81 | AQ32: 163.41 | AR32: 167.09 | AS32: 170.85 | AT32: 174.69 | AU32: 178.62 | AV32: 182.64
A35: 2. Loans
A36: 2b. Undiscounted | B36: =SUM(C36:AV36) -> 5107.4668 | C36: =C50 -> -300 | D36: =D50 -> 0 | E36: =E50 -> -48.66236 | F36: =F50 -> -16.22905 | G36: =G50 -> -15.49914 | H36: =H50 -> 67.9275 | I36: =I50 -> 170.33429 | J36: =J50 -> -16.174877 | ... AV36: =AV50 -> 370.97378
A37: 2b. Donor | B37: =SUM(C37:AV37) -> 1273.4388 | C37: =C36/(1+$B$4)^(C$9-$C$9+1) -> -288.46154 | D37: =D36/(1+$B$4)^(D$9-$C$9+1) -> 0 | E37: =E36/(1+$B$4)^(E$9-$C$9+1) -> -43.260661 | F37: =F36/(1+$B$4)^(F$9-$C$9+1) -> -13.87266 | G37: =G36/(1+$B$4)^(G$9-$C$9+1) -> -12.739163 | H37: =H36/(1+$B$4)^(H$9-$C$9+1) -> 53.68409 | I37: =I36/(1+$B$4)^(I$9-$C$9+1) -> 129.44006 | J37: =J36/(1+$B$4)^(J$9-$C$9+1) -> -11.818824 | ... AV37: =AV36/(1+$B$4)^(AV$9-$C$9+1) -> 61.067426
A38: 2b. Recipient | B38: =SUM(C38:AV38) -> -807.57032 | C38: =(C17+(-C45-C51))/(1+$B$5)^(C$9-$C$9+1) -> 284.81914 | D38: =(D17+(-D45-D51))/(1+$B$5)^(D$9-$C$9+1) -> 0 | E38: =(E17+(-E45-E51))/(1+$B$5)^(E$9-$C$9+1) -> 41.642512 | F38: =(F17+(-F45-F51))/(1+$B$5)^(F$9-$C$9+1) -> 13.18514 | G38: =(G17+(-G45-G51))/(1+$B$5)^(G$9-$C$9+1) -> 11.954934 | H38: =(H17+(-H45-H51))/(1+$B$5)^(H$9-$C$9+1) -> -49.743132 | I38: =(I17+(-I45-I51))/(1+$B$5)^(I$9-$C$9+1) -> -118.42339 | J38: =(J17+(-J45-J51))/(1+$B$5)^(J$9-$C$9+1) -> 10.676387 | ... AV38: =(AV17+(-AV45-AV51))/(1+$B$5)^(AV$9-$C$9+1) -> -34.036692
A40: 2a - With Fossil Fuel Savings
A41: Donor MIRR | B41: =MIRR(C43:AV43,B4,B4) -> 0.049177004
A42: Recipient MIRR | B42: =MIRR(C43:AV43,B5,B5) -> 0.060301381
A43: Net Cashflow (Million US$) | B43: =SUM(C43:AV43) -> 946.7667 | C43: =SUM(C44:C45) -> -300 | D43: =SUM(D44:D45) -> 0 | E43: =SUM(E44:E45) -> -45.4373 | F43: =SUM(F44:F45) -> -13.003 | G43: =SUM(G44:G45) -> -12.875 | H43: =SUM(H44:H45) -> 65.97 | I43: =SUM(I44:I45) -> 169.0689 | J43: =SUM(J44:J45) -> -17.7666 | ... AV43: =SUM(AV44:AV45) -> 24.3048
A44: Incremental Investment Needs Total (Million US$) | B44: =SUM(C44:AV44) -> -829.8024 | C44: =-C17 -> -300 | D44: =-D17 -> 0 | E44: =-E17 -> -40.8221 | F44: =-F17 -> -8.4931 | G44: =-G17 -> -9.2837 | H44: =-H17 -> 63.3406 | I44: =-I17 -> 167.113 | J44: =-J17 -> -20.2359 | ... AV44: =-AV17 -> -128.2393
A45: Delta Fossil Fuel Savings (Million US$) | B45: =SUM(C45:AV45) -> 1776.5691 | C45: {=TRANSPOSE('OSeMOSYS (Input)'!AN85:AN130)-TRANSPOSE('OSeMOSYS (Input)'!AN21:AN66)} -> 0 | D45: 0 | E45: -4.6152 | F45: -4.5099 | G45: -3.5913 | H45: 2.6294 | I45: 1.9559 | J45: 2.4693 | K45: 9.7175 | L45: 3.7868 | M45: 6.1791 | N45: 3.7812 | O45: 5.2467 | P45: 5.8192 | Q45: 7.9206 | R45: 5.5285 | S45: 6.678 | T45: 8.8512 | U45: 7.9744 | V45: 7.9916 | W45: 8.8247 | X45: 8.4078 | Y45: 6.9456 | Z45: 12.4458 | AA45: 14.673 | AB45: 25.6271 | AC45: 21.3545 | AD45: 22.676 | AE45: 26.0347 | AF45: 30.4391 | AG45: 34.9411 | AH45: 43.3815 | AI45: 52.6015 | AJ45: 59.5598 | AK45: 67.4945 | AL45: 76.245 | AM45: 84.4713 | AN45: 93.6008 | AO45: 103.1902 | AP45: 111.2738 | AQ45: 116.1024 | AR45: 121.4919 | AS45: 129.0093 | AT45: 135.4324 | AU45: 143.9882 | AV45: 152.5441
A47: 2b - With Fossil Fuel and Carbon Savings
A48: Donor MIRR | B48: =MIRR(C50:AV50,B4,B4) -> 0.071125271
A49: Recipient MIRR | B49: =MIRR(C50:AV50,B5,B5) -> 0.078381596
A50: Net Cashflow (Million US$) | B50: =SUM(C50:AV50) -> 5107.4668 | C50: =C43+C51 -> -300 | D50: =D43+D51 -> 0 | E50: =E43+E51 -> -48.66236 | F50: =F43+F51 -> -16.22905 | G50: =G43+G51 -> -15.49914 | H50: =H43+H51 -> 67.9275 | I50: =I43+I51 -> 170.33429 | J50: =J43+J51 -> -16.174877 | ... AV50: =AV43+AV51 -> 370.97378
A51: Carbon Savings (Million US$) | B51: =SUM(C51:AV51) -> 4160.7001 | C51: {=(TRANSPOSE('OSeMOSYS (Input)'!S139:S184)-TRANSPOSE('OSeMOSYS (Input)'!R139:R184))*'Financial Instruments'!C52:AV52} -> 0 | D51: 0 | E51: -3.22506 | F51: -3.22605 | G51: -2.62414 | H51: 1.9575 | I51: 1.265385 | J51: 1.591723 | K51: 12.059072 | L51: 2.443004 | M51: 3.629839 | N51: 1.997043 | O51: 6.22244 | P51: 8.396457 | Q51: 9.749432 | R51: 8.600742 | S51: 9.46504 | T51: 10.95081 | U51: 10.657024 | V51: 10.875942 | W51: 11.57156 | X51: 11.531439 | Y51: 10.827572 | Z51: 32.01484 | AA51: 41.560426 | AB51: 79.727648 | AC51: 81.25593 | AD51: 86.38616 | AE51: 93.001696 | AF51: 100.54019 | AG51: 108.44149 | AH51: 120.04062 | AI51: 132.93072 | AJ51: 146.73411 | AK51: 162.55103 | AL51: 178.33476 | AM51: 193.33542 | AN51: 210.80923 | AO51: 229.97982 | AP51: 246.52291 | AQ51: 257.58318 | AR51: 270.18453 | AS51: 288.10435 | AT51: 304.22264 | AU51: 325.05268 | AV51: 346.66898
A52: Carbon Price ($/Ton CO2e) | B52: =AVERAGE(C52:AV52) -> 115.59391 | C52: 67.06 | D52: 68.57 | E52: 70.11 | F52: 71.69 | G52: 73.3 | H52: 75 | I52: 76.69 | J52: 78.41 | K52: 80.18 | L52: 81.98 | M52: 83.83 | N52: 85.71 | O52: 87.64 | P52: 89.61 | Q52: 91.63 | R52: 93.69 | S52: 95.8 | T52: 97.95 | U52: 100.16 | V52: 102.41 | W52: 104.72 | X52: 107.07 | Y52: 109.48 | Z52: 111.94 | AA52: 114.46 | AB52: 117.04 | AC52: 119.67 | AD52: 122.36 | AE52: 125.12 | AF52: 127.93 | AG52: 130.81 | AH52: 133.75 | AI52: 136.76 | AJ52: 139.84 | AK52: 142.99 | AL52: 146.2 | AM52: 149.49 | AN52: 152.86 | AO52: 156.3 | AP52: 159.81 | AQ52: 163.41 | AR52: 167.09 | AS52: 170.85 | AT52: 174.69 | AU52: 178.62 | AV52: 182.64
A55: 3. Grant&Loan
A56: 3b. Undiscounted | B56: =SUM(C56:AV56) -> 5057.4668 | C56: =(C70-C69)-C69 -> -350 | D56: =D70 -> 0 | E56: =E70 -> -48.66236 | F56: =F70 -> -16.22905 | G56: =G70 -> -15.49914 | H56: =H70 -> 67.9275 | I56: =I70 -> 170.33429 | J56: =J70 -> -16.174877 | K56: =K70 -> 50.542372 | ... AV56: =AV70 -> 370.97378
A57: 3b. Donor | B57: =SUM(C57:AV57) -> 1225.3619 | C57: =C56/(1+$B$4)^(C$9-$C$9+1) -> -336.53846 | D57: =D56/(1+$B$4)^(D$9-$C$9+1) -> 0 | E57: =E56/(1+$B$4)^(E$9-$C$9+1) -> -43.260661 | F57: =F56/(1+$B$4)^(F$9-$C$9+1) -> -13.87266 | G57: =G56/(1+$B$4)^(G$9-$C$9+1) -> -12.739163 | H57: =H56/(1+$B$4)^(H$9-$C$9+1) -> 53.68409 | I57: =I56/(1+$B$4)^(I$9-$C$9+1) -> 129.44006 | J57: =J56/(1+$B$4)^(J$9-$C$9+1) -> -11.818824 | ... AV57: =AV56/(1+$B$4)^(AV$9-$C$9+1) -> 61.067426
A58: 3b. Recipient | B58: =SUM(C58:AV58) -> -760.10047 | C58: =(C17+C69+(-C45-C51))/(1+$B$5)^(C$9-$C$9+1) -> 332.289 | D58: =(D17+(-D45-D51))/(1+$B$5)^(D$9-$C$9+1) -> 0 | E58: =(E17+(-E45-E51))/(1+$B$5)^(E$9-$C$9+1) -> 41.642512 | F58: =(F17+(-F45-F51))/(1+$B$5)^(F$9-$C$9+1) -> 13.18514 | G58: =(G17+(-G45-G51))/(1+$B$5)^(G$9-$C$9+1) -> 11.954934 | H58: =(H17+(-H45-H51))/(1+$B$5)^(H$9-$C$9+1) -> -49.743132 | I58: =(I17+(-I45-I51))/(1+$B$5)^(I$9-$C$9+1) -> -118.42339 | J58: =(J17+(-J45-J51))/(1+$B$5)^(J$9-$C$9+1) -> 10.676387 | K58: =(K17+(-K45-K51))/(1+$B$5)^(K$9-$C$9+1) -> -31.672829 | ... AV58: =(AV17+(-AV45-AV51))/(1+$B$5)^(AV$9-$C$9+1) -> -34.036692
A60: 3a - With Fossil Fuel Savings
A61: Donor MIRR | B61: =MIRR(C64:AV64,B4,B4) -> 0.051118437
A62: Recipient MIRR | B62: =MIRR(C64:AV64,B5,B5) -> 0.062548563
A63: Grant (Million US$) | B63: Goal Seek; Set: Cell B58, To Value: Cell B3, By Changing: Cell C60 --> | C63: 50
A64: Net Cashflow (Million US$) | C64: =C43+C63 -> -250 | D64: =D63+D43 -> 0 | E64: =E63+E43 -> -45.4373 | F64: =F63+F43 -> -13.003 | G64: =G63+G43 -> -12.875 | H64: =H63+H43 -> 65.97 | I64: =I63+I43 -> 169.0689 | J64: =J63+J43 -> -17.7666 | K64: =K63+K43 -> 38.4833 | ... AV64: =AV63+AV43 -> 24.3048
A66: 3b - With Fossil Fuel and Carbon Savings
A67: Donor MIRR | B67: =MIRR(C70:AV70,B4,B4) -> 0.073757489
A68: Recipient MIRR | B68: =MIRR(C70:AV70,B5,B5) -> 0.081197094
A69: Grant (Million US$) | B69: Goal Seek; Set: Cell B64, To Value: Cell B3, By Changing: Cell C66 --> | C69: 50
A70: Net Cashflow (Million US$) | C70: =C50+C69 -> -250 | D70: =D69+D50 -> 0 | E70: =E69+E50 -> -48.66236 | F70: =F69+F50 -> -16.22905 | G70: =G69+G50 -> -15.49914 | H70: =H69+H50 -> 67.9275 | I70: =I69+I50 -> 170.33429 | J70: =J69+J50 -> -16.174877 | K70: =K69+K50 -> 50.542372 | ... AV70: =AV69+AV50 -> 370.97378
A73: 4. Grant Element
A74: 5. Undiscounted | B74: =SUM(C74:AV74) -> 32702.531 | C74: =-C96+C95 -> -804.29736 | D74: =-D96+D95 -> -797.11285 | E74: =-E96+E95 -> -748.99004 | F74: =-F96+F95 -> -597.05728 | G74: =-G96+G95 -> -1360.7878 | H74: =-H96+H95 -> -637.14162 | I74: =-I96+I95 -> -678.65184 | J74: =-J96+J95 -> -291.22777 | ... AV74: =-AV96+AV95 -> 2663.5716
A75: 5. Donor | B75: =SUM(C75:AV75) -> 3470.2213 | C75: =C74/(1+$B$4)^(C$9-$C$9+1) -> -773.36284 | D75: =D74/(1+$B$4)^(D$9-$C$9+1) -> -736.97564 | E75: =E74/(1+$B$4)^(E$9-$C$9+1) -> -665.84942 | F75: =F74/(1+$B$4)^(F$9-$C$9+1) -> -510.36706 | G75: =G74/(1+$B$4)^(G$9-$C$9+1) -> -1118.4684 | H75: =H74/(1+$B$4)^(H$9-$C$9+1) -> -503.54228 | I75: =I74/(1+$B$4)^(I$9-$C$9+1) -> -515.71962 | J75: =J74/(1+$B$4)^(J$9-$C$9+1) -> -212.79728 | ... AV75: =AV74/(1+$B$4)^(AV$9-$C$9+1) -> 438.46079
A76: 5. Recipient | B76: =SUM(C76:AV76) -> -355.39886 | C76: =(C96+-C95)/(1+$B$5)^(C$9-$C$9+1) -> 763.59761 | D76: =(D96+-D95)/(1+$B$5)^(D$9-$C$9+1) -> 718.48159 | E76: =(E96+-E95)/(1+$B$5)^(E$9-$C$9+1) -> 640.94356 | F76: =(F96+-F95)/(1+$B$5)^(F$9-$C$9+1) -> 485.07362 | G76: =(G96+-G95)/(1+$B$5)^(G$9-$C$9+1) -> 1049.6149 | H76: =(H96+-H95)/(1+$B$5)^(H$9-$C$9+1) -> 466.57716 | I76: =(I96+-I95)/(1+$B$5)^(I$9-$C$9+1) -> 471.82662 | J76: =(J96+-J95)/(1+$B$5)^(J$9-$C$9+1) -> 192.22776 | ... AV76: =(AV96+-AV95)/(1+$B$5)^(AV$9-$C$9+1) -> -244.3816
A78: 4a - Interest Rate
A80: Increase in Share of Concessional International Finance (Conc IFI) | B80: 1.0773272 | C80: <-- Goal Seek; Set: Cell B95, To Value, 0, By Changing: Cell B76
A81: Share of Concessional International Finance (Conc IFI) | B81: =IF(B80>0,B80*'High Level Dashboard'!F53,'High Level Dashboard'!F53) -> 0.80133044
A82: Share of Concessional Domestic Finance (Conc DPS) | B82: =(('High Level Dashboard'!$C$54 / (SUM('High Level Dashboard'!$C$53:'High Level Dashboard'!$C$56) - 'High Level Dashboard'!$C$53)) * (SUM('High Level Dashboard'!$C$53:'High Level Dashboard'!$C$56) - B81)) -> 0.086155357
A83: Share of Commercial International Finance (Comm Intl) | B83: =(('High Level Dashboard'!$C$55 / (SUM('High Level Dashboard'!$C$53:'High Level Dashboard'!$C$56) - 'High Level Dashboard'!$C$53)) * (SUM('High Level Dashboard'!$C$53:'High Level Dashboard'!$C$56) - B81)) -> 0.094464395
A84: Share of Commercial Domestic Finance (Comm Dom) | B84: =('High Level Dashboard'!$C$56 / (SUM('High Level Dashboard'!$C$53:'High Level Dashboard'!$C$56) - 'High Level Dashboard'!$C$53)) * (SUM('High Level Dashboard'!$C$53:'High Level Dashboard'!$C$56) - B81) -> 0.018049804
A85: Total Contribution Concessional International Finance (Conc IFI) | B85: =B80*SUM($C$96:$AV$96) -> 91513.053 | C85: <-- This is just investment needs and doesn't include existing financing
A86: Total Contribution Concessional Domestic Finance (Conc DPS) | B86: =B82*SUM($C$96:$AV$96) -> 7318.4265
A87: Total Contribution Commercial International Finance (Comm Intl) | B87: =B83*SUM($C$96:$AV$96) -> 8024.2337
A88: Total Contribution Commercial Domestic Finance (Comm Dom) | B88: =B84*SUM($C$96:$AV$96) -> 1533.2322
A89: Additional Contribution Concessional International Finance (Conc IFI) | B89: =B85-(SUM($C$96:$AV$96)*'High Level Dashboard'!C53) -> 23444.414
A91: Interest Rate | B91: =IF(B80>0,'High Level Dashboard'!E34,0) -> 0.053333243 | C91: WACC Calculator on repayment schedules below, repayment schedules to change so that the IR is historic and the weightings are referenced above
A93: Delta Financing Requirements | B93: =SUM(C93:AB93) -> -282.26623 | C93: =C106-C95 -> -16.279529 | D93: =D106-D95 -> -16.36808 | E93: =E106-E95 -> -18.352959 | F93: =F106-F95 -> -18.198477 | G93: =G106-G95 -> -18.079859 | H93: =H106-H95 -> -14.848431 | I93: =I106-I95 -> -22.594843 | J93: =J106-J95 -> -34.943272 | ... W93: =W106-W95 -> -182.05122 | X93: =X95-X106 -> 212.70068 | Y93: =Y95-Y106 -> 235.70075 | Z93: =Z95-Z106 -> 240.90712 | AA93: =AA95-AA106 -> 253.8048 | AB93: =AB95-AB106 -> 267.34837 | AC93: =AC95-AC106 -> 265.36513 | AD93: =AD95-AD106 -> 268.3644 | AE93: =AE95-AE106 -> 283.01925 | ... AV93: =AV95-AV106 -> 567.39944
A95: ='OSeMOSYS (Input)'!$C$4&" Financing Requirements" -> NetZero Financing Requirements | C95: =SUM(C97:C104) -> 45.985741 | D95: =SUM(D97:D104) -> 94.189945 | E95: =SUM(E97:E104) -> 143.32076 | F95: =SUM(F97:F104) -> 186.82472 | G95: =SUM(G97:G104) -> 276.49341 | H95: =SUM(H97:H104) -> 329.79708 | I95: =SUM(I97:I104) -> 422.04776 | J95: =SUM(J97:J104) -> 501.36223 | ... AV95: =SUM(AV97:AV104) -> 5262.4474
A96: Investment need (Million USD) | C96: ='Investment Needs'!C6 -> 850.2831 | D96: ='Investment Needs'!D6 -> 891.3028 | E96: ='Investment Needs'!E6 -> 892.3108 | F96: ='Investment Needs'!F6 -> 783.882 | G96: ='Investment Needs'!G6 -> 1637.2812 | H96: ='Investment Needs'!H6 -> 966.9387 | I96: ='Investment Needs'!I6 -> 1100.6996 | J96: ='Investment Needs'!J6 -> 792.59 | ... AV96: ='Investment Needs'!AV6 -> 2598.8758
A97: Loans - Concessional International Finance (Conc IFI) | C97: =$B$80*'High Level Dashboard'!$C$9* (-PMT('High Level Dashboard'!$C$10,'High Level Dashboard'!$C$12-'High Level Dashboard'!$C$11+1, SUMIFS('High Level Dashboard'!$B$65:$AV$65,'High Level Dashboard'!$B$64:$AV$64,">="&('High Level Dashboard'!B$64-(ROUNDDOWN('High Level Dashboard'!$C$12,0))+1),'High Level Dashboard'!$B$64:$AV$64,"<="&('High Level Dashboard'!B$64-(ROUNDUP('High Level Dashboard'!$C$11,0))))) + IFERROR(-PMT('High Level Dashboard'!$C$10,'High Level Dashboard'!$C$12-'High Level Dashboard'!$C$11+1, (HLOOKUP('High Level Dashboard'!B$64-(ROUNDUP('High Level Dashboard'!$C$12,0))+1,'High Level Dashboard'!$B$64:$AV$65,2,FALSE))*('High Level Dashboard'!$C$12-(ROUNDDOWN('High Level Dashboard'!$C$12,0)))),0) + IFERROR(-PMT('High Level Dashboard'!$C$10,'High Level Dashboard'!$C$12-'High Level Dashboard'!$C$11+1, (HLOOKUP('High Level Dashboard'!B$64-(ROUNDDOWN('High Level Dashboard'!$C$11,0)),'High Level Dashboard'!$B$64:$AV$65,2,FALSE)*('High Level Dashboard'!$C$11-ROUNDDOWN('High Level Dashboard'!$C$11,0)))),0) + (((SUMIFS('High Level Dashboard'!$B$65:$AV$65,'High Level Dashboard'!$B$64:$AV$64,">"&'High Level Dashboard'!B$64-ROUNDDOWN('High Level Dashboard'!$C$11,0),'High Level Dashboard'!$B$64:$AV$64,"<="&'High Level Dashboard'!B$64)+(IFERROR(SUMIF('High Level Dashboard'!$B$64:$AV$64,ROUNDDOWN('High Level Dashboard'!B$64-'High Level Dashboard'!$C$11,0)+1,'High Level Dashboard'!$B$65:$AV$65)*(1-('High Level Dashboard'!$C$11-ROUNDDOWN('High Level Dashboard'!$C$11,0))),"")))*'High Level Dashboard'!$C$10) )) -> 20.008442 | D97: =$B$80*'High Level Dashboard'!$C$9* (-PMT('High Level Dashboard'!$C$10,'High Level Dashboard'!$C$12-'High Level Dashboard'!$C$11+1, SUMIFS('High Level Dashboard'!$B$65:$AV$65,'High Level Dashboard'!$B$64:$AV$64,">="&('High Level Dashboard'!C$64-(ROUNDDOWN('High Level Dashboard'!$C$12,0))+1),'High Level Dashboard'!$B$64:$AV$64,"<="&('High Level Dashboard'!C$64-(ROUNDUP('High Level Dashboard'!$C$11,0))))) + IFERROR(-PMT('High Level Dashboard'!$C$10,'High Level Dashboard'!$C$12-'High Level Dashboard'!$C$11+1, (HLOOKUP('High Level Dashboard'!C$64-(ROUNDUP('High Level Dashboard'!$C$12,0))+1,'High Level Dashboard'!$B$64:$AV$65,2,FALSE))*('High Level Dashboard'!$C$12-(ROUNDDOWN('High Level Dashboard'!$C$12,0)))),0) + IFERROR(-PMT('High Level Dashboard'!$C$10,'High Level Dashboard'!$C$12-'High Level Dashboard'!$C$11+1, (HLOOKUP('High Level Dashboard'!C$64-(ROUNDDOWN('High Level Dashboard'!$C$11,0)),'High Level Dashboard'!$B$64:$AV$65,2,FALSE)*('High Level Dashboard'!$C$11-ROUNDDOWN('High Level Dashboard'!$C$11,0)))),0) + (((SUMIFS('High Level Dashboard'!$B$65:$AV$65,'High Level Dashboard'!$B$64:$AV$64,">"&'High Level Dashboard'!C$64-ROUNDDOWN('High Level Dashboard'!$C$11,0),'High Level Dashboard'!$B$64:$AV$64,"<="&'High Level Dashboard'!C$64)+(IFERROR(SUMIF('High Level Dashboard'!$B$64:$AV$64,ROUNDDOWN('High Level Dashboard'!C$64-'High Level Dashboard'!$C$11,0)+1,'High Level Dashboard'!$B$65:$AV$65)*(1-('High Level Dashboard'!$C$11-ROUNDDOWN('High Level Dashboard'!$C$11,0))),"")))*'High Level Dashboard'!$C$10) )) -> 40.982139 | E97: =$B$80*'High Level Dashboard'!$C$9* (-PMT('High Level Dashboard'!$C$10,'High Level Dashboard'!$C$12-'High Level Dashboard'!$C$11+1, SUMIFS('High Level Dashboard'!$B$65:$AV$65,'High Level Dashboard'!$B$64:$AV$64,">="&('High Level Dashboard'!D$64-(ROUNDDOWN('High Level Dashboard'!$C$12,0))+1),'High Level Dashboard'!$B$64:$AV$64,"<="&('High Level Dashboard'!D$64-(ROUNDUP('High Level Dashboard'!$C$11,0))))) + IFERROR(-PMT('High Level Dashboard'!$C$10,'High Level Dashboard'!$C$12-'High Level Dashboard'!$C$11+1, (HLOOKUP('High Level Dashboard'!D$64-(ROUNDUP('High Level Dashboard'!$C$12,0))+1,'High Level Dashboard'!$B$64:$AV$65,2,FALSE))*('High Level Dashboard'!$C$12-(ROUNDDOWN('High Level Dashboard'!$C$12,0)))),0) + IFERROR(-PMT('High Level Dashboard'!$C$10,'High Level Dashboard'!$C$12-'High Level Dashboard'!$C$11+1, (HLOOKUP('High Level Dashboard'!D$64-(ROUNDDOWN('High Level Dashboard'!$C$11,0)),'High Level Dashboard'!$B$64:$AV$65,2,FALSE)*('High Level Dashboard'!$C$11-ROUNDDOWN('High Level Dashboard'!$C$11,0)))),0) + (((SUMIFS('High Level Dashboard'!$B$65:$AV$65,'High Level Dashboard'!$B$64:$AV$64,">"&'High Level Dashboard'!D$64-ROUNDDOWN('High Level Dashboard'!$C$11,0),'High Level Dashboard'!$B$64:$AV$64,"<="&'High Level Dashboard'!D$64)+(IFERROR(SUMIF('High Level Dashboard'!$B$64:$AV$64,ROUNDDOWN('High Level Dashboard'!D$64-'High Level Dashboard'!$C$11,0)+1,'High Level Dashboard'!$B$65:$AV$65)*(1-('High Level Dashboard'!$C$11-ROUNDDOWN('High Level Dashboard'!$C$11,0))),"")))*'High Level Dashboard'!$C$10) )) -> 61.979556 | F97: =$B$80*'High Level Dashboard'!$C$9* (-PMT('High Level Dashboard'!$C$10,'High Level Dashboard'!$C$12-'High Level Dashboard'!$C$11+1, SUMIFS('High Level Dashboard'!$B$65:$AV$65,'High Level Dashboard'!$B$64:$AV$64,">="&('High Level Dashboard'!E$64-(ROUNDDOWN('High Level Dashboard'!$C$12,0))+1),'High Level Dashboard'!$B$64:$AV$64,"<="&('High Level Dashboard'!E$64-(ROUNDUP('High Level Dashboard'!$C$11,0))))) + IFERROR(-PMT('High Level Dashboard'!$C$10,'High Level Dashboard'!$C$12-'High Level Dashboard'!$C$11+1, (HLOOKUP('High Level Dashboard'!E$64-(ROUNDUP('High Level Dashboard'!$C$12,0))+1,'High Level Dashboard'!$B$64:$AV$65,2,FALSE))*('High Level Dashboard'!$C$12-(ROUNDDOWN('High Level Dashboard'!$C$12,0)))),0) + IFERROR(-PMT('High Level Dashboard'!$C$10,'High Level Dashboard'!$C$12-'High Level Dashboard'!$C$11+1, (HLOOKUP('High Level Dashboard'!E$64-(ROUNDDOWN('High Level Dashboard'!$C$11,0)),'High Level Dashboard'!$B$64:$AV$65,2,FALSE)*('High Level Dashboard'!$C$11-ROUNDDOWN('High Level Dashboard'!$C$11,0)))),0) + (((SUMIFS('High Level Dashboard'!$B$65:$AV$65,'High Level Dashboard'!$B$64:$AV$64,">"&'High Level Dashboard'!E$64-ROUNDDOWN('High Level Dashboard'!$C$11,0),'High Level Dashboard'!$B$64:$AV$64,"<="&'High Level Dashboard'!E$64)+(IFERROR(SUMIF('High Level Dashboard'!$B$64:$AV$64,ROUNDDOWN('High Level Dashboard'!E$64-'High Level Dashboard'!$C$11,0)+1,'High Level Dashboard'!$B$65:$AV$65)*(1-('High Level Dashboard'!$C$11-ROUNDDOWN('High Level Dashboard'!$C$11,0))),"")))*'High Level Dashboard'!$C$10) )) -> 80.42548 | G97: =$B$80*'High Level Dashboard'!$C$9* (-PMT('High Level Dashboard'!$C$10,'High Level Dashboard'!$C$12-'High Level Dashboard'!$C$11+1, SUMIFS('High Level Dashboard'!$B$65:$AV$65,'High Level Dashboard'!$B$64:$AV$64,">="&('High Level Dashboard'!F$64-(ROUNDDOWN('High Level Dashboard'!$C$12,0))+1),'High Level Dashboard'!$B$64:$AV$64,"<="&('High Level Dashboard'!F$64-(ROUNDUP('High Level Dashboard'!$C$11,0))))) + IFERROR(-PMT('High Level Dashboard'!$C$10,'High Level Dashboard'!$C$12-'High Level Dashboard'!$C$11+1, (HLOOKUP('High Level Dashboard'!F$64-(ROUNDUP('High Level Dashboard'!$C$12,0))+1,'High Level Dashboard'!$B$64:$AV$65,2,FALSE))*('High Level Dashboard'!$C$12-(ROUNDDOWN('High Level Dashboard'!$C$12,0)))),0) + IFERROR(-PMT('High Level Dashboard'!$C$10,'High Level Dashboard'!$C$12-'High Level Dashboard'!$C$11+1, (HLOOKUP('High Level Dashboard'!F$64-(ROUNDDOWN('High Level Dashboard'!$C$11,0)),'High Level Dashboard'!$B$64:$AV$65,2,FALSE)*('High Level Dashboard'!$C$11-ROUNDDOWN('High Level Dashboard'!$C$11,0)))),0) + (((SUMIFS('High Level Dashboard'!$B$65:$AV$65,'High Level Dashboard'!$B$64:$AV$64,">"&'High Level Dashboard'!F$64-ROUNDDOWN('High Level Dashboard'!$C$11,0),'High Level Dashboard'!$B$64:$AV$64,"<="&'High Level Dashboard'!F$64)+(IFERROR(SUMIF('High Level Dashboard'!$B$64:$AV$64,ROUNDDOWN('High Level Dashboard'!F$64-'High Level Dashboard'!$C$11,0)+1,'High Level Dashboard'!$B$65:$AV$65)*(1-('High Level Dashboard'!$C$11-ROUNDDOWN('High Level Dashboard'!$C$11,0))),"")))*'High Level Dashboard'!$C$10) )) -> 118.95317 | H97: =$B$80*'High Level Dashboard'!$C$9* (-PMT('High Level Dashboard'!$C$10,'High Level Dashboard'!$C$12-'High Level Dashboard'!$C$11+1, SUMIFS('High Level Dashboard'!$B$65:$AV$65,'High Level Dashboard'!$B$64:$AV$64,">="&('High Level Dashboard'!G$64-(ROUNDDOWN('High Level Dashboard'!$C$12,0))+1),'High Level Dashboard'!$B$64:$AV$64,"<="&('High Level Dashboard'!G$64-(ROUNDUP('High Level Dashboard'!$C$11,0))))) + IFERROR(-PMT('High Level Dashboard'!$C$10,'High Level Dashboard'!$C$12-'High Level Dashboard'!$C$11+1, (HLOOKUP('High Level Dashboard'!G$64-(ROUNDUP('High Level Dashboard'!$C$12,0))+1,'High Level Dashboard'!$B$64:$AV$65,2,FALSE))*('High Level Dashboard'!$C$12-(ROUNDDOWN('High Level Dashboard'!$C$12,0)))),0) + IFERROR(-PMT('High Level Dashboard'!$C$10,'High Level Dashboard'!$C$12-'High Level Dashboard'!$C$11+1, (HLOOKUP('High Level Dashboard'!G$64-(ROUNDDOWN('High Level Dashboard'!$C$11,0)),'High Level Dashboard'!$B$64:$AV$65,2,FALSE)*('High Level Dashboard'!$C$11-ROUNDDOWN('High Level Dashboard'!$C$11,0)))),0) + (((SUMIFS('High Level Dashboard'!$B$65:$AV$65,'High Level Dashboard'!$B$64:$AV$64,">"&'High Level Dashboard'!G$64-ROUNDDOWN('High Level Dashboard'!$C$11,0),'High Level Dashboard'!$B$64:$AV$64,"<="&'High Level Dashboard'!G$64)+(IFERROR(SUMIF('High Level Dashboard'!$B$64:$AV$64,ROUNDDOWN('High Level Dashboard'!G$64-'High Level Dashboard'!$C$11,0)+1,'High Level Dashboard'!$B$65:$AV$65)*(1-('High Level Dashboard'!$C$11-ROUNDDOWN('High Level Dashboard'!$C$11,0))),"")))*'High Level Dashboard'!$C$10) )) -> 141.7067 | I97: =$B$80*'High Level Dashboard'!$C$9* (-PMT('High Level Dashboard'!$C$10,'High Level Dashboard'!$C$12-'High Level Dashboard'!$C$11+1, SUMIFS('High Level Dashboard'!$B$65:$AV$65,'High Level Dashboard'!$B$64:$AV$64,">="&('High Level Dashboard'!H$64-(ROUNDDOWN('High Level Dashboard'!$C$12,0))+1),'High Level Dashboard'!$B$64:$AV$64,"<="&('High Level Dashboard'!H$64-(ROUNDUP('High Level Dashboard'!$C$11,0))))) + IFERROR(-PMT('High Level Dashboard'!$C$10,'High Level Dashboard'!$C$12-'High Level Dashboard'!$C$11+1, (HLOOKUP('High Level Dashboard'!H$64-(ROUNDUP('High Level Dashboard'!$C$12,0))+1,'High Level Dashboard'!$B$64:$AV$65,2,FALSE))*('High Level Dashboard'!$C$12-(ROUNDDOWN('High Level Dashboard'!$C$12,0)))),0) + IFERROR(-PMT('High Level Dashboard'!$C$10,'High Level Dashboard'!$C$12-'High Level Dashboard'!$C$11+1, (HLOOKUP('High Level Dashboard'!H$64-(ROUNDDOWN('High Level Dashboard'!$C$11,0)),'High Level Dashboard'!$B$64:$AV$65,2,FALSE)*('High Level Dashboard'!$C$11-ROUNDDOWN('High Level Dashboard'!$C$11,0)))),0) + (((SUMIFS('High Level Dashboard'!$B$65:$AV$65,'High Level Dashboard'!$B$64:$AV$64,">"&'High Level Dashboard'!H$64-ROUNDDOWN('High Level Dashboard'!$C$11,0),'High Level Dashboard'!$B$64:$AV$64,"<="&'High Level Dashboard'!H$64)+(IFERROR(SUMIF('High Level Dashboard'!$B$64:$AV$64,ROUNDDOWN('High Level Dashboard'!H$64-'High Level Dashboard'!$C$11,0)+1,'High Level Dashboard'!$B$65:$AV$65)*(1-('High Level Dashboard'!$C$11-ROUNDDOWN('High Level Dashboard'!$C$11,0))),"")))*'High Level Dashboard'!$C$10) )) -> 198.47026 | J97: =$B$80*'High Level Dashboard'!$C$9* (-PMT('High Level Dashboard'!$C$10,'High Level Dashboard'!$C$12-'High Level Dashboard'!$C$11+1, SUMIFS('High Level Dashboard'!$B$65:$AV$65,'High Level Dashboard'!$B$64:$AV$64,">="&('High Level Dashboard'!I$64-(ROUNDDOWN('High Level Dashboard'!$C$12,0))+1),'High Level Dashboard'!$B$64:$AV$64,"<="&('High Level Dashboard'!I$64-(ROUNDUP('High Level Dashboard'!$C$11,0))))) + IFERROR(-PMT('High Level Dashboard'!$C$10,'High Level Dashboard'!$C$12-'High Level Dashboard'!$C$11+1, (HLOOKUP('High Level Dashboard'!I$64-(ROUNDUP('High Level Dashboard'!$C$12,0))+1,'High Level Dashboard'!$B$64:$AV$65,2,FALSE))*('High Level Dashboard'!$C$12-(ROUNDDOWN('High Level Dashboard'!$C$12,0)))),0) + IFERROR(-PMT('High Level Dashboard'!$C$10,'High Level Dashboard'!$C$12-'High Level Dashboard'!$C$11+1, (HLOOKUP('High Level Dashboard'!I$64-(ROUNDDOWN('High Level Dashboard'!$C$11,0)),'High Level Dashboard'!$B$64:$AV$65,2,FALSE)*('High Level Dashboard'!$C$11-ROUNDDOWN('High Level Dashboard'!$C$11,0)))),0) + (((SUMIFS('High Level Dashboard'!$B$65:$AV$65,'High Level Dashboard'!$B$64:$AV$64,">"&'High Level Dashboard'!I$64-ROUNDDOWN('High Level Dashboard'!$C$11,0),'High Level Dashboard'!$B$64:$AV$64,"<="&'High Level Dashboard'!I$64)+(IFERROR(SUMIF('High Level Dashboard'!$B$64:$AV$64,ROUNDDOWN('High Level Dashboard'!I$64-'High Level Dashboard'!$C$11,0)+1,'High Level Dashboard'!$B$65:$AV$65)*(1-('High Level Dashboard'!$C$11-ROUNDDOWN('High Level Dashboard'!$C$11,0))),"")))*'High Level Dashboard'!$C$10) )) -> 252.08784 | ... AV97: =$B$80*'High Level Dashboard'!$C$9* (-PMT('High Level Dashboard'!$C$10,'High Level Dashboard'!$C$12-'High Level Dashboard'!$C$11+1, SUMIFS('High Level Dashboard'!$B$65:$AV$65,'High Level Dashboard'!$B$64:$AV$64,">="&('High Level Dashboard'!AU$64-(ROUNDDOWN('High Level Dashboard'!$C$12,0))+1),'High Level Dashboard'!$B$64:$AV$64,"<="&('High Level Dashboard'!AU$64-(ROUNDUP('High Level Dashboard'!$C$11,0))))) + IFERROR(-PMT('High Level Dashboard'!$C$10,'High Level Dashboard'!$C$12-'High Level Dashboard'!$C$11+1, (HLOOKUP('High Level Dashboard'!AU$64-(ROUNDUP('High Level Dashboard'!$C$12,0))+1,'High Level Dashboard'!$B$64:$AV$65,2,FALSE))*('High Level Dashboard'!$C$12-(ROUNDDOWN('High Level Dashboard'!$C$12,0)))),0) + IFERROR(-PMT('High Level Dashboard'!$C$10,'High Level Dashboard'!$C$12-'High Level Dashboard'!$C$11+1, (HLOOKUP('High Level Dashboard'!AU$64-(ROUNDDOWN('High Level Dashboard'!$C$11,0)),'High Level Dashboard'!$B$64:$AV$65,2,FALSE)*('High Level Dashboard'!$C$11-ROUNDDOWN('High Level Dashboard'!$C$11,0)))),0) + (((SUMIFS('High Level Dashboard'!$B$65:$AV$65,'High Level Dashboard'!$B$64:$AV$64,">"&'High Level Dashboard'!AU$64-ROUNDDOWN('High Level Dashboard'!$C$11,0),'High Level Dashboard'!$B$64:$AV$64,"<="&'High Level Dashboard'!AU$64)+(IFERROR(SUMIF('High Level Dashboard'!$B$64:$AV$64,ROUNDDOWN('High Level Dashboard'!AU$64-'High Level Dashboard'!$C$11,0)+1,'High Level Dashboard'!$B$65:$AV$65)*(1-('High Level Dashboard'!$C$11-ROUNDDOWN('High Level Dashboard'!$C$11,0))),"")))*'High Level Dashboard'!$C$10) )) -> 3260.0348
A98: Loans - Concessional Domestic Finance (Conc DPS) | C98: =$B$82*'High Level Dashboard'!$C$15* (-PMT('High Level Dashboard'!$C$16,'High Level Dashboard'!$C$18-'High Level Dashboard'!$C$17+1, SUMIFS('High Level Dashboard'!$B$65:$AV$65,'High Level Dashboard'!$B$64:$AV$64,">="&('High Level Dashboard'!B$64-(ROUNDDOWN('High Level Dashboard'!$C$18,0))+1),'High Level Dashboard'!$B$64:$AV$64,"<="&('High Level Dashboard'!B$64-(ROUNDUP('High Level Dashboard'!$C$17,0))))) + IFERROR(-PMT('High Level Dashboard'!$C$16,'High Level Dashboard'!$C$18-'High Level Dashboard'!$C$17+1, (HLOOKUP('High Level Dashboard'!B$64-(ROUNDUP('High Level Dashboard'!$C$18,0))+1,'High Level Dashboard'!$B$64:$AV$65,2,FALSE))*('High Level Dashboard'!$C$18-(ROUNDDOWN('High Level Dashboard'!$C$18,0)))),0) + IFERROR(-PMT('High Level Dashboard'!$C$16,'High Level Dashboard'!$C$18-'High Level Dashboard'!$C$17+1, (HLOOKUP('High Level Dashboard'!B$64-(ROUNDDOWN('High Level Dashboard'!$C$17,0)),'High Level Dashboard'!$B$64:$AV$65,2,FALSE)*('High Level Dashboard'!$C$17-ROUNDDOWN('High Level Dashboard'!$C$17,0)))),0) + (((SUMIFS('High Level Dashboard'!$B$65:$AV$65,'High Level Dashboard'!$B$64:$AV$64,">"&'High Level Dashboard'!B$64-ROUNDDOWN('High Level Dashboard'!$C$17,0),'High Level Dashboard'!$B$64:$AV$64,"<="&'High Level Dashboard'!B$64)+(IFERROR(SUMIF('High Level Dashboard'!$B$64:$AV$64,ROUNDDOWN('High Level Dashboard'!B$64-'High Level Dashboard'!$C$17,0)+1,'High Level Dashboard'!$B$65:$AV$65)*(1-('High Level Dashboard'!$C$17-ROUNDDOWN('High Level Dashboard'!$C$17,0))),"")))*'High Level Dashboard'!$C$16) )) -> 0.3278442 | D98: =$B$82*'High Level Dashboard'!$C$15* (-PMT('High Level Dashboard'!$C$16,'High Level Dashboard'!$C$18-'High Level Dashboard'!$C$17+1, SUMIFS('High Level Dashboard'!$B$65:$AV$65,'High Level Dashboard'!$B$64:$AV$64,">="&('High Level Dashboard'!C$64-(ROUNDDOWN('High Level Dashboard'!$C$18,0))+1),'High Level Dashboard'!$B$64:$AV$64,"<="&('High Level Dashboard'!C$64-(ROUNDUP('High Level Dashboard'!$C$17,0))))) + IFERROR(-PMT('High Level Dashboard'!$C$16,'High Level Dashboard'!$C$18-'High Level Dashboard'!$C$17+1, (HLOOKUP('High Level Dashboard'!C$64-(ROUNDUP('High Level Dashboard'!$C$18,0))+1,'High Level Dashboard'!$B$64:$AV$65,2,FALSE))*('High Level Dashboard'!$C$18-(ROUNDDOWN('High Level Dashboard'!$C$18,0)))),0) + IFERROR(-PMT('High Level Dashboard'!$C$16,'High Level Dashboard'!$C$18-'High Level Dashboard'!$C$17+1, (HLOOKUP('High Level Dashboard'!C$64-(ROUNDDOWN('High Level Dashboard'!$C$17,0)),'High Level Dashboard'!$B$64:$AV$65,2,FALSE)*('High Level Dashboard'!$C$17-ROUNDDOWN('High Level Dashboard'!$C$17,0)))),0) + (((SUMIFS('High Level Dashboard'!$B$65:$AV$65,'High Level Dashboard'!$B$64:$AV$64,">"&'High Level Dashboard'!C$64-ROUNDDOWN('High Level Dashboard'!$C$17,0),'High Level Dashboard'!$B$64:$AV$64,"<="&'High Level Dashboard'!C$64)+(IFERROR(SUMIF('High Level Dashboard'!$B$64:$AV$64,ROUNDDOWN('High Level Dashboard'!C$64-'High Level Dashboard'!$C$17,0)+1,'High Level Dashboard'!$B$65:$AV$65)*(1-('High Level Dashboard'!$C$17-ROUNDDOWN('High Level Dashboard'!$C$17,0))),"")))*'High Level Dashboard'!$C$16) )) -> 0.67150439 | E98: =$B$82*'High Level Dashboard'!$C$15* (-PMT('High Level Dashboard'!$C$16,'High Level Dashboard'!$C$18-'High Level Dashboard'!$C$17+1, SUMIFS('High Level Dashboard'!$B$65:$AV$65,'High Level Dashboard'!$B$64:$AV$64,">="&('High Level Dashboard'!D$64-(ROUNDDOWN('High Level Dashboard'!$C$18,0))+1),'High Level Dashboard'!$B$64:$AV$64,"<="&('High Level Dashboard'!D$64-(ROUNDUP('High Level Dashboard'!$C$17,0))))) + IFERROR(-PMT('High Level Dashboard'!$C$16,'High Level Dashboard'!$C$18-'High Level Dashboard'!$C$17+1, (HLOOKUP('High Level Dashboard'!D$64-(ROUNDUP('High Level Dashboard'!$C$18,0))+1,'High Level Dashboard'!$B$64:$AV$65,2,FALSE))*('High Level Dashboard'!$C$18-(ROUNDDOWN('High Level Dashboard'!$C$18,0)))),0) + IFERROR(-PMT('High Level Dashboard'!$C$16,'High Level Dashboard'!$C$18-'High Level Dashboard'!$C$17+1, (HLOOKUP('High Level Dashboard'!D$64-(ROUNDDOWN('High Level Dashboard'!$C$17,0)),'High Level Dashboard'!$B$64:$AV$65,2,FALSE)*('High Level Dashboard'!$C$17-ROUNDDOWN('High Level Dashboard'!$C$17,0)))),0) + (((SUMIFS('High Level Dashboard'!$B$65:$AV$65,'High Level Dashboard'!$B$64:$AV$64,">"&'High Level Dashboard'!D$64-ROUNDDOWN('High Level Dashboard'!$C$17,0),'High Level Dashboard'!$B$64:$AV$64,"<="&'High Level Dashboard'!D$64)+(IFERROR(SUMIF('High Level Dashboard'!$B$64:$AV$64,ROUNDDOWN('High Level Dashboard'!D$64-'High Level Dashboard'!$C$17,0)+1,'High Level Dashboard'!$B$65:$AV$65)*(1-('High Level Dashboard'!$C$17-ROUNDDOWN('High Level Dashboard'!$C$17,0))),"")))*'High Level Dashboard'!$C$16) )) -> 1.0155532 | F98: =$B$82*'High Level Dashboard'!$C$15* (-PMT('High Level Dashboard'!$C$16,'High Level Dashboard'!$C$18-'High Level Dashboard'!$C$17+1, SUMIFS('High Level Dashboard'!$B$65:$AV$65,'High Level Dashboard'!$B$64:$AV$64,">="&('High Level Dashboard'!E$64-(ROUNDDOWN('High Level Dashboard'!$C$18,0))+1),'High Level Dashboard'!$B$64:$AV$64,"<="&('High Level Dashboard'!E$64-(ROUNDUP('High Level Dashboard'!$C$17,0))))) + IFERROR(-PMT('High Level Dashboard'!$C$16,'High Level Dashboard'!$C$18-'High Level Dashboard'!$C$17+1, (HLOOKUP('High Level Dashboard'!E$64-(ROUNDUP('High Level Dashboard'!$C$18,0))+1,'High Level Dashboard'!$B$64:$AV$65,2,FALSE))*('High Level Dashboard'!$C$18-(ROUNDDOWN('High Level Dashboard'!$C$18,0)))),0) + IFERROR(-PMT('High Level Dashboard'!$C$16,'High Level Dashboard'!$C$18-'High Level Dashboard'!$C$17+1, (HLOOKUP('High Level Dashboard'!E$64-(ROUNDDOWN('High Level Dashboard'!$C$17,0)),'High Level Dashboard'!$B$64:$AV$65,2,FALSE)*('High Level Dashboard'!$C$17-ROUNDDOWN('High Level Dashboard'!$C$17,0)))),0) + (((SUMIFS('High Level Dashboard'!$B$65:$AV$65,'High Level Dashboard'!$B$64:$AV$64,">"&'High Level Dashboard'!E$64-ROUNDDOWN('High Level Dashboard'!$C$17,0),'High Level Dashboard'!$B$64:$AV$64,"<="&'High Level Dashboard'!E$64)+(IFERROR(SUMIF('High Level Dashboard'!$B$64:$AV$64,ROUNDDOWN('High Level Dashboard'!E$64-'High Level Dashboard'!$C$17,0)+1,'High Level Dashboard'!$B$65:$AV$65)*(1-('High Level Dashboard'!$C$17-ROUNDDOWN('High Level Dashboard'!$C$17,0))),"")))*'High Level Dashboard'!$C$16) )) -> 1.3177951 | G98: =$B$82*'High Level Dashboard'!$C$15* (-PMT('High Level Dashboard'!$C$16,'High Level Dashboard'!$C$18-'High Level Dashboard'!$C$17+1, SUMIFS('High Level Dashboard'!$B$65:$AV$65,'High Level Dashboard'!$B$64:$AV$64,">="&('High Level Dashboard'!F$64-(ROUNDDOWN('High Level Dashboard'!$C$18,0))+1),'High Level Dashboard'!$B$64:$AV$64,"<="&('High Level Dashboard'!F$64-(ROUNDUP('High Level Dashboard'!$C$17,0))))) + IFERROR(-PMT('High Level Dashboard'!$C$16,'High Level Dashboard'!$C$18-'High Level Dashboard'!$C$17+1, (HLOOKUP('High Level Dashboard'!F$64-(ROUNDUP('High Level Dashboard'!$C$18,0))+1,'High Level Dashboard'!$B$64:$AV$65,2,FALSE))*('High Level Dashboard'!$C$18-(ROUNDDOWN('High Level Dashboard'!$C$18,0)))),0) + IFERROR(-PMT('High Level Dashboard'!$C$16,'High Level Dashboard'!$C$18-'High Level Dashboard'!$C$17+1, (HLOOKUP('High Level Dashboard'!F$64-(ROUNDDOWN('High Level Dashboard'!$C$17,0)),'High Level Dashboard'!$B$64:$AV$65,2,FALSE)*('High Level Dashboard'!$C$17-ROUNDDOWN('High Level Dashboard'!$C$17,0)))),0) + (((SUMIFS('High Level Dashboard'!$B$65:$AV$65,'High Level Dashboard'!$B$64:$AV$64,">"&'High Level Dashboard'!F$64-ROUNDDOWN('High Level Dashboard'!$C$17,0),'High Level Dashboard'!$B$64:$AV$64,"<="&'High Level Dashboard'!F$64)+(IFERROR(SUMIF('High Level Dashboard'!$B$64:$AV$64,ROUNDDOWN('High Level Dashboard'!F$64-'High Level Dashboard'!$C$17,0)+1,'High Level Dashboard'!$B$65:$AV$65)*(1-('High Level Dashboard'!$C$17-ROUNDDOWN('High Level Dashboard'!$C$17,0))),"")))*'High Level Dashboard'!$C$16) )) -> 1.9490827 | H98: =$B$82*'High Level Dashboard'!$C$15* (-PMT('High Level Dashboard'!$C$16,'High Level Dashboard'!$C$18-'High Level Dashboard'!$C$17+1, SUMIFS('High Level Dashboard'!$B$65:$AV$65,'High Level Dashboard'!$B$64:$AV$64,">="&('High Level Dashboard'!G$64-(ROUNDDOWN('High Level Dashboard'!$C$18,0))+1),'High Level Dashboard'!$B$64:$AV$64,"<="&('High Level Dashboard'!G$64-(ROUNDUP('High Level Dashboard'!$C$17,0))))) + IFERROR(-PMT('High Level Dashboard'!$C$16,'High Level Dashboard'!$C$18-'High Level Dashboard'!$C$17+1, (HLOOKUP('High Level Dashboard'!G$64-(ROUNDUP('High Level Dashboard'!$C$18,0))+1,'High Level Dashboard'!$B$64:$AV$65,2,FALSE))*('High Level Dashboard'!$C$18-(ROUNDDOWN('High Level Dashboard'!$C$18,0)))),0) + IFERROR(-PMT('High Level Dashboard'!$C$16,'High Level Dashboard'!$C$18-'High Level Dashboard'!$C$17+1, (HLOOKUP('High Level Dashboard'!G$64-(ROUNDDOWN('High Level Dashboard'!$C$17,0)),'High Level Dashboard'!$B$64:$AV$65,2,FALSE)*('High Level Dashboard'!$C$17-ROUNDDOWN('High Level Dashboard'!$C$17,0)))),0) + (((SUMIFS('High Level Dashboard'!$B$65:$AV$65,'High Level Dashboard'!$B$64:$AV$64,">"&'High Level Dashboard'!G$64-ROUNDDOWN('High Level Dashboard'!$C$17,0),'High Level Dashboard'!$B$64:$AV$64,"<="&'High Level Dashboard'!G$64)+(IFERROR(SUMIF('High Level Dashboard'!$B$64:$AV$64,ROUNDDOWN('High Level Dashboard'!G$64-'High Level Dashboard'!$C$17,0)+1,'High Level Dashboard'!$B$65:$AV$65)*(1-('High Level Dashboard'!$C$17-ROUNDDOWN('High Level Dashboard'!$C$17,0))),"")))*'High Level Dashboard'!$C$16) )) -> 2.3219059 | I98: =$B$82*'High Level Dashboard'!$C$15* (-PMT('High Level Dashboard'!$C$16,'High Level Dashboard'!$C$18-'High Level Dashboard'!$C$17+1, SUMIFS('High Level Dashboard'!$B$65:$AV$65,'High Level Dashboard'!$B$64:$AV$64,">="&('High Level Dashboard'!H$64-(ROUNDDOWN('High Level Dashboard'!$C$18,0))+1),'High Level Dashboard'!$B$64:$AV$64,"<="&('High Level Dashboard'!H$64-(ROUNDUP('High Level Dashboard'!$C$17,0))))) + IFERROR(-PMT('High Level Dashboard'!$C$16,'High Level Dashboard'!$C$18-'High Level Dashboard'!$C$17+1, (HLOOKUP('High Level Dashboard'!H$64-(ROUNDUP('High Level Dashboard'!$C$18,0))+1,'High Level Dashboard'!$B$64:$AV$65,2,FALSE))*('High Level Dashboard'!$C$18-(ROUNDDOWN('High Level Dashboard'!$C$18,0)))),0) + IFERROR(-PMT('High Level Dashboard'!$C$16,'High Level Dashboard'!$C$18-'High Level Dashboard'!$C$17+1, (HLOOKUP('High Level Dashboard'!H$64-(ROUNDDOWN('High Level Dashboard'!$C$17,0)),'High Level Dashboard'!$B$64:$AV$65,2,FALSE)*('High Level Dashboard'!$C$17-ROUNDDOWN('High Level Dashboard'!$C$17,0)))),0) + (((SUMIFS('High Level Dashboard'!$B$65:$AV$65,'High Level Dashboard'!$B$64:$AV$64,">"&'High Level Dashboard'!H$64-ROUNDDOWN('High Level Dashboard'!$C$17,0),'High Level Dashboard'!$B$64:$AV$64,"<="&'High Level Dashboard'!H$64)+(IFERROR(SUMIF('High Level Dashboard'!$B$64:$AV$64,ROUNDDOWN('High Level Dashboard'!H$64-'High Level Dashboard'!$C$17,0)+1,'High Level Dashboard'!$B$65:$AV$65)*(1-('High Level Dashboard'!$C$17-ROUNDDOWN('High Level Dashboard'!$C$17,0))),"")))*'High Level Dashboard'!$C$16) )) -> 2.7463033 | J98: =$B$82*'High Level Dashboard'!$C$15* (-PMT('High Level Dashboard'!$C$16,'High Level Dashboard'!$C$18-'High Level Dashboard'!$C$17+1, SUMIFS('High Level Dashboard'!$B$65:$AV$65,'High Level Dashboard'!$B$64:$AV$64,">="&('High Level Dashboard'!I$64-(ROUNDDOWN('High Level Dashboard'!$C$18,0))+1),'High Level Dashboard'!$B$64:$AV$64,"<="&('High Level Dashboard'!I$64-(ROUNDUP('High Level Dashboard'!$C$17,0))))) + IFERROR(-PMT('High Level Dashboard'!$C$16,'High Level Dashboard'!$C$18-'High Level Dashboard'!$C$17+1, (HLOOKUP('High Level Dashboard'!I$64-(ROUNDUP('High Level Dashboard'!$C$18,0))+1,'High Level Dashboard'!$B$64:$AV$65,2,FALSE))*('High Level Dashboard'!$C$18-(ROUNDDOWN('High Level Dashboard'!$C$18,0)))),0) + IFERROR(-PMT('High Level Dashboard'!$C$16,'High Level Dashboard'!$C$18-'High Level Dashboard'!$C$17+1, (HLOOKUP('High Level Dashboard'!I$64-(ROUNDDOWN('High Level Dashboard'!$C$17,0)),'High Level Dashboard'!$B$64:$AV$65,2,FALSE)*('High Level Dashboard'!$C$17-ROUNDDOWN('High Level Dashboard'!$C$17,0)))),0) + (((SUMIFS('High Level Dashboard'!$B$65:$AV$65,'High Level Dashboard'!$B$64:$AV$64,">"&'High Level Dashboard'!I$64-ROUNDDOWN('High Level Dashboard'!$C$17,0),'High Level Dashboard'!$B$64:$AV$64,"<="&'High Level Dashboard'!I$64)+(IFERROR(SUMIF('High Level Dashboard'!$B$64:$AV$64,ROUNDDOWN('High Level Dashboard'!I$64-'High Level Dashboard'!$C$17,0)+1,'High Level Dashboard'!$B$65:$AV$65)*(1-('High Level Dashboard'!$C$17-ROUNDDOWN('High Level Dashboard'!$C$17,0))),"")))*'High Level Dashboard'!$C$16) )) -> 3.1116964 | ... AV98: =$B$82*'High Level Dashboard'!$C$15* (-PMT('High Level Dashboard'!$C$16,'High Level Dashboard'!$C$18-'High Level Dashboard'!$C$17+1, SUMIFS('High Level Dashboard'!$B$65:$AV$65,'High Level Dashboard'!$B$64:$AV$64,">="&('High Level Dashboard'!AU$64-(ROUNDDOWN('High Level Dashboard'!$C$18,0))+1),'High Level Dashboard'!$B$64:$AV$64,"<="&('High Level Dashboard'!AU$64-(ROUNDUP('High Level Dashboard'!$C$17,0))))) + IFERROR(-PMT('High Level Dashboard'!$C$16,'High Level Dashboard'!$C$18-'High Level Dashboard'!$C$17+1, (HLOOKUP('High Level Dashboard'!AU$64-(ROUNDUP('High Level Dashboard'!$C$18,0))+1,'High Level Dashboard'!$B$64:$AV$65,2,FALSE))*('High Level Dashboard'!$C$18-(ROUNDDOWN('High Level Dashboard'!$C$18,0)))),0) + IFERROR(-PMT('High Level Dashboard'!$C$16,'High Level Dashboard'!$C$18-'High Level Dashboard'!$C$17+1, (HLOOKUP('High Level Dashboard'!AU$64-(ROUNDDOWN('High Level Dashboard'!$C$17,0)),'High Level Dashboard'!$B$64:$AV$65,2,FALSE)*('High Level Dashboard'!$C$17-ROUNDDOWN('High Level Dashboard'!$C$17,0)))),0) + (((SUMIFS('High Level Dashboard'!$B$65:$AV$65,'High Level Dashboard'!$B$64:$AV$64,">"&'High Level Dashboard'!AU$64-ROUNDDOWN('High Level Dashboard'!$C$17,0),'High Level Dashboard'!$B$64:$AV$64,"<="&'High Level Dashboard'!AU$64)+(IFERROR(SUMIF('High Level Dashboard'!$B$64:$AV$64,ROUNDDOWN('High Level Dashboard'!AU$64-'High Level Dashboard'!$C$17,0)+1,'High Level Dashboard'!$B$65:$AV$65)*(1-('High Level Dashboard'!$C$17-ROUNDDOWN('High Level Dashboard'!$C$17,0))),"")))*'High Level Dashboard'!$C$16) )) -> 44.81113
A99: Loans - Commercial International Finance (Comm Intl) | C99: =$B$83*'High Level Dashboard'!$C$21* (-PMT('High Level Dashboard'!$C$22,'High Level Dashboard'!$C$24-'High Level Dashboard'!$C$23+1, SUMIFS('High Level Dashboard'!$B$65:$AV$65,'High Level Dashboard'!$B$64:$AV$64,">="&('High Level Dashboard'!B$64-(ROUNDDOWN('High Level Dashboard'!$C$24,0))+1),'High Level Dashboard'!$B$64:$AV$64,"<="&('High Level Dashboard'!B$64-(ROUNDUP('High Level Dashboard'!$C$23,0))))) + IFERROR(-PMT('High Level Dashboard'!$C$22,'High Level Dashboard'!$C$24-'High Level Dashboard'!$C$23+1, (HLOOKUP('High Level Dashboard'!B$64-(ROUNDUP('High Level Dashboard'!$C$24,0))+1,'High Level Dashboard'!$B$64:$AV$65,2,FALSE))*('High Level Dashboard'!$C$24-(ROUNDDOWN('High Level Dashboard'!$C$24,0)))),0) + IFERROR(-PMT('High Level Dashboard'!$C$22,'High Level Dashboard'!$C$24-'High Level Dashboard'!$C$23+1, (HLOOKUP('High Level Dashboard'!B$64-(ROUNDDOWN('High Level Dashboard'!$C$23,0)),'High Level Dashboard'!$B$64:$AV$65,2,FALSE)*('High Level Dashboard'!$C$23-ROUNDDOWN('High Level Dashboard'!$C$23,0)))),0) + (((SUMIFS('High Level Dashboard'!$B$65:$AV$65,'High Level Dashboard'!$B$64:$AV$64,">"&'High Level Dashboard'!B$64-ROUNDDOWN('High Level Dashboard'!$C$23,0),'High Level Dashboard'!$B$64:$AV$64,"<="&'High Level Dashboard'!B$64)+(IFERROR(SUMIF('High Level Dashboard'!$B$64:$AV$64,ROUNDDOWN('High Level Dashboard'!B$64-'High Level Dashboard'!$C$23,0)+1,'High Level Dashboard'!$B$65:$AV$65)*(1-('High Level Dashboard'!$C$23-ROUNDDOWN('High Level Dashboard'!$C$23,0))),"")))*'High Level Dashboard'!$C$22) )) -> 2.818929 | D99: =$B$83*'High Level Dashboard'!$C$21* (-PMT('High Level Dashboard'!$C$22,'High Level Dashboard'!$C$24-'High Level Dashboard'!$C$23+1, SUMIFS('High Level Dashboard'!$B$65:$AV$65,'High Level Dashboard'!$B$64:$AV$64,">="&('High Level Dashboard'!C$64-(ROUNDDOWN('High Level Dashboard'!$C$24,0))+1),'High Level Dashboard'!$B$64:$AV$64,"<="&('High Level Dashboard'!C$64-(ROUNDUP('High Level Dashboard'!$C$23,0))))) + IFERROR(-PMT('High Level Dashboard'!$C$22,'High Level Dashboard'!$C$24-'High Level Dashboard'!$C$23+1, (HLOOKUP('High Level Dashboard'!C$64-(ROUNDUP('High Level Dashboard'!$C$24,0))+1,'High Level Dashboard'!$B$64:$AV$65,2,FALSE))*('High Level Dashboard'!$C$24-(ROUNDDOWN('High Level Dashboard'!$C$24,0)))),0) + IFERROR(-PMT('High Level Dashboard'!$C$22,'High Level Dashboard'!$C$24-'High Level Dashboard'!$C$23+1, (HLOOKUP('High Level Dashboard'!C$64-(ROUNDDOWN('High Level Dashboard'!$C$23,0)),'High Level Dashboard'!$B$64:$AV$65,2,FALSE)*('High Level Dashboard'!$C$23-ROUNDDOWN('High Level Dashboard'!$C$23,0)))),0) + (((SUMIFS('High Level Dashboard'!$B$65:$AV$65,'High Level Dashboard'!$B$64:$AV$64,">"&'High Level Dashboard'!C$64-ROUNDDOWN('High Level Dashboard'!$C$23,0),'High Level Dashboard'!$B$64:$AV$64,"<="&'High Level Dashboard'!C$64)+(IFERROR(SUMIF('High Level Dashboard'!$B$64:$AV$64,ROUNDDOWN('High Level Dashboard'!C$64-'High Level Dashboard'!$C$23,0)+1,'High Level Dashboard'!$B$65:$AV$65)*(1-('High Level Dashboard'!$C$23-ROUNDDOWN('High Level Dashboard'!$C$23,0))),"")))*'High Level Dashboard'!$C$22) )) -> 5.7738498 | E99: =$B$83*'High Level Dashboard'!$C$21* (-PMT('High Level Dashboard'!$C$22,'High Level Dashboard'!$C$24-'High Level Dashboard'!$C$23+1, SUMIFS('High Level Dashboard'!$B$65:$AV$65,'High Level Dashboard'!$B$64:$AV$64,">="&('High Level Dashboard'!D$64-(ROUNDDOWN('High Level Dashboard'!$C$24,0))+1),'High Level Dashboard'!$B$64:$AV$64,"<="&('High Level Dashboard'!D$64-(ROUNDUP('High Level Dashboard'!$C$23,0))))) + IFERROR(-PMT('High Level Dashboard'!$C$22,'High Level Dashboard'!$C$24-'High Level Dashboard'!$C$23+1, (HLOOKUP('High Level Dashboard'!D$64-(ROUNDUP('High Level Dashboard'!$C$24,0))+1,'High Level Dashboard'!$B$64:$AV$65,2,FALSE))*('High Level Dashboard'!$C$24-(ROUNDDOWN('High Level Dashboard'!$C$24,0)))),0) + IFERROR(-PMT('High Level Dashboard'!$C$22,'High Level Dashboard'!$C$24-'High Level Dashboard'!$C$23+1, (HLOOKUP('High Level Dashboard'!D$64-(ROUNDDOWN('High Level Dashboard'!$C$23,0)),'High Level Dashboard'!$B$64:$AV$65,2,FALSE)*('High Level Dashboard'!$C$23-ROUNDDOWN('High Level Dashboard'!$C$23,0)))),0) + (((SUMIFS('High Level Dashboard'!$B$65:$AV$65,'High Level Dashboard'!$B$64:$AV$64,">"&'High Level Dashboard'!D$64-ROUNDDOWN('High Level Dashboard'!$C$23,0),'High Level Dashboard'!$B$64:$AV$64,"<="&'High Level Dashboard'!D$64)+(IFERROR(SUMIF('High Level Dashboard'!$B$64:$AV$64,ROUNDDOWN('High Level Dashboard'!D$64-'High Level Dashboard'!$C$23,0)+1,'High Level Dashboard'!$B$65:$AV$65)*(1-('High Level Dashboard'!$C$23-ROUNDDOWN('High Level Dashboard'!$C$23,0))),"")))*'High Level Dashboard'!$C$22) )) -> 9.6042075 | F99: =$B$83*'High Level Dashboard'!$C$21* (-PMT('High Level Dashboard'!$C$22,'High Level Dashboard'!$C$24-'High Level Dashboard'!$C$23+1, SUMIFS('High Level Dashboard'!$B$65:$AV$65,'High Level Dashboard'!$B$64:$AV$64,">="&('High Level Dashboard'!E$64-(ROUNDDOWN('High Level Dashboard'!$C$24,0))+1),'High Level Dashboard'!$B$64:$AV$64,"<="&('High Level Dashboard'!E$64-(ROUNDUP('High Level Dashboard'!$C$23,0))))) + IFERROR(-PMT('High Level Dashboard'!$C$22,'High Level Dashboard'!$C$24-'High Level Dashboard'!$C$23+1, (HLOOKUP('High Level Dashboard'!E$64-(ROUNDUP('High Level Dashboard'!$C$24,0))+1,'High Level Dashboard'!$B$64:$AV$65,2,FALSE))*('High Level Dashboard'!$C$24-(ROUNDDOWN('High Level Dashboard'!$C$24,0)))),0) + IFERROR(-PMT('High Level Dashboard'!$C$22,'High Level Dashboard'!$C$24-'High Level Dashboard'!$C$23+1, (HLOOKUP('High Level Dashboard'!E$64-(ROUNDDOWN('High Level Dashboard'!$C$23,0)),'High Level Dashboard'!$B$64:$AV$65,2,FALSE)*('High Level Dashboard'!$C$23-ROUNDDOWN('High Level Dashboard'!$C$23,0)))),0) + (((SUMIFS('High Level Dashboard'!$B$65:$AV$65,'High Level Dashboard'!$B$64:$AV$64,">"&'High Level Dashboard'!E$64-ROUNDDOWN('High Level Dashboard'!$C$23,0),'High Level Dashboard'!$B$64:$AV$64,"<="&'High Level Dashboard'!E$64)+(IFERROR(SUMIF('High Level Dashboard'!$B$64:$AV$64,ROUNDDOWN('High Level Dashboard'!E$64-'High Level Dashboard'!$C$23,0)+1,'High Level Dashboard'!$B$65:$AV$65)*(1-('High Level Dashboard'!$C$23-ROUNDDOWN('High Level Dashboard'!$C$23,0))),"")))*'High Level Dashboard'!$C$22) )) -> 13.312383 | G99: =$B$83*'High Level Dashboard'!$C$21* (-PMT('High Level Dashboard'!$C$22,'High Level Dashboard'!$C$24-'High Level Dashboard'!$C$23+1, SUMIFS('High Level Dashboard'!$B$65:$AV$65,'High Level Dashboard'!$B$64:$AV$64,">="&('High Level Dashboard'!F$64-(ROUNDDOWN('High Level Dashboard'!$C$24,0))+1),'High Level Dashboard'!$B$64:$AV$64,"<="&('High Level Dashboard'!F$64-(ROUNDUP('High Level Dashboard'!$C$23,0))))) + IFERROR(-PMT('High Level Dashboard'!$C$22,'High Level Dashboard'!$C$24-'High Level Dashboard'!$C$23+1, (HLOOKUP('High Level Dashboard'!F$64-(ROUNDUP('High Level Dashboard'!$C$24,0))+1,'High Level Dashboard'!$B$64:$AV$65,2,FALSE))*('High Level Dashboard'!$C$24-(ROUNDDOWN('High Level Dashboard'!$C$24,0)))),0) + IFERROR(-PMT('High Level Dashboard'!$C$22,'High Level Dashboard'!$C$24-'High Level Dashboard'!$C$23+1, (HLOOKUP('High Level Dashboard'!F$64-(ROUNDDOWN('High Level Dashboard'!$C$23,0)),'High Level Dashboard'!$B$64:$AV$65,2,FALSE)*('High Level Dashboard'!$C$23-ROUNDDOWN('High Level Dashboard'!$C$23,0)))),0) + (((SUMIFS('High Level Dashboard'!$B$65:$AV$65,'High Level Dashboard'!$B$64:$AV$64,">"&'High Level Dashboard'!F$64-ROUNDDOWN('High Level Dashboard'!$C$23,0),'High Level Dashboard'!$B$64:$AV$64,"<="&'High Level Dashboard'!F$64)+(IFERROR(SUMIF('High Level Dashboard'!$B$64:$AV$64,ROUNDDOWN('High Level Dashboard'!F$64-'High Level Dashboard'!$C$23,0)+1,'High Level Dashboard'!$B$65:$AV$65)*(1-('High Level Dashboard'!$C$23-ROUNDDOWN('High Level Dashboard'!$C$23,0))),"")))*'High Level Dashboard'!$C$22) )) -> 19.860269 | H99: =$B$83*'High Level Dashboard'!$C$21* (-PMT('High Level Dashboard'!$C$22,'High Level Dashboard'!$C$24-'High Level Dashboard'!$C$23+1, SUMIFS('High Level Dashboard'!$B$65:$AV$65,'High Level Dashboard'!$B$64:$AV$64,">="&('High Level Dashboard'!G$64-(ROUNDDOWN('High Level Dashboard'!$C$24,0))+1),'High Level Dashboard'!$B$64:$AV$64,"<="&('High Level Dashboard'!G$64-(ROUNDUP('High Level Dashboard'!$C$23,0))))) + IFERROR(-PMT('High Level Dashboard'!$C$22,'High Level Dashboard'!$C$24-'High Level Dashboard'!$C$23+1, (HLOOKUP('High Level Dashboard'!G$64-(ROUNDUP('High Level Dashboard'!$C$24,0))+1,'High Level Dashboard'!$B$64:$AV$65,2,FALSE))*('High Level Dashboard'!$C$24-(ROUNDDOWN('High Level Dashboard'!$C$24,0)))),0) + IFERROR(-PMT('High Level Dashboard'!$C$22,'High Level Dashboard'!$C$24-'High Level Dashboard'!$C$23+1, (HLOOKUP('High Level Dashboard'!G$64-(ROUNDDOWN('High Level Dashboard'!$C$23,0)),'High Level Dashboard'!$B$64:$AV$65,2,FALSE)*('High Level Dashboard'!$C$23-ROUNDDOWN('High Level Dashboard'!$C$23,0)))),0) + (((SUMIFS('High Level Dashboard'!$B$65:$AV$65,'High Level Dashboard'!$B$64:$AV$64,">"&'High Level Dashboard'!G$64-ROUNDDOWN('High Level Dashboard'!$C$23,0),'High Level Dashboard'!$B$64:$AV$64,"<="&'High Level Dashboard'!G$64)+(IFERROR(SUMIF('High Level Dashboard'!$B$64:$AV$64,ROUNDDOWN('High Level Dashboard'!G$64-'High Level Dashboard'!$C$23,0)+1,'High Level Dashboard'!$B$65:$AV$65)*(1-('High Level Dashboard'!$C$23-ROUNDDOWN('High Level Dashboard'!$C$23,0))),"")))*'High Level Dashboard'!$C$22) )) -> 24.074801 | I99: =$B$83*'High Level Dashboard'!$C$21* (-PMT('High Level Dashboard'!$C$22,'High Level Dashboard'!$C$24-'High Level Dashboard'!$C$23+1, SUMIFS('High Level Dashboard'!$B$65:$AV$65,'High Level Dashboard'!$B$64:$AV$64,">="&('High Level Dashboard'!H$64-(ROUNDDOWN('High Level Dashboard'!$C$24,0))+1),'High Level Dashboard'!$B$64:$AV$64,"<="&('High Level Dashboard'!H$64-(ROUNDUP('High Level Dashboard'!$C$23,0))))) + IFERROR(-PMT('High Level Dashboard'!$C$22,'High Level Dashboard'!$C$24-'High Level Dashboard'!$C$23+1, (HLOOKUP('High Level Dashboard'!H$64-(ROUNDUP('High Level Dashboard'!$C$24,0))+1,'High Level Dashboard'!$B$64:$AV$65,2,FALSE))*('High Level Dashboard'!$C$24-(ROUNDDOWN('High Level Dashboard'!$C$24,0)))),0) + IFERROR(-PMT('High Level Dashboard'!$C$22,'High Level Dashboard'!$C$24-'High Level Dashboard'!$C$23+1, (HLOOKUP('High Level Dashboard'!H$64-(ROUNDDOWN('High Level Dashboard'!$C$23,0)),'High Level Dashboard'!$B$64:$AV$65,2,FALSE)*('High Level Dashboard'!$C$23-ROUNDDOWN('High Level Dashboard'!$C$23,0)))),0) + (((SUMIFS('High Level Dashboard'!$B$65:$AV$65,'High Level Dashboard'!$B$64:$AV$64,">"&'High Level Dashboard'!H$64-ROUNDDOWN('High Level Dashboard'!$C$23,0),'High Level Dashboard'!$B$64:$AV$64,"<="&'High Level Dashboard'!H$64)+(IFERROR(SUMIF('High Level Dashboard'!$B$64:$AV$64,ROUNDDOWN('High Level Dashboard'!H$64-'High Level Dashboard'!$C$23,0)+1,'High Level Dashboard'!$B$65:$AV$65)*(1-('High Level Dashboard'!$C$23-ROUNDDOWN('High Level Dashboard'!$C$23,0))),"")))*'High Level Dashboard'!$C$22) )) -> 29.583186 | J99: =$B$83*'High Level Dashboard'!$C$21* (-PMT('High Level Dashboard'!$C$22,'High Level Dashboard'!$C$24-'High Level Dashboard'!$C$23+1, SUMIFS('High Level Dashboard'!$B$65:$AV$65,'High Level Dashboard'!$B$64:$AV$64,">="&('High Level Dashboard'!I$64-(ROUNDDOWN('High Level Dashboard'!$C$24,0))+1),'High Level Dashboard'!$B$64:$AV$64,"<="&('High Level Dashboard'!I$64-(ROUNDUP('High Level Dashboard'!$C$23,0))))) + IFERROR(-PMT('High Level Dashboard'!$C$22,'High Level Dashboard'!$C$24-'High Level Dashboard'!$C$23+1, (HLOOKUP('High Level Dashboard'!I$64-(ROUNDUP('High Level Dashboard'!$C$24,0))+1,'High Level Dashboard'!$B$64:$AV$65,2,FALSE))*('High Level Dashboard'!$C$24-(ROUNDDOWN('High Level Dashboard'!$C$24,0)))),0) + IFERROR(-PMT('High Level Dashboard'!$C$22,'High Level Dashboard'!$C$24-'High Level Dashboard'!$C$23+1, (HLOOKUP('High Level Dashboard'!I$64-(ROUNDDOWN('High Level Dashboard'!$C$23,0)),'High Level Dashboard'!$B$64:$AV$65,2,FALSE)*('High Level Dashboard'!$C$23-ROUNDDOWN('High Level Dashboard'!$C$23,0)))),0) + (((SUMIFS('High Level Dashboard'!$B$65:$AV$65,'High Level Dashboard'!$B$64:$AV$64,">"&'High Level Dashboard'!I$64-ROUNDDOWN('High Level Dashboard'!$C$23,0),'High Level Dashboard'!$B$64:$AV$64,"<="&'High Level Dashboard'!I$64)+(IFERROR(SUMIF('High Level Dashboard'!$B$64:$AV$64,ROUNDDOWN('High Level Dashboard'!I$64-'High Level Dashboard'!$C$23,0)+1,'High Level Dashboard'!$B$65:$AV$65)*(1-('High Level Dashboard'!$C$23-ROUNDDOWN('High Level Dashboard'!$C$23,0))),"")))*'High Level Dashboard'!$C$22) )) -> 33.578494 | ... AV99: =$B$83*'High Level Dashboard'!$C$21* (-PMT('High Level Dashboard'!$C$22,'High Level Dashboard'!$C$24-'High Level Dashboard'!$C$23+1, SUMIFS('High Level Dashboard'!$B$65:$AV$65,'High Level Dashboard'!$B$64:$AV$64,">="&('High Level Dashboard'!AU$64-(ROUNDDOWN('High Level Dashboard'!$C$24,0))+1),'High Level Dashboard'!$B$64:$AV$64,"<="&('High Level Dashboard'!AU$64-(ROUNDUP('High Level Dashboard'!$C$23,0))))) + IFERROR(-PMT('High Level Dashboard'!$C$22,'High Level Dashboard'!$C$24-'High Level Dashboard'!$C$23+1, (HLOOKUP('High Level Dashboard'!AU$64-(ROUNDUP('High Level Dashboard'!$C$24,0))+1,'High Level Dashboard'!$B$64:$AV$65,2,FALSE))*('High Level Dashboard'!$C$24-(ROUNDDOWN('High Level Dashboard'!$C$24,0)))),0) + IFERROR(-PMT('High Level Dashboard'!$C$22,'High Level Dashboard'!$C$24-'High Level Dashboard'!$C$23+1, (HLOOKUP('High Level Dashboard'!AU$64-(ROUNDDOWN('High Level Dashboard'!$C$23,0)),'High Level Dashboard'!$B$64:$AV$65,2,FALSE)*('High Level Dashboard'!$C$23-ROUNDDOWN('High Level Dashboard'!$C$23,0)))),0) + (((SUMIFS('High Level Dashboard'!$B$65:$AV$65,'High Level Dashboard'!$B$64:$AV$64,">"&'High Level Dashboard'!AU$64-ROUNDDOWN('High Level Dashboard'!$C$23,0),'High Level Dashboard'!$B$64:$AV$64,"<="&'High Level Dashboard'!AU$64)+(IFERROR(SUMIF('High Level Dashboard'!$B$64:$AV$64,ROUNDDOWN('High Level Dashboard'!AU$64-'High Level Dashboard'!$C$23,0)+1,'High Level Dashboard'!$B$65:$AV$65)*(1-('High Level Dashboard'!$C$23-ROUNDDOWN('High Level Dashboard'!$C$23,0))),"")))*'High Level Dashboard'!$C$22) )) -> 167.80451
A100: Loans - Commercial Domestic Finance (Comm Dom) | C100: =$B$84*'High Level Dashboard'!$C$27* (-PMT('High Level Dashboard'!$C$28,'High Level Dashboard'!$C$30-'High Level Dashboard'!$C$29+1, SUMIFS('High Level Dashboard'!$B$65:$AV$65,'High Level Dashboard'!$B$64:$AV$64,">="&('High Level Dashboard'!B$64-(ROUNDDOWN('High Level Dashboard'!$C$30,0))+1),'High Level Dashboard'!$B$64:$AV$64,"<="&('High Level Dashboard'!B$64-(ROUNDUP('High Level Dashboard'!$C$29,0))))) + IFERROR(-PMT('High Level Dashboard'!$C$28,'High Level Dashboard'!$C$30-'High Level Dashboard'!$C$29+1, (HLOOKUP('High Level Dashboard'!B$64-(ROUNDUP('High Level Dashboard'!$C$30,0))+1,'High Level Dashboard'!$B$64:$AV$65,2,FALSE))*('High Level Dashboard'!$C$30-(ROUNDDOWN('High Level Dashboard'!$C$30,0)))),0) + IFERROR(-PMT('High Level Dashboard'!$C$28,'High Level Dashboard'!$C$30-'High Level Dashboard'!$C$29+1, (HLOOKUP('High Level Dashboard'!B$64-(ROUNDDOWN('High Level Dashboard'!$C$29,0)),'High Level Dashboard'!$B$64:$AV$65,2,FALSE)*('High Level Dashboard'!$C$29-ROUNDDOWN('High Level Dashboard'!$C$29,0)))),0) + (((SUMIFS('High Level Dashboard'!$B$65:$AV$65,'High Level Dashboard'!$B$64:$AV$64,">"&'High Level Dashboard'!B$64-ROUNDDOWN('High Level Dashboard'!$C$29,0),'High Level Dashboard'!$B$64:$AV$64,"<="&'High Level Dashboard'!B$64)+(IFERROR(SUMIF('High Level Dashboard'!$B$64:$AV$64,ROUNDDOWN('High Level Dashboard'!B$64-'High Level Dashboard'!$C$29,0)+1,'High Level Dashboard'!$B$65:$AV$65)*(1-('High Level Dashboard'!$C$29-ROUNDDOWN('High Level Dashboard'!$C$29,0))),"")))*'High Level Dashboard'!$C$28) )) -> 0.46569484 | D100: =$B$84*'High Level Dashboard'!$C$27* (-PMT('High Level Dashboard'!$C$28,'High Level Dashboard'!$C$30-'High Level Dashboard'!$C$29+1, SUMIFS('High Level Dashboard'!$B$65:$AV$65,'High Level Dashboard'!$B$64:$AV$64,">="&('High Level Dashboard'!C$64-(ROUNDDOWN('High Level Dashboard'!$C$30,0))+1),'High Level Dashboard'!$B$64:$AV$64,"<="&('High Level Dashboard'!C$64-(ROUNDUP('High Level Dashboard'!$C$29,0))))) + IFERROR(-PMT('High Level Dashboard'!$C$28,'High Level Dashboard'!$C$30-'High Level Dashboard'!$C$29+1, (HLOOKUP('High Level Dashboard'!C$64-(ROUNDUP('High Level Dashboard'!$C$30,0))+1,'High Level Dashboard'!$B$64:$AV$65,2,FALSE))*('High Level Dashboard'!$C$30-(ROUNDDOWN('High Level Dashboard'!$C$30,0)))),0) + IFERROR(-PMT('High Level Dashboard'!$C$28,'High Level Dashboard'!$C$30-'High Level Dashboard'!$C$29+1, (HLOOKUP('High Level Dashboard'!C$64-(ROUNDDOWN('High Level Dashboard'!$C$29,0)),'High Level Dashboard'!$B$64:$AV$65,2,FALSE)*('High Level Dashboard'!$C$29-ROUNDDOWN('High Level Dashboard'!$C$29,0)))),0) + (((SUMIFS('High Level Dashboard'!$B$65:$AV$65,'High Level Dashboard'!$B$64:$AV$64,">"&'High Level Dashboard'!C$64-ROUNDDOWN('High Level Dashboard'!$C$29,0),'High Level Dashboard'!$B$64:$AV$64,"<="&'High Level Dashboard'!C$64)+(IFERROR(SUMIF('High Level Dashboard'!$B$64:$AV$64,ROUNDDOWN('High Level Dashboard'!C$64-'High Level Dashboard'!$C$29,0)+1,'High Level Dashboard'!$B$65:$AV$65)*(1-('High Level Dashboard'!$C$29-ROUNDDOWN('High Level Dashboard'!$C$29,0))),"")))*'High Level Dashboard'!$C$28) )) -> 0.95385592 | E100: =$B$84*'High Level Dashboard'!$C$27* (-PMT('High Level Dashboard'!$C$28,'High Level Dashboard'!$C$30-'High Level Dashboard'!$C$29+1, SUMIFS('High Level Dashboard'!$B$65:$AV$65,'High Level Dashboard'!$B$64:$AV$64,">="&('High Level Dashboard'!D$64-(ROUNDDOWN('High Level Dashboard'!$C$30,0))+1),'High Level Dashboard'!$B$64:$AV$64,"<="&('High Level Dashboard'!D$64-(ROUNDUP('High Level Dashboard'!$C$29,0))))) + IFERROR(-PMT('High Level Dashboard'!$C$28,'High Level Dashboard'!$C$30-'High Level Dashboard'!$C$29+1, (HLOOKUP('High Level Dashboard'!D$64-(ROUNDUP('High Level Dashboard'!$C$30,0))+1,'High Level Dashboard'!$B$64:$AV$65,2,FALSE))*('High Level Dashboard'!$C$30-(ROUNDDOWN('High Level Dashboard'!$C$30,0)))),0) + IFERROR(-PMT('High Level Dashboard'!$C$28,'High Level Dashboard'!$C$30-'High Level Dashboard'!$C$29+1, (HLOOKUP('High Level Dashboard'!D$64-(ROUNDDOWN('High Level Dashboard'!$C$29,0)),'High Level Dashboard'!$B$64:$AV$65,2,FALSE)*('High Level Dashboard'!$C$29-ROUNDDOWN('High Level Dashboard'!$C$29,0)))),0) + (((SUMIFS('High Level Dashboard'!$B$65:$AV$65,'High Level Dashboard'!$B$64:$AV$64,">"&'High Level Dashboard'!D$64-ROUNDDOWN('High Level Dashboard'!$C$29,0),'High Level Dashboard'!$B$64:$AV$64,"<="&'High Level Dashboard'!D$64)+(IFERROR(SUMIF('High Level Dashboard'!$B$64:$AV$64,ROUNDDOWN('High Level Dashboard'!D$64-'High Level Dashboard'!$C$29,0)+1,'High Level Dashboard'!$B$65:$AV$65)*(1-('High Level Dashboard'!$C$29-ROUNDDOWN('High Level Dashboard'!$C$29,0))),"")))*'High Level Dashboard'!$C$28) )) -> 1.4425691 | F100: =$B$84*'High Level Dashboard'!$C$27* (-PMT('High Level Dashboard'!$C$28,'High Level Dashboard'!$C$30-'High Level Dashboard'!$C$29+1, SUMIFS('High Level Dashboard'!$B$65:$AV$65,'High Level Dashboard'!$B$64:$AV$64,">="&('High Level Dashboard'!E$64-(ROUNDDOWN('High Level Dashboard'!$C$30,0))+1),'High Level Dashboard'!$B$64:$AV$64,"<="&('High Level Dashboard'!E$64-(ROUNDUP('High Level Dashboard'!$C$29,0))))) + IFERROR(-PMT('High Level Dashboard'!$C$28,'High Level Dashboard'!$C$30-'High Level Dashboard'!$C$29+1, (HLOOKUP('High Level Dashboard'!E$64-(ROUNDUP('High Level Dashboard'!$C$30,0))+1,'High Level Dashboard'!$B$64:$AV$65,2,FALSE))*('High Level Dashboard'!$C$30-(ROUNDDOWN('High Level Dashboard'!$C$30,0)))),0) + IFERROR(-PMT('High Level Dashboard'!$C$28,'High Level Dashboard'!$C$30-'High Level Dashboard'!$C$29+1, (HLOOKUP('High Level Dashboard'!E$64-(ROUNDDOWN('High Level Dashboard'!$C$29,0)),'High Level Dashboard'!$B$64:$AV$65,2,FALSE)*('High Level Dashboard'!$C$29-ROUNDDOWN('High Level Dashboard'!$C$29,0)))),0) + (((SUMIFS('High Level Dashboard'!$B$65:$AV$65,'High Level Dashboard'!$B$64:$AV$64,">"&'High Level Dashboard'!E$64-ROUNDDOWN('High Level Dashboard'!$C$29,0),'High Level Dashboard'!$B$64:$AV$64,"<="&'High Level Dashboard'!E$64)+(IFERROR(SUMIF('High Level Dashboard'!$B$64:$AV$64,ROUNDDOWN('High Level Dashboard'!E$64-'High Level Dashboard'!$C$29,0)+1,'High Level Dashboard'!$B$65:$AV$65)*(1-('High Level Dashboard'!$C$29-ROUNDDOWN('High Level Dashboard'!$C$29,0))),"")))*'High Level Dashboard'!$C$28) )) -> 1.8718964 | G100: =$B$84*'High Level Dashboard'!$C$27* (-PMT('High Level Dashboard'!$C$28,'High Level Dashboard'!$C$30-'High Level Dashboard'!$C$29+1, SUMIFS('High Level Dashboard'!$B$65:$AV$65,'High Level Dashboard'!$B$64:$AV$64,">="&('High Level Dashboard'!F$64-(ROUNDDOWN('High Level Dashboard'!$C$30,0))+1),'High Level Dashboard'!$B$64:$AV$64,"<="&('High Level Dashboard'!F$64-(ROUNDUP('High Level Dashboard'!$C$29,0))))) + IFERROR(-PMT('High Level Dashboard'!$C$28,'High Level Dashboard'!$C$30-'High Level Dashboard'!$C$29+1, (HLOOKUP('High Level Dashboard'!F$64-(ROUNDUP('High Level Dashboard'!$C$30,0))+1,'High Level Dashboard'!$B$64:$AV$65,2,FALSE))*('High Level Dashboard'!$C$30-(ROUNDDOWN('High Level Dashboard'!$C$30,0)))),0) + IFERROR(-PMT('High Level Dashboard'!$C$28,'High Level Dashboard'!$C$30-'High Level Dashboard'!$C$29+1, (HLOOKUP('High Level Dashboard'!F$64-(ROUNDDOWN('High Level Dashboard'!$C$29,0)),'High Level Dashboard'!$B$64:$AV$65,2,FALSE)*('High Level Dashboard'!$C$29-ROUNDDOWN('High Level Dashboard'!$C$29,0)))),0) + (((SUMIFS('High Level Dashboard'!$B$65:$AV$65,'High Level Dashboard'!$B$64:$AV$64,">"&'High Level Dashboard'!F$64-ROUNDDOWN('High Level Dashboard'!$C$29,0),'High Level Dashboard'!$B$64:$AV$64,"<="&'High Level Dashboard'!F$64)+(IFERROR(SUMIF('High Level Dashboard'!$B$64:$AV$64,ROUNDDOWN('High Level Dashboard'!F$64-'High Level Dashboard'!$C$29,0)+1,'High Level Dashboard'!$B$65:$AV$65)*(1-('High Level Dashboard'!$C$29-ROUNDDOWN('High Level Dashboard'!$C$29,0))),"")))*'High Level Dashboard'!$C$28) )) -> 2.7686253 | H100: =$B$84*'High Level Dashboard'!$C$27* (-PMT('High Level Dashboard'!$C$28,'High Level Dashboard'!$C$30-'High Level Dashboard'!$C$29+1, SUMIFS('High Level Dashboard'!$B$65:$AV$65,'High Level Dashboard'!$B$64:$AV$64,">="&('High Level Dashboard'!G$64-(ROUNDDOWN('High Level Dashboard'!$C$30,0))+1),'High Level Dashboard'!$B$64:$AV$64,"<="&('High Level Dashboard'!G$64-(ROUNDUP('High Level Dashboard'!$C$29,0))))) + IFERROR(-PMT('High Level Dashboard'!$C$28,'High Level Dashboard'!$C$30-'High Level Dashboard'!$C$29+1, (HLOOKUP('High Level Dashboard'!G$64-(ROUNDUP('High Level Dashboard'!$C$30,0))+1,'High Level Dashboard'!$B$64:$AV$65,2,FALSE))*('High Level Dashboard'!$C$30-(ROUNDDOWN('High Level Dashboard'!$C$30,0)))),0) + IFERROR(-PMT('High Level Dashboard'!$C$28,'High Level Dashboard'!$C$30-'High Level Dashboard'!$C$29+1, (HLOOKUP('High Level Dashboard'!G$64-(ROUNDDOWN('High Level Dashboard'!$C$29,0)),'High Level Dashboard'!$B$64:$AV$65,2,FALSE)*('High Level Dashboard'!$C$29-ROUNDDOWN('High Level Dashboard'!$C$29,0)))),0) + (((SUMIFS('High Level Dashboard'!$B$65:$AV$65,'High Level Dashboard'!$B$64:$AV$64,">"&'High Level Dashboard'!G$64-ROUNDDOWN('High Level Dashboard'!$C$29,0),'High Level Dashboard'!$B$64:$AV$64,"<="&'High Level Dashboard'!G$64)+(IFERROR(SUMIF('High Level Dashboard'!$B$64:$AV$64,ROUNDDOWN('High Level Dashboard'!G$64-'High Level Dashboard'!$C$29,0)+1,'High Level Dashboard'!$B$65:$AV$65)*(1-('High Level Dashboard'!$C$29-ROUNDDOWN('High Level Dashboard'!$C$29,0))),"")))*'High Level Dashboard'!$C$28) )) -> 3.2982117 | I100: =$B$84*'High Level Dashboard'!$C$27* (-PMT('High Level Dashboard'!$C$28,'High Level Dashboard'!$C$30-'High Level Dashboard'!$C$29+1, SUMIFS('High Level Dashboard'!$B$65:$AV$65,'High Level Dashboard'!$B$64:$AV$64,">="&('High Level Dashboard'!H$64-(ROUNDDOWN('High Level Dashboard'!$C$30,0))+1),'High Level Dashboard'!$B$64:$AV$64,"<="&('High Level Dashboard'!H$64-(ROUNDUP('High Level Dashboard'!$C$29,0))))) + IFERROR(-PMT('High Level Dashboard'!$C$28,'High Level Dashboard'!$C$30-'High Level Dashboard'!$C$29+1, (HLOOKUP('High Level Dashboard'!H$64-(ROUNDUP('High Level Dashboard'!$C$30,0))+1,'High Level Dashboard'!$B$64:$AV$65,2,FALSE))*('High Level Dashboard'!$C$30-(ROUNDDOWN('High Level Dashboard'!$C$30,0)))),0) + IFERROR(-PMT('High Level Dashboard'!$C$28,'High Level Dashboard'!$C$30-'High Level Dashboard'!$C$29+1, (HLOOKUP('High Level Dashboard'!H$64-(ROUNDDOWN('High Level Dashboard'!$C$29,0)),'High Level Dashboard'!$B$64:$AV$65,2,FALSE)*('High Level Dashboard'!$C$29-ROUNDDOWN('High Level Dashboard'!$C$29,0)))),0) + (((SUMIFS('High Level Dashboard'!$B$65:$AV$65,'High Level Dashboard'!$B$64:$AV$64,">"&'High Level Dashboard'!H$64-ROUNDDOWN('High Level Dashboard'!$C$29,0),'High Level Dashboard'!$B$64:$AV$64,"<="&'High Level Dashboard'!H$64)+(IFERROR(SUMIF('High Level Dashboard'!$B$64:$AV$64,ROUNDDOWN('High Level Dashboard'!H$64-'High Level Dashboard'!$C$29,0)+1,'High Level Dashboard'!$B$65:$AV$65)*(1-('High Level Dashboard'!$C$29-ROUNDDOWN('High Level Dashboard'!$C$29,0))),"")))*'High Level Dashboard'!$C$28) )) -> 3.9010581 | J100: =$B$84*'High Level Dashboard'!$C$27* (-PMT('High Level Dashboard'!$C$28,'High Level Dashboard'!$C$30-'High Level Dashboard'!$C$29+1, SUMIFS('High Level Dashboard'!$B$65:$AV$65,'High Level Dashboard'!$B$64:$AV$64,">="&('High Level Dashboard'!I$64-(ROUNDDOWN('High Level Dashboard'!$C$30,0))+1),'High Level Dashboard'!$B$64:$AV$64,"<="&('High Level Dashboard'!I$64-(ROUNDUP('High Level Dashboard'!$C$29,0))))) + IFERROR(-PMT('High Level Dashboard'!$C$28,'High Level Dashboard'!$C$30-'High Level Dashboard'!$C$29+1, (HLOOKUP('High Level Dashboard'!I$64-(ROUNDUP('High Level Dashboard'!$C$30,0))+1,'High Level Dashboard'!$B$64:$AV$65,2,FALSE))*('High Level Dashboard'!$C$30-(ROUNDDOWN('High Level Dashboard'!$C$30,0)))),0) + IFERROR(-PMT('High Level Dashboard'!$C$28,'High Level Dashboard'!$C$30-'High Level Dashboard'!$C$29+1, (HLOOKUP('High Level Dashboard'!I$64-(ROUNDDOWN('High Level Dashboard'!$C$29,0)),'High Level Dashboard'!$B$64:$AV$65,2,FALSE)*('High Level Dashboard'!$C$29-ROUNDDOWN('High Level Dashboard'!$C$29,0)))),0) + (((SUMIFS('High Level Dashboard'!$B$65:$AV$65,'High Level Dashboard'!$B$64:$AV$64,">"&'High Level Dashboard'!I$64-ROUNDDOWN('High Level Dashboard'!$C$29,0),'High Level Dashboard'!$B$64:$AV$64,"<="&'High Level Dashboard'!I$64)+(IFERROR(SUMIF('High Level Dashboard'!$B$64:$AV$64,ROUNDDOWN('High Level Dashboard'!I$64-'High Level Dashboard'!$C$29,0)+1,'High Level Dashboard'!$B$65:$AV$65)*(1-('High Level Dashboard'!$C$29-ROUNDDOWN('High Level Dashboard'!$C$29,0))),"")))*'High Level Dashboard'!$C$28) )) -> 4.3899131 | ... AV100: =$B$84*'High Level Dashboard'!$C$27* (-PMT('High Level Dashboard'!$C$28,'High Level Dashboard'!$C$30-'High Level Dashboard'!$C$29+1, SUMIFS('High Level Dashboard'!$B$65:$AV$65,'High Level Dashboard'!$B$64:$AV$64,">="&('High Level Dashboard'!AU$64-(ROUNDDOWN('High Level Dashboard'!$C$30,0))+1),'High Level Dashboard'!$B$64:$AV$64,"<="&('High Level Dashboard'!AU$64-(ROUNDUP('High Level Dashboard'!$C$29,0))))) + IFERROR(-PMT('High Level Dashboard'!$C$28,'High Level Dashboard'!$C$30-'High Level Dashboard'!$C$29+1, (HLOOKUP('High Level Dashboard'!AU$64-(ROUNDUP('High Level Dashboard'!$C$30,0))+1,'High Level Dashboard'!$B$64:$AV$65,2,FALSE))*('High Level Dashboard'!$C$30-(ROUNDDOWN('High Level Dashboard'!$C$30,0)))),0) + IFERROR(-PMT('High Level Dashboard'!$C$28,'High Level Dashboard'!$C$30-'High Level Dashboard'!$C$29+1, (HLOOKUP('High Level Dashboard'!AU$64-(ROUNDDOWN('High Level Dashboard'!$C$29,0)),'High Level Dashboard'!$B$64:$AV$65,2,FALSE)*('High Level Dashboard'!$C$29-ROUNDDOWN('High Level Dashboard'!$C$29,0)))),0) + (((SUMIFS('High Level Dashboard'!$B$65:$AV$65,'High Level Dashboard'!$B$64:$AV$64,">"&'High Level Dashboard'!AU$64-ROUNDDOWN('High Level Dashboard'!$C$29,0),'High Level Dashboard'!$B$64:$AV$64,"<="&'High Level Dashboard'!AU$64)+(IFERROR(SUMIF('High Level Dashboard'!$B$64:$AV$64,ROUNDDOWN('High Level Dashboard'!AU$64-'High Level Dashboard'!$C$29,0)+1,'High Level Dashboard'!$B$65:$AV$65)*(1-('High Level Dashboard'!$C$29-ROUNDDOWN('High Level Dashboard'!$C$29,0))),"")))*'High Level Dashboard'!$C$28) )) -> 27.855786
A101: Equity - Concessional International Finance (Conc IFI) | C101: =$B$80*'High Level Dashboard'!$D$9* (IFERROR(-PMT('High Level Dashboard'!$D$10,'High Level Dashboard'!$D$12+1, SUMIFS('High Level Dashboard'!$B$65:$AV$65,'High Level Dashboard'!$B$64:$AV$64,">"&'High Level Dashboard'!B$64-ROUNDDOWN('High Level Dashboard'!$D$12,0),'High Level Dashboard'!$B$64:$AV$64,"<="&'High Level Dashboard'!B$64)),"")+ IFERROR(-PMT('High Level Dashboard'!$D$10, 'High Level Dashboard'!$D$12+1, SUMIF('High Level Dashboard'!$B$64:$AV$64,ROUNDDOWN('High Level Dashboard'!B$64-'High Level Dashboard'!$D$12,0)+1,'High Level Dashboard'!$B$65:$AV$65)* (('High Level Dashboard'!$D$12-ROUNDDOWN('High Level Dashboard'!$D$12,0)))),"") ) -> 2.3553719 | D101: =$B$80*'High Level Dashboard'!$D$9* (IFERROR(-PMT('High Level Dashboard'!$D$10,'High Level Dashboard'!$D$12+1, SUMIFS('High Level Dashboard'!$B$65:$AV$65,'High Level Dashboard'!$B$64:$AV$64,">"&'High Level Dashboard'!C$64-ROUNDDOWN('High Level Dashboard'!$D$12,0),'High Level Dashboard'!$B$64:$AV$64,"<="&'High Level Dashboard'!C$64)),"")+ IFERROR(-PMT('High Level Dashboard'!$D$10, 'High Level Dashboard'!$D$12+1, SUMIF('High Level Dashboard'!$B$64:$AV$64,ROUNDDOWN('High Level Dashboard'!C$64-'High Level Dashboard'!$D$12,0)+1,'High Level Dashboard'!$B$65:$AV$65)* (('High Level Dashboard'!$D$12-ROUNDDOWN('High Level Dashboard'!$D$12,0)))),"") ) -> 4.8243727 | E101: =$B$80*'High Level Dashboard'!$D$9* (IFERROR(-PMT('High Level Dashboard'!$D$10,'High Level Dashboard'!$D$12+1, SUMIFS('High Level Dashboard'!$B$65:$AV$65,'High Level Dashboard'!$B$64:$AV$64,">"&'High Level Dashboard'!D$64-ROUNDDOWN('High Level Dashboard'!$D$12,0),'High Level Dashboard'!$B$64:$AV$64,"<="&'High Level Dashboard'!D$64)),"")+ IFERROR(-PMT('High Level Dashboard'!$D$10, 'High Level Dashboard'!$D$12+1, SUMIF('High Level Dashboard'!$B$64:$AV$64,ROUNDDOWN('High Level Dashboard'!D$64-'High Level Dashboard'!$D$12,0)+1,'High Level Dashboard'!$B$65:$AV$65)* (('High Level Dashboard'!$D$12-ROUNDDOWN('High Level Dashboard'!$D$12,0)))),"") ) -> 7.2961656 | F101: =$B$80*'High Level Dashboard'!$D$9* (IFERROR(-PMT('High Level Dashboard'!$D$10,'High Level Dashboard'!$D$12+1, SUMIFS('High Level Dashboard'!$B$65:$AV$65,'High Level Dashboard'!$B$64:$AV$64,">"&'High Level Dashboard'!E$64-ROUNDDOWN('High Level Dashboard'!$D$12,0),'High Level Dashboard'!$B$64:$AV$64,"<="&'High Level Dashboard'!E$64)),"")+ IFERROR(-PMT('High Level Dashboard'!$D$10, 'High Level Dashboard'!$D$12+1, SUMIF('High Level Dashboard'!$B$64:$AV$64,ROUNDDOWN('High Level Dashboard'!E$64-'High Level Dashboard'!$D$12,0)+1,'High Level Dashboard'!$B$65:$AV$65)* (('High Level Dashboard'!$D$12-ROUNDDOWN('High Level Dashboard'!$D$12,0)))),"") ) -> 9.4675997 | G101: =$B$80*'High Level Dashboard'!$D$9* (IFERROR(-PMT('High Level Dashboard'!$D$10,'High Level Dashboard'!$D$12+1, SUMIFS('High Level Dashboard'!$B$65:$AV$65,'High Level Dashboard'!$B$64:$AV$64,">"&'High Level Dashboard'!F$64-ROUNDDOWN('High Level Dashboard'!$D$12,0),'High Level Dashboard'!$B$64:$AV$64,"<="&'High Level Dashboard'!F$64)),"")+ IFERROR(-PMT('High Level Dashboard'!$D$10, 'High Level Dashboard'!$D$12+1, SUMIF('High Level Dashboard'!$B$64:$AV$64,ROUNDDOWN('High Level Dashboard'!F$64-'High Level Dashboard'!$D$12,0)+1,'High Level Dashboard'!$B$65:$AV$65)* (('High Level Dashboard'!$D$12-ROUNDDOWN('High Level Dashboard'!$D$12,0)))),"") ) -> 14.003038 | H101: =$B$80*'High Level Dashboard'!$D$9* (IFERROR(-PMT('High Level Dashboard'!$D$10,'High Level Dashboard'!$D$12+1, SUMIFS('High Level Dashboard'!$B$65:$AV$65,'High Level Dashboard'!$B$64:$AV$64,">"&'High Level Dashboard'!G$64-ROUNDDOWN('High Level Dashboard'!$D$12,0),'High Level Dashboard'!$B$64:$AV$64,"<="&'High Level Dashboard'!G$64)),"")+ IFERROR(-PMT('High Level Dashboard'!$D$10, 'High Level Dashboard'!$D$12+1, SUMIF('High Level Dashboard'!$B$64:$AV$64,ROUNDDOWN('High Level Dashboard'!G$64-'High Level Dashboard'!$D$12,0)+1,'High Level Dashboard'!$B$65:$AV$65)* (('High Level Dashboard'!$D$12-ROUNDDOWN('High Level Dashboard'!$D$12,0)))),"") ) -> 16.681558 | I101: =$B$80*'High Level Dashboard'!$D$9* (IFERROR(-PMT('High Level Dashboard'!$D$10,'High Level Dashboard'!$D$12+1, SUMIFS('High Level Dashboard'!$B$65:$AV$65,'High Level Dashboard'!$B$64:$AV$64,">"&'High Level Dashboard'!H$64-ROUNDDOWN('High Level Dashboard'!$D$12,0),'High Level Dashboard'!$B$64:$AV$64,"<="&'High Level Dashboard'!H$64)),"")+ IFERROR(-PMT('High Level Dashboard'!$D$10, 'High Level Dashboard'!$D$12+1, SUMIF('High Level Dashboard'!$B$64:$AV$64,ROUNDDOWN('High Level Dashboard'!H$64-'High Level Dashboard'!$D$12,0)+1,'High Level Dashboard'!$B$65:$AV$65)* (('High Level Dashboard'!$D$12-ROUNDDOWN('High Level Dashboard'!$D$12,0)))),"") ) -> 19.730609 | J101: =$B$80*'High Level Dashboard'!$D$9* (IFERROR(-PMT('High Level Dashboard'!$D$10,'High Level Dashboard'!$D$12+1, SUMIFS('High Level Dashboard'!$B$65:$AV$65,'High Level Dashboard'!$B$64:$AV$64,">"&'High Level Dashboard'!I$64-ROUNDDOWN('High Level Dashboard'!$D$12,0),'High Level Dashboard'!$B$64:$AV$64,"<="&'High Level Dashboard'!I$64)),"")+ IFERROR(-PMT('High Level Dashboard'!$D$10, 'High Level Dashboard'!$D$12+1, SUMIF('High Level Dashboard'!$B$64:$AV$64,ROUNDDOWN('High Level Dashboard'!I$64-'High Level Dashboard'!$D$12,0)+1,'High Level Dashboard'!$B$65:$AV$65)* (('High Level Dashboard'!$D$12-ROUNDDOWN('High Level Dashboard'!$D$12,0)))),"") ) -> 21.926165 | ... AV101: =$B$80*'High Level Dashboard'!$D$9* (IFERROR(-PMT('High Level Dashboard'!$D$10,'High Level Dashboard'!$D$12+1, SUMIFS('High Level Dashboard'!$B$65:$AV$65,'High Level Dashboard'!$B$64:$AV$64,">"&'High Level Dashboard'!AU$64-ROUNDDOWN('High Level Dashboard'!$D$12,0),'High Level Dashboard'!$B$64:$AV$64,"<="&'High Level Dashboard'!AU$64)),"")+ IFERROR(-PMT('High Level Dashboard'!$D$10, 'High Level Dashboard'!$D$12+1, SUMIF('High Level Dashboard'!$B$64:$AV$64,ROUNDDOWN('High Level Dashboard'!AU$64-'High Level Dashboard'!$D$12,0)+1,'High Level Dashboard'!$B$65:$AV$65)* (('High Level Dashboard'!$D$12-ROUNDDOWN('High Level Dashboard'!$D$12,0)))),"") ) -> 161.32467
A102: Equity - Concessional Domestic Finance (Conc DPS) | C102: =$B$82*'High Level Dashboard'!$D$15* (IFERROR(-PMT('High Level Dashboard'!$D$16,'High Level Dashboard'!$D$18+1, SUMIFS('High Level Dashboard'!$B$65:$AV$65,'High Level Dashboard'!$B$64:$AV$64,">"&'High Level Dashboard'!B$64-ROUNDDOWN('High Level Dashboard'!$D$18,0),'High Level Dashboard'!$B$64:$AV$64,"<="&'High Level Dashboard'!B$64)),"")+ IFERROR(-PMT('High Level Dashboard'!$D$16, 'High Level Dashboard'!$D$18+1, SUMIF('High Level Dashboard'!$B$64:$AV$64,ROUNDDOWN('High Level Dashboard'!B$64-'High Level Dashboard'!$D$18,0)+1,'High Level Dashboard'!$B$65:$AV$65)* (('High Level Dashboard'!$D$18-ROUNDDOWN('High Level Dashboard'!$D$18,0)))),"") ) -> 12.008173 | D102: =$B$82*'High Level Dashboard'!$D$15* (IFERROR(-PMT('High Level Dashboard'!$D$16,'High Level Dashboard'!$D$18+1, SUMIFS('High Level Dashboard'!$B$65:$AV$65,'High Level Dashboard'!$B$64:$AV$64,">"&'High Level Dashboard'!C$64-ROUNDDOWN('High Level Dashboard'!$D$18,0),'High Level Dashboard'!$B$64:$AV$64,"<="&'High Level Dashboard'!C$64)),"")+ IFERROR(-PMT('High Level Dashboard'!$D$16, 'High Level Dashboard'!$D$18+1, SUMIF('High Level Dashboard'!$B$64:$AV$64,ROUNDDOWN('High Level Dashboard'!C$64-'High Level Dashboard'!$D$18,0)+1,'High Level Dashboard'!$B$65:$AV$65)* (('High Level Dashboard'!$D$18-ROUNDDOWN('High Level Dashboard'!$D$18,0)))),"") ) -> 24.59565 | E102: =$B$82*'High Level Dashboard'!$D$15* (IFERROR(-PMT('High Level Dashboard'!$D$16,'High Level Dashboard'!$D$18+1, SUMIFS('High Level Dashboard'!$B$65:$AV$65,'High Level Dashboard'!$B$64:$AV$64,">"&'High Level Dashboard'!D$64-ROUNDDOWN('High Level Dashboard'!$D$18,0),'High Level Dashboard'!$B$64:$AV$64,"<="&'High Level Dashboard'!D$64)),"")+ IFERROR(-PMT('High Level Dashboard'!$D$16, 'High Level Dashboard'!$D$18+1, SUMIF('High Level Dashboard'!$B$64:$AV$64,ROUNDDOWN('High Level Dashboard'!D$64-'High Level Dashboard'!$D$18,0)+1,'High Level Dashboard'!$B$65:$AV$65)* (('High Level Dashboard'!$D$18-ROUNDDOWN('High Level Dashboard'!$D$18,0)))),"") ) -> 37.197362 | F102: =$B$82*'High Level Dashboard'!$D$15* (IFERROR(-PMT('High Level Dashboard'!$D$16,'High Level Dashboard'!$D$18+1, SUMIFS('High Level Dashboard'!$B$65:$AV$65,'High Level Dashboard'!$B$64:$AV$64,">"&'High Level Dashboard'!E$64-ROUNDDOWN('High Level Dashboard'!$D$18,0),'High Level Dashboard'!$B$64:$AV$64,"<="&'High Level Dashboard'!E$64)),"")+ IFERROR(-PMT('High Level Dashboard'!$D$16, 'High Level Dashboard'!$D$18+1, SUMIF('High Level Dashboard'!$B$64:$AV$64,ROUNDDOWN('High Level Dashboard'!E$64-'High Level Dashboard'!$D$18,0)+1,'High Level Dashboard'!$B$65:$AV$65)* (('High Level Dashboard'!$D$18-ROUNDDOWN('High Level Dashboard'!$D$18,0)))),"") ) -> 48.267782 | G102: =$B$82*'High Level Dashboard'!$D$15* (IFERROR(-PMT('High Level Dashboard'!$D$16,'High Level Dashboard'!$D$18+1, SUMIFS('High Level Dashboard'!$B$65:$AV$65,'High Level Dashboard'!$B$64:$AV$64,">"&'High Level Dashboard'!F$64-ROUNDDOWN('High Level Dashboard'!$D$18,0),'High Level Dashboard'!$B$64:$AV$64,"<="&'High Level Dashboard'!F$64)),"")+ IFERROR(-PMT('High Level Dashboard'!$D$16, 'High Level Dashboard'!$D$18+1, SUMIF('High Level Dashboard'!$B$64:$AV$64,ROUNDDOWN('High Level Dashboard'!F$64-'High Level Dashboard'!$D$18,0)+1,'High Level Dashboard'!$B$65:$AV$65)* (('High Level Dashboard'!$D$18-ROUNDDOWN('High Level Dashboard'!$D$18,0)))),"") ) -> 71.390382 | H102: =$B$82*'High Level Dashboard'!$D$15* (IFERROR(-PMT('High Level Dashboard'!$D$16,'High Level Dashboard'!$D$18+1, SUMIFS('High Level Dashboard'!$B$65:$AV$65,'High Level Dashboard'!$B$64:$AV$64,">"&'High Level Dashboard'!G$64-ROUNDDOWN('High Level Dashboard'!$D$18,0),'High Level Dashboard'!$B$64:$AV$64,"<="&'High Level Dashboard'!G$64)),"")+ IFERROR(-PMT('High Level Dashboard'!$D$16, 'High Level Dashboard'!$D$18+1, SUMIF('High Level Dashboard'!$B$64:$AV$64,ROUNDDOWN('High Level Dashboard'!G$64-'High Level Dashboard'!$D$18,0)+1,'High Level Dashboard'!$B$65:$AV$65)* (('High Level Dashboard'!$D$18-ROUNDDOWN('High Level Dashboard'!$D$18,0)))),"") ) -> 85.046031 | I102: =$B$82*'High Level Dashboard'!$D$15* (IFERROR(-PMT('High Level Dashboard'!$D$16,'High Level Dashboard'!$D$18+1, SUMIFS('High Level Dashboard'!$B$65:$AV$65,'High Level Dashboard'!$B$64:$AV$64,">"&'High Level Dashboard'!H$64-ROUNDDOWN('High Level Dashboard'!$D$18,0),'High Level Dashboard'!$B$64:$AV$64,"<="&'High Level Dashboard'!H$64)),"")+ IFERROR(-PMT('High Level Dashboard'!$D$16, 'High Level Dashboard'!$D$18+1, SUMIF('High Level Dashboard'!$B$64:$AV$64,ROUNDDOWN('High Level Dashboard'!H$64-'High Level Dashboard'!$D$18,0)+1,'High Level Dashboard'!$B$65:$AV$65)* (('High Level Dashboard'!$D$18-ROUNDDOWN('High Level Dashboard'!$D$18,0)))),"") ) -> 100.59073 | J102: =$B$82*'High Level Dashboard'!$D$15* (IFERROR(-PMT('High Level Dashboard'!$D$16,'High Level Dashboard'!$D$18+1, SUMIFS('High Level Dashboard'!$B$65:$AV$65,'High Level Dashboard'!$B$64:$AV$64,">"&'High Level Dashboard'!I$64-ROUNDDOWN('High Level Dashboard'!$D$18,0),'High Level Dashboard'!$B$64:$AV$64,"<="&'High Level Dashboard'!I$64)),"")+ IFERROR(-PMT('High Level Dashboard'!$D$16, 'High Level Dashboard'!$D$18+1, SUMIF('High Level Dashboard'!$B$64:$AV$64,ROUNDDOWN('High Level Dashboard'!I$64-'High Level Dashboard'!$D$18,0)+1,'High Level Dashboard'!$B$65:$AV$65)* (('High Level Dashboard'!$D$18-ROUNDDOWN('High Level Dashboard'!$D$18,0)))),"") ) -> 111.78412 | ... AV102: =$B$82*'High Level Dashboard'!$D$15* (IFERROR(-PMT('High Level Dashboard'!$D$16,'High Level Dashboard'!$D$18+1, SUMIFS('High Level Dashboard'!$B$65:$AV$65,'High Level Dashboard'!$B$64:$AV$64,">"&'High Level Dashboard'!AU$64-ROUNDDOWN('High Level Dashboard'!$D$18,0),'High Level Dashboard'!$B$64:$AV$64,"<="&'High Level Dashboard'!AU$64)),"")+ IFERROR(-PMT('High Level Dashboard'!$D$16, 'High Level Dashboard'!$D$18+1, SUMIF('High Level Dashboard'!$B$64:$AV$64,ROUNDDOWN('High Level Dashboard'!AU$64-'High Level Dashboard'!$D$18,0)+1,'High Level Dashboard'!$B$65:$AV$65)* (('High Level Dashboard'!$D$18-ROUNDDOWN('High Level Dashboard'!$D$18,0)))),"") ) -> 1027.3959
A103: Equity - Commercial International Finance (Comm Intl) | C103: =$B$83*'High Level Dashboard'!$D$21* (IFERROR(-PMT('High Level Dashboard'!$D$22,'High Level Dashboard'!$D$24+1, SUMIFS('High Level Dashboard'!$B$65:$AV$65,'High Level Dashboard'!$B$64:$AV$64,">"&'High Level Dashboard'!B$64-ROUNDDOWN('High Level Dashboard'!$D$24,0),'High Level Dashboard'!$B$64:$AV$64,"<="&'High Level Dashboard'!B$64)),"")+ IFERROR(-PMT('High Level Dashboard'!$D$22, 'High Level Dashboard'!$D$24+1, SUMIF('High Level Dashboard'!$B$64:$AV$64,ROUNDDOWN('High Level Dashboard'!B$64-'High Level Dashboard'!$D$24,0)+1,'High Level Dashboard'!$B$65:$AV$65)* (('High Level Dashboard'!$D$24-ROUNDDOWN('High Level Dashboard'!$D$24,0)))),"") ) -> 6.2532474 | D103: =$B$83*'High Level Dashboard'!$D$21* (IFERROR(-PMT('High Level Dashboard'!$D$22,'High Level Dashboard'!$D$24+1, SUMIFS('High Level Dashboard'!$B$65:$AV$65,'High Level Dashboard'!$B$64:$AV$64,">"&'High Level Dashboard'!C$64-ROUNDDOWN('High Level Dashboard'!$D$24,0),'High Level Dashboard'!$B$64:$AV$64,"<="&'High Level Dashboard'!C$64)),"")+ IFERROR(-PMT('High Level Dashboard'!$D$22, 'High Level Dashboard'!$D$24+1, SUMIF('High Level Dashboard'!$B$64:$AV$64,ROUNDDOWN('High Level Dashboard'!C$64-'High Level Dashboard'!$D$24,0)+1,'High Level Dashboard'!$B$65:$AV$65)* (('High Level Dashboard'!$D$24-ROUNDDOWN('High Level Dashboard'!$D$24,0)))),"") ) -> 12.808166 | E103: =$B$83*'High Level Dashboard'!$D$21* (IFERROR(-PMT('High Level Dashboard'!$D$22,'High Level Dashboard'!$D$24+1, SUMIFS('High Level Dashboard'!$B$65:$AV$65,'High Level Dashboard'!$B$64:$AV$64,">"&'High Level Dashboard'!D$64-ROUNDDOWN('High Level Dashboard'!$D$24,0),'High Level Dashboard'!$B$64:$AV$64,"<="&'High Level Dashboard'!D$64)),"")+ IFERROR(-PMT('High Level Dashboard'!$D$22, 'High Level Dashboard'!$D$24+1, SUMIF('High Level Dashboard'!$B$64:$AV$64,ROUNDDOWN('High Level Dashboard'!D$64-'High Level Dashboard'!$D$24,0)+1,'High Level Dashboard'!$B$65:$AV$65)* (('High Level Dashboard'!$D$24-ROUNDDOWN('High Level Dashboard'!$D$24,0)))),"") ) -> 19.370499 | F103: =$B$83*'High Level Dashboard'!$D$21* (IFERROR(-PMT('High Level Dashboard'!$D$22,'High Level Dashboard'!$D$24+1, SUMIFS('High Level Dashboard'!$B$65:$AV$65,'High Level Dashboard'!$B$64:$AV$64,">"&'High Level Dashboard'!E$64-ROUNDDOWN('High Level Dashboard'!$D$24,0),'High Level Dashboard'!$B$64:$AV$64,"<="&'High Level Dashboard'!E$64)),"")+ IFERROR(-PMT('High Level Dashboard'!$D$22, 'High Level Dashboard'!$D$24+1, SUMIF('High Level Dashboard'!$B$64:$AV$64,ROUNDDOWN('High Level Dashboard'!E$64-'High Level Dashboard'!$D$24,0)+1,'High Level Dashboard'!$B$65:$AV$65)* (('High Level Dashboard'!$D$24-ROUNDDOWN('High Level Dashboard'!$D$24,0)))),"") ) -> 25.135412 | G103: =$B$83*'High Level Dashboard'!$D$21* (IFERROR(-PMT('High Level Dashboard'!$D$22,'High Level Dashboard'!$D$24+1, SUMIFS('High Level Dashboard'!$B$65:$AV$65,'High Level Dashboard'!$B$64:$AV$64,">"&'High Level Dashboard'!F$64-ROUNDDOWN('High Level Dashboard'!$D$24,0),'High Level Dashboard'!$B$64:$AV$64,"<="&'High Level Dashboard'!F$64)),"")+ IFERROR(-PMT('High Level Dashboard'!$D$22, 'High Level Dashboard'!$D$24+1, SUMIF('High Level Dashboard'!$B$64:$AV$64,ROUNDDOWN('High Level Dashboard'!F$64-'High Level Dashboard'!$D$24,0)+1,'High Level Dashboard'!$B$65:$AV$65)* (('High Level Dashboard'!$D$24-ROUNDDOWN('High Level Dashboard'!$D$24,0)))),"") ) -> 37.176489 | H103: =$B$83*'High Level Dashboard'!$D$21* (IFERROR(-PMT('High Level Dashboard'!$D$22,'High Level Dashboard'!$D$24+1, SUMIFS('High Level Dashboard'!$B$65:$AV$65,'High Level Dashboard'!$B$64:$AV$64,">"&'High Level Dashboard'!G$64-ROUNDDOWN('High Level Dashboard'!$D$24,0),'High Level Dashboard'!$B$64:$AV$64,"<="&'High Level Dashboard'!G$64)),"")+ IFERROR(-PMT('High Level Dashboard'!$D$22, 'High Level Dashboard'!$D$24+1, SUMIF('High Level Dashboard'!$B$64:$AV$64,ROUNDDOWN('High Level Dashboard'!G$64-'High Level Dashboard'!$D$24,0)+1,'High Level Dashboard'!$B$65:$AV$65)* (('High Level Dashboard'!$D$24-ROUNDDOWN('High Level Dashboard'!$D$24,0)))),"") ) -> 44.287658 | I103: =$B$83*'High Level Dashboard'!$D$21* (IFERROR(-PMT('High Level Dashboard'!$D$22,'High Level Dashboard'!$D$24+1, SUMIFS('High Level Dashboard'!$B$65:$AV$65,'High Level Dashboard'!$B$64:$AV$64,">"&'High Level Dashboard'!H$64-ROUNDDOWN('High Level Dashboard'!$D$24,0),'High Level Dashboard'!$B$64:$AV$64,"<="&'High Level Dashboard'!H$64)),"")+ IFERROR(-PMT('High Level Dashboard'!$D$22, 'High Level Dashboard'!$D$24+1, SUMIF('High Level Dashboard'!$B$64:$AV$64,ROUNDDOWN('High Level Dashboard'!H$64-'High Level Dashboard'!$D$24,0)+1,'High Level Dashboard'!$B$65:$AV$65)* (('High Level Dashboard'!$D$24-ROUNDDOWN('High Level Dashboard'!$D$24,0)))),"") ) -> 52.382546 | J103: =$B$83*'High Level Dashboard'!$D$21* (IFERROR(-PMT('High Level Dashboard'!$D$22,'High Level Dashboard'!$D$24+1, SUMIFS('High Level Dashboard'!$B$65:$AV$65,'High Level Dashboard'!$B$64:$AV$64,">"&'High Level Dashboard'!I$64-ROUNDDOWN('High Level Dashboard'!$D$24,0),'High Level Dashboard'!$B$64:$AV$64,"<="&'High Level Dashboard'!I$64)),"")+ IFERROR(-PMT('High Level Dashboard'!$D$22, 'High Level Dashboard'!$D$24+1, SUMIF('High Level Dashboard'!$B$64:$AV$64,ROUNDDOWN('High Level Dashboard'!I$64-'High Level Dashboard'!$D$24,0)+1,'High Level Dashboard'!$B$65:$AV$65)* (('High Level Dashboard'!$D$24-ROUNDDOWN('High Level Dashboard'!$D$24,0)))),"") ) -> 58.2115 | ... AV103: =$B$83*'High Level Dashboard'!$D$21* (IFERROR(-PMT('High Level Dashboard'!$D$22,'High Level Dashboard'!$D$24+1, SUMIFS('High Level Dashboard'!$B$65:$AV$65,'High Level Dashboard'!$B$64:$AV$64,">"&'High Level Dashboard'!AU$64-ROUNDDOWN('High Level Dashboard'!$D$24,0),'High Level Dashboard'!$B$64:$AV$64,"<="&'High Level Dashboard'!AU$64)),"")+ IFERROR(-PMT('High Level Dashboard'!$D$22, 'High Level Dashboard'!$D$24+1, SUMIF('High Level Dashboard'!$B$64:$AV$64,ROUNDDOWN('High Level Dashboard'!AU$64-'High Level Dashboard'!$D$24,0)+1,'High Level Dashboard'!$B$65:$AV$65)* (('High Level Dashboard'!$D$24-ROUNDDOWN('High Level Dashboard'!$D$24,0)))),"") ) -> 436.35654
A104: Equity - Commercial Domestic Finance (Comm Dom) | C104: =$B$84*'High Level Dashboard'!$D$27* (IFERROR(-PMT('High Level Dashboard'!$D$28,'High Level Dashboard'!$D$30+1, SUMIFS('High Level Dashboard'!$B$65:$AV$65,'High Level Dashboard'!$B$64:$AV$64,">"&'High Level Dashboard'!B$64-ROUNDDOWN('High Level Dashboard'!$D$30,0),'High Level Dashboard'!$B$64:$AV$64,"<="&'High Level Dashboard'!B$64)),"")+ IFERROR(-PMT('High Level Dashboard'!$D$28, 'High Level Dashboard'!$D$30+1, SUMIF('High Level Dashboard'!$B$64:$AV$64,ROUNDDOWN('High Level Dashboard'!B$64-'High Level Dashboard'!$D$30,0)+1,'High Level Dashboard'!$B$65:$AV$65)* (('High Level Dashboard'!$D$30-ROUNDDOWN('High Level Dashboard'!$D$30,0)))),"") ) -> 1.748039 | D104: =$B$84*'High Level Dashboard'!$D$27* (IFERROR(-PMT('High Level Dashboard'!$D$28,'High Level Dashboard'!$D$30+1, SUMIFS('High Level Dashboard'!$B$65:$AV$65,'High Level Dashboard'!$B$64:$AV$64,">"&'High Level Dashboard'!C$64-ROUNDDOWN('High Level Dashboard'!$D$30,0),'High Level Dashboard'!$B$64:$AV$64,"<="&'High Level Dashboard'!C$64)),"")+ IFERROR(-PMT('High Level Dashboard'!$D$28, 'High Level Dashboard'!$D$30+1, SUMIF('High Level Dashboard'!$B$64:$AV$64,ROUNDDOWN('High Level Dashboard'!C$64-'High Level Dashboard'!$D$30,0)+1,'High Level Dashboard'!$B$65:$AV$65)* (('High Level Dashboard'!$D$30-ROUNDDOWN('High Level Dashboard'!$D$30,0)))),"") ) -> 3.5804075 | E104: =$B$84*'High Level Dashboard'!$D$27* (IFERROR(-PMT('High Level Dashboard'!$D$28,'High Level Dashboard'!$D$30+1, SUMIFS('High Level Dashboard'!$B$65:$AV$65,'High Level Dashboard'!$B$64:$AV$64,">"&'High Level Dashboard'!D$64-ROUNDDOWN('High Level Dashboard'!$D$30,0),'High Level Dashboard'!$B$64:$AV$64,"<="&'High Level Dashboard'!D$64)),"")+ IFERROR(-PMT('High Level Dashboard'!$D$28, 'High Level Dashboard'!$D$30+1, SUMIF('High Level Dashboard'!$B$64:$AV$64,ROUNDDOWN('High Level Dashboard'!D$64-'High Level Dashboard'!$D$30,0)+1,'High Level Dashboard'!$B$65:$AV$65)* (('High Level Dashboard'!$D$30-ROUNDDOWN('High Level Dashboard'!$D$30,0)))),"") ) -> 5.4148484 | F104: =$B$84*'High Level Dashboard'!$D$27* (IFERROR(-PMT('High Level Dashboard'!$D$28,'High Level Dashboard'!$D$30+1, SUMIFS('High Level Dashboard'!$B$65:$AV$65,'High Level Dashboard'!$B$64:$AV$64,">"&'High Level Dashboard'!E$64-ROUNDDOWN('High Level Dashboard'!$D$30,0),'High Level Dashboard'!$B$64:$AV$64,"<="&'High Level Dashboard'!E$64)),"")+ IFERROR(-PMT('High Level Dashboard'!$D$28, 'High Level Dashboard'!$D$30+1, SUMIF('High Level Dashboard'!$B$64:$AV$64,ROUNDDOWN('High Level Dashboard'!E$64-'High Level Dashboard'!$D$30,0)+1,'High Level Dashboard'!$B$65:$AV$65)* (('High Level Dashboard'!$D$30-ROUNDDOWN('High Level Dashboard'!$D$30,0)))),"") ) -> 7.0263779 | G104: =$B$84*'High Level Dashboard'!$D$27* (IFERROR(-PMT('High Level Dashboard'!$D$28,'High Level Dashboard'!$D$30+1, SUMIFS('High Level Dashboard'!$B$65:$AV$65,'High Level Dashboard'!$B$64:$AV$64,">"&'High Level Dashboard'!F$64-ROUNDDOWN('High Level Dashboard'!$D$30,0),'High Level Dashboard'!$B$64:$AV$64,"<="&'High Level Dashboard'!F$64)),"")+ IFERROR(-PMT('High Level Dashboard'!$D$28, 'High Level Dashboard'!$D$30+1, SUMIF('High Level Dashboard'!$B$64:$AV$64,ROUNDDOWN('High Level Dashboard'!F$64-'High Level Dashboard'!$D$30,0)+1,'High Level Dashboard'!$B$65:$AV$65)* (('High Level Dashboard'!$D$30-ROUNDDOWN('High Level Dashboard'!$D$30,0)))),"") ) -> 10.392352 | H104: =$B$84*'High Level Dashboard'!$D$27* (IFERROR(-PMT('High Level Dashboard'!$D$28,'High Level Dashboard'!$D$30+1, SUMIFS('High Level Dashboard'!$B$65:$AV$65,'High Level Dashboard'!$B$64:$AV$64,">"&'High Level Dashboard'!G$64-ROUNDDOWN('High Level Dashboard'!$D$30,0),'High Level Dashboard'!$B$64:$AV$64,"<="&'High Level Dashboard'!G$64)),"")+ IFERROR(-PMT('High Level Dashboard'!$D$28, 'High Level Dashboard'!$D$30+1, SUMIF('High Level Dashboard'!$B$64:$AV$64,ROUNDDOWN('High Level Dashboard'!G$64-'High Level Dashboard'!$D$30,0)+1,'High Level Dashboard'!$B$65:$AV$65)* (('High Level Dashboard'!$D$30-ROUNDDOWN('High Level Dashboard'!$D$30,0)))),"") ) -> 12.380216 | I104: =$B$84*'High Level Dashboard'!$D$27* (IFERROR(-PMT('High Level Dashboard'!$D$28,'High Level Dashboard'!$D$30+1, SUMIFS('High Level Dashboard'!$B$65:$AV$65,'High Level Dashboard'!$B$64:$AV$64,">"&'High Level Dashboard'!H$64-ROUNDDOWN('High Level Dashboard'!$D$30,0),'High Level Dashboard'!$B$64:$AV$64,"<="&'High Level Dashboard'!H$64)),"")+ IFERROR(-PMT('High Level Dashboard'!$D$28, 'High Level Dashboard'!$D$30+1, SUMIF('High Level Dashboard'!$B$64:$AV$64,ROUNDDOWN('High Level Dashboard'!H$64-'High Level Dashboard'!$D$30,0)+1,'High Level Dashboard'!$B$65:$AV$65)* (('High Level Dashboard'!$D$30-ROUNDDOWN('High Level Dashboard'!$D$30,0)))),"") ) -> 14.643069 | J104: =$B$84*'High Level Dashboard'!$D$27* (IFERROR(-PMT('High Level Dashboard'!$D$28,'High Level Dashboard'!$D$30+1, SUMIFS('High Level Dashboard'!$B$65:$AV$65,'High Level Dashboard'!$B$64:$AV$64,">"&'High Level Dashboard'!I$64-ROUNDDOWN('High Level Dashboard'!$D$30,0),'High Level Dashboard'!$B$64:$AV$64,"<="&'High Level Dashboard'!I$64)),"")+ IFERROR(-PMT('High Level Dashboard'!$D$28, 'High Level Dashboard'!$D$30+1, SUMIF('High Level Dashboard'!$B$64:$AV$64,ROUNDDOWN('High Level Dashboard'!I$64-'High Level Dashboard'!$D$30,0)+1,'High Level Dashboard'!$B$65:$AV$65)* (('High Level Dashboard'!$D$30-ROUNDDOWN('High Level Dashboard'!$D$30,0)))),"") ) -> 16.272501 | ... AV104: =$B$84*'High Level Dashboard'!$D$27* (IFERROR(-PMT('High Level Dashboard'!$D$28,'High Level Dashboard'!$D$30+1, SUMIFS('High Level Dashboard'!$B$65:$AV$65,'High Level Dashboard'!$B$64:$AV$64,">"&'High Level Dashboard'!AU$64-ROUNDDOWN('High Level Dashboard'!$D$30,0),'High Level Dashboard'!$B$64:$AV$64,"<="&'High Level Dashboard'!AU$64)),"")+ IFERROR(-PMT('High Level Dashboard'!$D$28, 'High Level Dashboard'!$D$30+1, SUMIF('High Level Dashboard'!$B$64:$AV$64,ROUNDDOWN('High Level Dashboard'!AU$64-'High Level Dashboard'!$D$30,0)+1,'High Level Dashboard'!$B$65:$AV$65)* (('High Level Dashboard'!$D$30-ROUNDDOWN('High Level Dashboard'!$D$30,0)))),"") ) -> 136.86403
A106: ='OSeMOSYS (Input)'!$C$5&" Financing Requirements" -> LeastCost Financing Requirements | C106: =SUM(C108:C115) -> 29.706213 | D106: =SUM(D108:D115) -> 77.821866 | E106: =SUM(E108:E115) -> 124.9678 | F106: =SUM(F108:F115) -> 168.62625 | G106: =SUM(G108:G115) -> 258.41355 | H106: =SUM(H108:H115) -> 314.94865 | I106: =SUM(I108:I115) -> 399.45291 | J106: =SUM(J108:J115) -> 466.41896 | ... AV106: =SUM(AV108:AV115) -> 4695.0479
A107: Investment need (Million USD) | C107: ='Investment Needs'!C7 -> 550.2831 | D107: ='Investment Needs'!D7 -> 891.3028 | E107: ='Investment Needs'!E7 -> 859.8577 | F107: ='Investment Needs'!F7 -> 783.882 | G107: ='Investment Needs'!G7 -> 1637.2812 | H107: ='Investment Needs'!H7 -> 1023.3453 | I107: ='Investment Needs'!I7 -> 1265.5083 | J107: ='Investment Needs'!J7 -> 769.2618 | ... AV107: ='Investment Needs'!AV7 -> 2501.8254
A108: Loans - Concessional International Finance (Conc IFI) | C108: ='High Level Dashboard'!$C$53*'High Level Dashboard'!$C$9* (-PMT('High Level Dashboard'!$C$10,'High Level Dashboard'!$C$12-'High Level Dashboard'!$C$11+1, SUMIFS('High Level Dashboard'!$B$112:$AV$112,'High Level Dashboard'!$B$64:$AV$64,">="&('High Level Dashboard'!B$64-(ROUNDDOWN('High Level Dashboard'!$C$12,0))+1),'High Level Dashboard'!$B$64:$AV$64,"<="&('High Level Dashboard'!B$64-(ROUNDUP('High Level Dashboard'!$C$11,0))))) + IFERROR(-PMT('High Level Dashboard'!$C$10,'High Level Dashboard'!$C$12-'High Level Dashboard'!$C$11+1, (_xlfn.XLOOKUP('High Level Dashboard'!B$64-(ROUNDUP('High Level Dashboard'!$C$12,0))+1,'High Level Dashboard'!$B$64:$AV$64,'High Level Dashboard'!$B$112:$AV$112,""))*('High Level Dashboard'!$C$12-(ROUNDDOWN('High Level Dashboard'!$C$12,0)))),0) + IFERROR(-PMT('High Level Dashboard'!$C$10,'High Level Dashboard'!$C$12-'High Level Dashboard'!$C$11+1, (_xlfn.XLOOKUP('High Level Dashboard'!B$64-(ROUNDDOWN('High Level Dashboard'!$C$11,0)),'High Level Dashboard'!$B$64:$AV$64,'High Level Dashboard'!$B$112:$AV$112,"")*('High Level Dashboard'!$C$11-ROUNDDOWN('High Level Dashboard'!$C$11,0)))),0) + (((SUMIFS('High Level Dashboard'!$B$112:$AV$112,'High Level Dashboard'!$B$64:$AV$64,">"&'High Level Dashboard'!B$64-ROUNDDOWN('High Level Dashboard'!$C$11,0),'High Level Dashboard'!$B$64:$AV$64,"<="&'High Level Dashboard'!B$64)+(IFERROR(SUMIF('High Level Dashboard'!$B$64:$AV$64,ROUNDDOWN('High Level Dashboard'!B$64-'High Level Dashboard'!$C$11,0)+1,'High Level Dashboard'!$B$112:$AV$112)*(1-('High Level Dashboard'!$C$11-ROUNDDOWN('High Level Dashboard'!$C$11,0))),"")))*'High Level Dashboard'!$C$10) )) -> 9.6316328 | D108: ='High Level Dashboard'!$C$53*'High Level Dashboard'!$C$9* (-PMT('High Level Dashboard'!$C$10,'High Level Dashboard'!$C$12-'High Level Dashboard'!$C$11+1, SUMIFS('High Level Dashboard'!$B$112:$AV$112,'High Level Dashboard'!$B$64:$AV$64,">="&('High Level Dashboard'!C$64-(ROUNDDOWN('High Level Dashboard'!$C$12,0))+1),'High Level Dashboard'!$B$64:$AV$64,"<="&('High Level Dashboard'!C$64-(ROUNDUP('High Level Dashboard'!$C$11,0))))) + IFERROR(-PMT('High Level Dashboard'!$C$10,'High Level Dashboard'!$C$12-'High Level Dashboard'!$C$11+1, (_xlfn.XLOOKUP('High Level Dashboard'!C$64-(ROUNDUP('High Level Dashboard'!$C$12,0))+1,'High Level Dashboard'!$B$64:$AV$64,'High Level Dashboard'!$B$112:$AV$112,""))*('High Level Dashboard'!$C$12-(ROUNDDOWN('High Level Dashboard'!$C$12,0)))),0) + IFERROR(-PMT('High Level Dashboard'!$C$10,'High Level Dashboard'!$C$12-'High Level Dashboard'!$C$11+1, (_xlfn.XLOOKUP('High Level Dashboard'!C$64-(ROUNDDOWN('High Level Dashboard'!$C$11,0)),'High Level Dashboard'!$B$64:$AV$64,'High Level Dashboard'!$B$112:$AV$112,"")*('High Level Dashboard'!$C$11-ROUNDDOWN('High Level Dashboard'!$C$11,0)))),0) + (((SUMIFS('High Level Dashboard'!$B$112:$AV$112,'High Level Dashboard'!$B$64:$AV$64,">"&'High Level Dashboard'!C$64-ROUNDDOWN('High Level Dashboard'!$C$11,0),'High Level Dashboard'!$B$64:$AV$64,"<="&'High Level Dashboard'!C$64)+(IFERROR(SUMIF('High Level Dashboard'!$B$64:$AV$64,ROUNDDOWN('High Level Dashboard'!C$64-'High Level Dashboard'!$C$11,0)+1,'High Level Dashboard'!$B$112:$AV$112)*(1-('High Level Dashboard'!$C$11-ROUNDDOWN('High Level Dashboard'!$C$11,0))),"")))*'High Level Dashboard'!$C$10) )) -> 25.232151 | E108: ='High Level Dashboard'!$C$53*'High Level Dashboard'!$C$9* (-PMT('High Level Dashboard'!$C$10,'High Level Dashboard'!$C$12-'High Level Dashboard'!$C$11+1, SUMIFS('High Level Dashboard'!$B$112:$AV$112,'High Level Dashboard'!$B$64:$AV$64,">="&('High Level Dashboard'!D$64-(ROUNDDOWN('High Level Dashboard'!$C$12,0))+1),'High Level Dashboard'!$B$64:$AV$64,"<="&('High Level Dashboard'!D$64-(ROUNDUP('High Level Dashboard'!$C$11,0))))) + IFERROR(-PMT('High Level Dashboard'!$C$10,'High Level Dashboard'!$C$12-'High Level Dashboard'!$C$11+1, (_xlfn.XLOOKUP('High Level Dashboard'!D$64-(ROUNDUP('High Level Dashboard'!$C$12,0))+1,'High Level Dashboard'!$B$64:$AV$64,'High Level Dashboard'!$B$112:$AV$112,""))*('High Level Dashboard'!$C$12-(ROUNDDOWN('High Level Dashboard'!$C$12,0)))),0) + IFERROR(-PMT('High Level Dashboard'!$C$10,'High Level Dashboard'!$C$12-'High Level Dashboard'!$C$11+1, (_xlfn.XLOOKUP('High Level Dashboard'!D$64-(ROUNDDOWN('High Level Dashboard'!$C$11,0)),'High Level Dashboard'!$B$64:$AV$64,'High Level Dashboard'!$B$112:$AV$112,"")*('High Level Dashboard'!$C$11-ROUNDDOWN('High Level Dashboard'!$C$11,0)))),0) + (((SUMIFS('High Level Dashboard'!$B$112:$AV$112,'High Level Dashboard'!$B$64:$AV$64,">"&'High Level Dashboard'!D$64-ROUNDDOWN('High Level Dashboard'!$C$11,0),'High Level Dashboard'!$B$64:$AV$64,"<="&'High Level Dashboard'!D$64)+(IFERROR(SUMIF('High Level Dashboard'!$B$64:$AV$64,ROUNDDOWN('High Level Dashboard'!D$64-'High Level Dashboard'!$C$11,0)+1,'High Level Dashboard'!$B$112:$AV$112)*(1-('High Level Dashboard'!$C$11-ROUNDDOWN('High Level Dashboard'!$C$11,0))),"")))*'High Level Dashboard'!$C$10) )) -> 40.282283 | F108: ='High Level Dashboard'!$C$53*'High Level Dashboard'!$C$9* (-PMT('High Level Dashboard'!$C$10,'High Level Dashboard'!$C$12-'High Level Dashboard'!$C$11+1, SUMIFS('High Level Dashboard'!$B$112:$AV$112,'High Level Dashboard'!$B$64:$AV$64,">="&('High Level Dashboard'!E$64-(ROUNDDOWN('High Level Dashboard'!$C$12,0))+1),'High Level Dashboard'!$B$64:$AV$64,"<="&('High Level Dashboard'!E$64-(ROUNDUP('High Level Dashboard'!$C$11,0))))) + IFERROR(-PMT('High Level Dashboard'!$C$10,'High Level Dashboard'!$C$12-'High Level Dashboard'!$C$11+1, (_xlfn.XLOOKUP('High Level Dashboard'!E$64-(ROUNDUP('High Level Dashboard'!$C$12,0))+1,'High Level Dashboard'!$B$64:$AV$64,'High Level Dashboard'!$B$112:$AV$112,""))*('High Level Dashboard'!$C$12-(ROUNDDOWN('High Level Dashboard'!$C$12,0)))),0) + IFERROR(-PMT('High Level Dashboard'!$C$10,'High Level Dashboard'!$C$12-'High Level Dashboard'!$C$11+1, (_xlfn.XLOOKUP('High Level Dashboard'!E$64-(ROUNDDOWN('High Level Dashboard'!$C$11,0)),'High Level Dashboard'!$B$64:$AV$64,'High Level Dashboard'!$B$112:$AV$112,"")*('High Level Dashboard'!$C$11-ROUNDDOWN('High Level Dashboard'!$C$11,0)))),0) + (((SUMIFS('High Level Dashboard'!$B$112:$AV$112,'High Level Dashboard'!$B$64:$AV$64,">"&'High Level Dashboard'!E$64-ROUNDDOWN('High Level Dashboard'!$C$11,0),'High Level Dashboard'!$B$64:$AV$64,"<="&'High Level Dashboard'!E$64)+(IFERROR(SUMIF('High Level Dashboard'!$B$64:$AV$64,ROUNDDOWN('High Level Dashboard'!E$64-'High Level Dashboard'!$C$11,0)+1,'High Level Dashboard'!$B$112:$AV$112)*(1-('High Level Dashboard'!$C$11-ROUNDDOWN('High Level Dashboard'!$C$11,0))),"")))*'High Level Dashboard'!$C$10) )) -> 54.002609 | G108: ='High Level Dashboard'!$C$53*'High Level Dashboard'!$C$9* (-PMT('High Level Dashboard'!$C$10,'High Level Dashboard'!$C$12-'High Level Dashboard'!$C$11+1, SUMIFS('High Level Dashboard'!$B$112:$AV$112,'High Level Dashboard'!$B$64:$AV$64,">="&('High Level Dashboard'!F$64-(ROUNDDOWN('High Level Dashboard'!$C$12,0))+1),'High Level Dashboard'!$B$64:$AV$64,"<="&('High Level Dashboard'!F$64-(ROUNDUP('High Level Dashboard'!$C$11,0))))) + IFERROR(-PMT('High Level Dashboard'!$C$10,'High Level Dashboard'!$C$12-'High Level Dashboard'!$C$11+1, (_xlfn.XLOOKUP('High Level Dashboard'!F$64-(ROUNDUP('High Level Dashboard'!$C$12,0))+1,'High Level Dashboard'!$B$64:$AV$64,'High Level Dashboard'!$B$112:$AV$112,""))*('High Level Dashboard'!$C$12-(ROUNDDOWN('High Level Dashboard'!$C$12,0)))),0) + IFERROR(-PMT('High Level Dashboard'!$C$10,'High Level Dashboard'!$C$12-'High Level Dashboard'!$C$11+1, (_xlfn.XLOOKUP('High Level Dashboard'!F$64-(ROUNDDOWN('High Level Dashboard'!$C$11,0)),'High Level Dashboard'!$B$64:$AV$64,'High Level Dashboard'!$B$112:$AV$112,"")*('High Level Dashboard'!$C$11-ROUNDDOWN('High Level Dashboard'!$C$11,0)))),0) + (((SUMIFS('High Level Dashboard'!$B$112:$AV$112,'High Level Dashboard'!$B$64:$AV$64,">"&'High Level Dashboard'!F$64-ROUNDDOWN('High Level Dashboard'!$C$11,0),'High Level Dashboard'!$B$64:$AV$64,"<="&'High Level Dashboard'!F$64)+(IFERROR(SUMIF('High Level Dashboard'!$B$64:$AV$64,ROUNDDOWN('High Level Dashboard'!F$64-'High Level Dashboard'!$C$11,0)+1,'High Level Dashboard'!$B$112:$AV$112)*(1-('High Level Dashboard'!$C$11-ROUNDDOWN('High Level Dashboard'!$C$11,0))),"")))*'High Level Dashboard'!$C$10) )) -> 82.660025 | H108: ='High Level Dashboard'!$C$53*'High Level Dashboard'!$C$9* (-PMT('High Level Dashboard'!$C$10,'High Level Dashboard'!$C$12-'High Level Dashboard'!$C$11+1, SUMIFS('High Level Dashboard'!$B$112:$AV$112,'High Level Dashboard'!$B$64:$AV$64,">="&('High Level Dashboard'!G$64-(ROUNDDOWN('High Level Dashboard'!$C$12,0))+1),'High Level Dashboard'!$B$64:$AV$64,"<="&('High Level Dashboard'!G$64-(ROUNDUP('High Level Dashboard'!$C$11,0))))) + IFERROR(-PMT('High Level Dashboard'!$C$10,'High Level Dashboard'!$C$12-'High Level Dashboard'!$C$11+1, (_xlfn.XLOOKUP('High Level Dashboard'!G$64-(ROUNDUP('High Level Dashboard'!$C$12,0))+1,'High Level Dashboard'!$B$64:$AV$64,'High Level Dashboard'!$B$112:$AV$112,""))*('High Level Dashboard'!$C$12-(ROUNDDOWN('High Level Dashboard'!$C$12,0)))),0) + IFERROR(-PMT('High Level Dashboard'!$C$10,'High Level Dashboard'!$C$12-'High Level Dashboard'!$C$11+1, (_xlfn.XLOOKUP('High Level Dashboard'!G$64-(ROUNDDOWN('High Level Dashboard'!$C$11,0)),'High Level Dashboard'!$B$64:$AV$64,'High Level Dashboard'!$B$112:$AV$112,"")*('High Level Dashboard'!$C$11-ROUNDDOWN('High Level Dashboard'!$C$11,0)))),0) + (((SUMIFS('High Level Dashboard'!$B$112:$AV$112,'High Level Dashboard'!$B$64:$AV$64,">"&'High Level Dashboard'!G$64-ROUNDDOWN('High Level Dashboard'!$C$11,0),'High Level Dashboard'!$B$64:$AV$64,"<="&'High Level Dashboard'!G$64)+(IFERROR(SUMIF('High Level Dashboard'!$B$64:$AV$64,ROUNDDOWN('High Level Dashboard'!G$64-'High Level Dashboard'!$C$11,0)+1,'High Level Dashboard'!$B$112:$AV$112)*(1-('High Level Dashboard'!$C$11-ROUNDDOWN('High Level Dashboard'!$C$11,0))),"")))*'High Level Dashboard'!$C$10) )) -> 100.57169 | I108: ='High Level Dashboard'!$C$53*'High Level Dashboard'!$C$9* (-PMT('High Level Dashboard'!$C$10,'High Level Dashboard'!$C$12-'High Level Dashboard'!$C$11+1, SUMIFS('High Level Dashboard'!$B$112:$AV$112,'High Level Dashboard'!$B$64:$AV$64,">="&('High Level Dashboard'!H$64-(ROUNDDOWN('High Level Dashboard'!$C$12,0))+1),'High Level Dashboard'!$B$64:$AV$64,"<="&('High Level Dashboard'!H$64-(ROUNDUP('High Level Dashboard'!$C$11,0))))) + IFERROR(-PMT('High Level Dashboard'!$C$10,'High Level Dashboard'!$C$12-'High Level Dashboard'!$C$11+1, (_xlfn.XLOOKUP('High Level Dashboard'!H$64-(ROUNDUP('High Level Dashboard'!$C$12,0))+1,'High Level Dashboard'!$B$64:$AV$64,'High Level Dashboard'!$B$112:$AV$112,""))*('High Level Dashboard'!$C$12-(ROUNDDOWN('High Level Dashboard'!$C$12,0)))),0) + IFERROR(-PMT('High Level Dashboard'!$C$10,'High Level Dashboard'!$C$12-'High Level Dashboard'!$C$11+1, (_xlfn.XLOOKUP('High Level Dashboard'!H$64-(ROUNDDOWN('High Level Dashboard'!$C$11,0)),'High Level Dashboard'!$B$64:$AV$64,'High Level Dashboard'!$B$112:$AV$112,"")*('High Level Dashboard'!$C$11-ROUNDDOWN('High Level Dashboard'!$C$11,0)))),0) + (((SUMIFS('High Level Dashboard'!$B$112:$AV$112,'High Level Dashboard'!$B$64:$AV$64,">"&'High Level Dashboard'!H$64-ROUNDDOWN('High Level Dashboard'!$C$11,0),'High Level Dashboard'!$B$64:$AV$64,"<="&'High Level Dashboard'!H$64)+(IFERROR(SUMIF('High Level Dashboard'!$B$64:$AV$64,ROUNDDOWN('High Level Dashboard'!H$64-'High Level Dashboard'!$C$11,0)+1,'High Level Dashboard'!$B$112:$AV$112)*(1-('High Level Dashboard'!$C$11-ROUNDDOWN('High Level Dashboard'!$C$11,0))),"")))*'High Level Dashboard'!$C$10) )) -> 137.57846 | J108: ='High Level Dashboard'!$C$53*'High Level Dashboard'!$C$9* (-PMT('High Level Dashboard'!$C$10,'High Level Dashboard'!$C$12-'High Level Dashboard'!$C$11+1, SUMIFS('High Level Dashboard'!$B$112:$AV$112,'High Level Dashboard'!$B$64:$AV$64,">="&('High Level Dashboard'!I$64-(ROUNDDOWN('High Level Dashboard'!$C$12,0))+1),'High Level Dashboard'!$B$64:$AV$64,"<="&('High Level Dashboard'!I$64-(ROUNDUP('High Level Dashboard'!$C$11,0))))) + IFERROR(-PMT('High Level Dashboard'!$C$10,'High Level Dashboard'!$C$12-'High Level Dashboard'!$C$11+1, (_xlfn.XLOOKUP('High Level Dashboard'!I$64-(ROUNDUP('High Level Dashboard'!$C$12,0))+1,'High Level Dashboard'!$B$64:$AV$64,'High Level Dashboard'!$B$112:$AV$112,""))*('High Level Dashboard'!$C$12-(ROUNDDOWN('High Level Dashboard'!$C$12,0)))),0) + IFERROR(-PMT('High Level Dashboard'!$C$10,'High Level Dashboard'!$C$12-'High Level Dashboard'!$C$11+1, (_xlfn.XLOOKUP('High Level Dashboard'!I$64-(ROUNDDOWN('High Level Dashboard'!$C$11,0)),'High Level Dashboard'!$B$64:$AV$64,'High Level Dashboard'!$B$112:$AV$112,"")*('High Level Dashboard'!$C$11-ROUNDDOWN('High Level Dashboard'!$C$11,0)))),0) + (((SUMIFS('High Level Dashboard'!$B$112:$AV$112,'High Level Dashboard'!$B$64:$AV$64,">"&'High Level Dashboard'!I$64-ROUNDDOWN('High Level Dashboard'!$C$11,0),'High Level Dashboard'!$B$64:$AV$64,"<="&'High Level Dashboard'!I$64)+(IFERROR(SUMIF('High Level Dashboard'!$B$64:$AV$64,ROUNDDOWN('High Level Dashboard'!I$64-'High Level Dashboard'!$C$11,0)+1,'High Level Dashboard'!$B$112:$AV$112)*(1-('High Level Dashboard'!$C$11-ROUNDDOWN('High Level Dashboard'!$C$11,0))),"")))*'High Level Dashboard'!$C$10) )) -> 176.36524 | ... AV108: ='High Level Dashboard'!$C$53*'High Level Dashboard'!$C$9* (-PMT('High Level Dashboard'!$C$10,'High Level Dashboard'!$C$12-'High Level Dashboard'!$C$11+1, SUMIFS('High Level Dashboard'!$B$112:$AV$112,'High Level Dashboard'!$B$64:$AV$64,">="&('High Level Dashboard'!AU$64-(ROUNDDOWN('High Level Dashboard'!$C$12,0))+1),'High Level Dashboard'!$B$64:$AV$64,"<="&('High Level Dashboard'!AU$64-(ROUNDUP('High Level Dashboard'!$C$11,0))))) + IFERROR(-PMT('High Level Dashboard'!$C$10,'High Level Dashboard'!$C$12-'High Level Dashboard'!$C$11+1, (_xlfn.XLOOKUP('High Level Dashboard'!AU$64-(ROUNDUP('High Level Dashboard'!$C$12,0))+1,'High Level Dashboard'!$B$64:$AV$64,'High Level Dashboard'!$B$112:$AV$112,""))*('High Level Dashboard'!$C$12-(ROUNDDOWN('High Level Dashboard'!$C$12,0)))),0) + IFERROR(-PMT('High Level Dashboard'!$C$10,'High Level Dashboard'!$C$12-'High Level Dashboard'!$C$11+1, (_xlfn.XLOOKUP('High Level Dashboard'!AU$64-(ROUNDDOWN('High Level Dashboard'!$C$11,0)),'High Level Dashboard'!$B$64:$AV$64,'High Level Dashboard'!$B$112:$AV$112,"")*('High Level Dashboard'!$C$11-ROUNDDOWN('High Level Dashboard'!$C$11,0)))),0) + (((SUMIFS('High Level Dashboard'!$B$112:$AV$112,'High Level Dashboard'!$B$64:$AV$64,">"&'High Level Dashboard'!AU$64-ROUNDDOWN('High Level Dashboard'!$C$11,0),'High Level Dashboard'!$B$64:$AV$64,"<="&'High Level Dashboard'!AU$64)+(IFERROR(SUMIF('High Level Dashboard'!$B$64:$AV$64,ROUNDDOWN('High Level Dashboard'!AU$64-'High Level Dashboard'!$C$11,0)+1,'High Level Dashboard'!$B$112:$AV$112)*(1-('High Level Dashboard'!$C$11-ROUNDDOWN('High Level Dashboard'!$C$11,0))),"")))*'High Level Dashboard'!$C$10) )) -> 2410.3743
A109: Loans - Concessional Domestic Finance (Conc DPS) | C109: ='High Level Dashboard'!$C$54*'High Level Dashboard'!$C$15* (-PMT('High Level Dashboard'!$C$16,'High Level Dashboard'!$C$18-'High Level Dashboard'!$C$17+1, SUMIFS('High Level Dashboard'!$B$112:$AV$112,'High Level Dashboard'!$B$64:$AV$64,">="&('High Level Dashboard'!B$64-(ROUNDDOWN('High Level Dashboard'!$C$18,0))+1),'High Level Dashboard'!$B$64:$AV$64,"<="&('High Level Dashboard'!B$64-(ROUNDUP('High Level Dashboard'!$C$17,0))))) + IFERROR(-PMT('High Level Dashboard'!$C$16,'High Level Dashboard'!$C$18-'High Level Dashboard'!$C$17+1, (_xlfn.XLOOKUP('High Level Dashboard'!B$64-(ROUNDUP('High Level Dashboard'!$C$18,0))+1,'High Level Dashboard'!$B$64:$AV$64,'High Level Dashboard'!$B$112:$AV$112,""))*('High Level Dashboard'!$C$18-(ROUNDDOWN('High Level Dashboard'!$C$18,0)))),0) + IFERROR(-PMT('High Level Dashboard'!$C$16,'High Level Dashboard'!$C$18-'High Level Dashboard'!$C$17+1, (_xlfn.XLOOKUP('High Level Dashboard'!B$64-(ROUNDDOWN('High Level Dashboard'!$C$17,0)),'High Level Dashboard'!$B$64:$AV$64,'High Level Dashboard'!$B$112:$AV$112,"")*('High Level Dashboard'!$C$17-ROUNDDOWN('High Level Dashboard'!$C$17,0)))),0) + (((SUMIFS('High Level Dashboard'!$B$112:$AV$112,'High Level Dashboard'!$B$64:$AV$64,">"&'High Level Dashboard'!B$64-ROUNDDOWN('High Level Dashboard'!$C$17,0),'High Level Dashboard'!$B$64:$AV$64,"<="&'High Level Dashboard'!B$64)+(IFERROR(SUMIF('High Level Dashboard'!$B$64:$AV$64,ROUNDDOWN('High Level Dashboard'!B$64-'High Level Dashboard'!$C$17,0)+1,'High Level Dashboard'!$B$112:$AV$112)*(1-('High Level Dashboard'!$C$17-ROUNDDOWN('High Level Dashboard'!$C$17,0))),"")))*'High Level Dashboard'!$C$16) )) -> 0.27359941 | D109: ='High Level Dashboard'!$C$54*'High Level Dashboard'!$C$15* (-PMT('High Level Dashboard'!$C$16,'High Level Dashboard'!$C$18-'High Level Dashboard'!$C$17+1, SUMIFS('High Level Dashboard'!$B$112:$AV$112,'High Level Dashboard'!$B$64:$AV$64,">="&('High Level Dashboard'!C$64-(ROUNDDOWN('High Level Dashboard'!$C$18,0))+1),'High Level Dashboard'!$B$64:$AV$64,"<="&('High Level Dashboard'!C$64-(ROUNDUP('High Level Dashboard'!$C$17,0))))) + IFERROR(-PMT('High Level Dashboard'!$C$16,'High Level Dashboard'!$C$18-'High Level Dashboard'!$C$17+1, (_xlfn.XLOOKUP('High Level Dashboard'!C$64-(ROUNDUP('High Level Dashboard'!$C$18,0))+1,'High Level Dashboard'!$B$64:$AV$64,'High Level Dashboard'!$B$112:$AV$112,""))*('High Level Dashboard'!$C$18-(ROUNDDOWN('High Level Dashboard'!$C$18,0)))),0) + IFERROR(-PMT('High Level Dashboard'!$C$16,'High Level Dashboard'!$C$18-'High Level Dashboard'!$C$17+1, (_xlfn.XLOOKUP('High Level Dashboard'!C$64-(ROUNDDOWN('High Level Dashboard'!$C$17,0)),'High Level Dashboard'!$B$64:$AV$64,'High Level Dashboard'!$B$112:$AV$112,"")*('High Level Dashboard'!$C$17-ROUNDDOWN('High Level Dashboard'!$C$17,0)))),0) + (((SUMIFS('High Level Dashboard'!$B$112:$AV$112,'High Level Dashboard'!$B$64:$AV$64,">"&'High Level Dashboard'!C$64-ROUNDDOWN('High Level Dashboard'!$C$17,0),'High Level Dashboard'!$B$64:$AV$64,"<="&'High Level Dashboard'!C$64)+(IFERROR(SUMIF('High Level Dashboard'!$B$64:$AV$64,ROUNDDOWN('High Level Dashboard'!C$64-'High Level Dashboard'!$C$17,0)+1,'High Level Dashboard'!$B$112:$AV$112)*(1-('High Level Dashboard'!$C$17-ROUNDDOWN('High Level Dashboard'!$C$17,0))),"")))*'High Level Dashboard'!$C$16) )) -> 0.71675297 | E109: ='High Level Dashboard'!$C$54*'High Level Dashboard'!$C$15* (-PMT('High Level Dashboard'!$C$16,'High Level Dashboard'!$C$18-'High Level Dashboard'!$C$17+1, SUMIFS('High Level Dashboard'!$B$112:$AV$112,'High Level Dashboard'!$B$64:$AV$64,">="&('High Level Dashboard'!D$64-(ROUNDDOWN('High Level Dashboard'!$C$18,0))+1),'High Level Dashboard'!$B$64:$AV$64,"<="&('High Level Dashboard'!D$64-(ROUNDUP('High Level Dashboard'!$C$17,0))))) + IFERROR(-PMT('High Level Dashboard'!$C$16,'High Level Dashboard'!$C$18-'High Level Dashboard'!$C$17+1, (_xlfn.XLOOKUP('High Level Dashboard'!D$64-(ROUNDUP('High Level Dashboard'!$C$18,0))+1,'High Level Dashboard'!$B$64:$AV$64,'High Level Dashboard'!$B$112:$AV$112,""))*('High Level Dashboard'!$C$18-(ROUNDDOWN('High Level Dashboard'!$C$18,0)))),0) + IFERROR(-PMT('High Level Dashboard'!$C$16,'High Level Dashboard'!$C$18-'High Level Dashboard'!$C$17+1, (_xlfn.XLOOKUP('High Level Dashboard'!D$64-(ROUNDDOWN('High Level Dashboard'!$C$17,0)),'High Level Dashboard'!$B$64:$AV$64,'High Level Dashboard'!$B$112:$AV$112,"")*('High Level Dashboard'!$C$17-ROUNDDOWN('High Level Dashboard'!$C$17,0)))),0) + (((SUMIFS('High Level Dashboard'!$B$112:$AV$112,'High Level Dashboard'!$B$64:$AV$64,">"&'High Level Dashboard'!D$64-ROUNDDOWN('High Level Dashboard'!$C$17,0),'High Level Dashboard'!$B$64:$AV$64,"<="&'High Level Dashboard'!D$64)+(IFERROR(SUMIF('High Level Dashboard'!$B$64:$AV$64,ROUNDDOWN('High Level Dashboard'!D$64-'High Level Dashboard'!$C$17,0)+1,'High Level Dashboard'!$B$112:$AV$112)*(1-('High Level Dashboard'!$C$17-ROUNDDOWN('High Level Dashboard'!$C$17,0))),"")))*'High Level Dashboard'!$C$16) )) -> 1.1442721 | F109: ='High Level Dashboard'!$C$54*'High Level Dashboard'!$C$15* (-PMT('High Level Dashboard'!$C$16,'High Level Dashboard'!$C$18-'High Level Dashboard'!$C$17+1, SUMIFS('High Level Dashboard'!$B$112:$AV$112,'High Level Dashboard'!$B$64:$AV$64,">="&('High Level Dashboard'!E$64-(ROUNDDOWN('High Level Dashboard'!$C$18,0))+1),'High Level Dashboard'!$B$64:$AV$64,"<="&('High Level Dashboard'!E$64-(ROUNDUP('High Level Dashboard'!$C$17,0))))) + IFERROR(-PMT('High Level Dashboard'!$C$16,'High Level Dashboard'!$C$18-'High Level Dashboard'!$C$17+1, (_xlfn.XLOOKUP('High Level Dashboard'!E$64-(ROUNDUP('High Level Dashboard'!$C$18,0))+1,'High Level Dashboard'!$B$64:$AV$64,'High Level Dashboard'!$B$112:$AV$112,""))*('High Level Dashboard'!$C$18-(ROUNDDOWN('High Level Dashboard'!$C$18,0)))),0) + IFERROR(-PMT('High Level Dashboard'!$C$16,'High Level Dashboard'!$C$18-'High Level Dashboard'!$C$17+1, (_xlfn.XLOOKUP('High Level Dashboard'!E$64-(ROUNDDOWN('High Level Dashboard'!$C$17,0)),'High Level Dashboard'!$B$64:$AV$64,'High Level Dashboard'!$B$112:$AV$112,"")*('High Level Dashboard'!$C$17-ROUNDDOWN('High Level Dashboard'!$C$17,0)))),0) + (((SUMIFS('High Level Dashboard'!$B$112:$AV$112,'High Level Dashboard'!$B$64:$AV$64,">"&'High Level Dashboard'!E$64-ROUNDDOWN('High Level Dashboard'!$C$17,0),'High Level Dashboard'!$B$64:$AV$64,"<="&'High Level Dashboard'!E$64)+(IFERROR(SUMIF('High Level Dashboard'!$B$64:$AV$64,ROUNDDOWN('High Level Dashboard'!E$64-'High Level Dashboard'!$C$17,0)+1,'High Level Dashboard'!$B$112:$AV$112)*(1-('High Level Dashboard'!$C$17-ROUNDDOWN('High Level Dashboard'!$C$17,0))),"")))*'High Level Dashboard'!$C$16) )) -> 1.5340163 | G109: ='High Level Dashboard'!$C$54*'High Level Dashboard'!$C$15* (-PMT('High Level Dashboard'!$C$16,'High Level Dashboard'!$C$18-'High Level Dashboard'!$C$17+1, SUMIFS('High Level Dashboard'!$B$112:$AV$112,'High Level Dashboard'!$B$64:$AV$64,">="&('High Level Dashboard'!F$64-(ROUNDDOWN('High Level Dashboard'!$C$18,0))+1),'High Level Dashboard'!$B$64:$AV$64,"<="&('High Level Dashboard'!F$64-(ROUNDUP('High Level Dashboard'!$C$17,0))))) + IFERROR(-PMT('High Level Dashboard'!$C$16,'High Level Dashboard'!$C$18-'High Level Dashboard'!$C$17+1, (_xlfn.XLOOKUP('High Level Dashboard'!F$64-(ROUNDUP('High Level Dashboard'!$C$18,0))+1,'High Level Dashboard'!$B$64:$AV$64,'High Level Dashboard'!$B$112:$AV$112,""))*('High Level Dashboard'!$C$18-(ROUNDDOWN('High Level Dashboard'!$C$18,0)))),0) + IFERROR(-PMT('High Level Dashboard'!$C$16,'High Level Dashboard'!$C$18-'High Level Dashboard'!$C$17+1, (_xlfn.XLOOKUP('High Level Dashboard'!F$64-(ROUNDDOWN('High Level Dashboard'!$C$17,0)),'High Level Dashboard'!$B$64:$AV$64,'High Level Dashboard'!$B$112:$AV$112,"")*('High Level Dashboard'!$C$17-ROUNDDOWN('High Level Dashboard'!$C$17,0)))),0) + (((SUMIFS('High Level Dashboard'!$B$112:$AV$112,'High Level Dashboard'!$B$64:$AV$64,">"&'High Level Dashboard'!F$64-ROUNDDOWN('High Level Dashboard'!$C$17,0),'High Level Dashboard'!$B$64:$AV$64,"<="&'High Level Dashboard'!F$64)+(IFERROR(SUMIF('High Level Dashboard'!$B$64:$AV$64,ROUNDDOWN('High Level Dashboard'!F$64-'High Level Dashboard'!$C$17,0)+1,'High Level Dashboard'!$B$112:$AV$112)*(1-('High Level Dashboard'!$C$17-ROUNDDOWN('High Level Dashboard'!$C$17,0))),"")))*'High Level Dashboard'!$C$16) )) -> 2.3480685 | H109: ='High Level Dashboard'!$C$54*'High Level Dashboard'!$C$15* (-PMT('High Level Dashboard'!$C$16,'High Level Dashboard'!$C$18-'High Level Dashboard'!$C$17+1, SUMIFS('High Level Dashboard'!$B$112:$AV$112,'High Level Dashboard'!$B$64:$AV$64,">="&('High Level Dashboard'!G$64-(ROUNDDOWN('High Level Dashboard'!$C$18,0))+1),'High Level Dashboard'!$B$64:$AV$64,"<="&('High Level Dashboard'!G$64-(ROUNDUP('High Level Dashboard'!$C$17,0))))) + IFERROR(-PMT('High Level Dashboard'!$C$16,'High Level Dashboard'!$C$18-'High Level Dashboard'!$C$17+1, (_xlfn.XLOOKUP('High Level Dashboard'!G$64-(ROUNDUP('High Level Dashboard'!$C$18,0))+1,'High Level Dashboard'!$B$64:$AV$64,'High Level Dashboard'!$B$112:$AV$112,""))*('High Level Dashboard'!$C$18-(ROUNDDOWN('High Level Dashboard'!$C$18,0)))),0) + IFERROR(-PMT('High Level Dashboard'!$C$16,'High Level Dashboard'!$C$18-'High Level Dashboard'!$C$17+1, (_xlfn.XLOOKUP('High Level Dashboard'!G$64-(ROUNDDOWN('High Level Dashboard'!$C$17,0)),'High Level Dashboard'!$B$64:$AV$64,'High Level Dashboard'!$B$112:$AV$112,"")*('High Level Dashboard'!$C$17-ROUNDDOWN('High Level Dashboard'!$C$17,0)))),0) + (((SUMIFS('High Level Dashboard'!$B$112:$AV$112,'High Level Dashboard'!$B$64:$AV$64,">"&'High Level Dashboard'!G$64-ROUNDDOWN('High Level Dashboard'!$C$17,0),'High Level Dashboard'!$B$64:$AV$64,"<="&'High Level Dashboard'!G$64)+(IFERROR(SUMIF('High Level Dashboard'!$B$64:$AV$64,ROUNDDOWN('High Level Dashboard'!G$64-'High Level Dashboard'!$C$17,0)+1,'High Level Dashboard'!$B$112:$AV$112)*(1-('High Level Dashboard'!$C$17-ROUNDDOWN('High Level Dashboard'!$C$17,0))),"")))*'High Level Dashboard'!$C$16) )) -> 2.8568733 | I109: ='High Level Dashboard'!$C$54*'High Level Dashboard'!$C$15* (-PMT('High Level Dashboard'!$C$16,'High Level Dashboard'!$C$18-'High Level Dashboard'!$C$17+1, SUMIFS('High Level Dashboard'!$B$112:$AV$112,'High Level Dashboard'!$B$64:$AV$64,">="&('High Level Dashboard'!H$64-(ROUNDDOWN('High Level Dashboard'!$C$18,0))+1),'High Level Dashboard'!$B$64:$AV$64,"<="&('High Level Dashboard'!H$64-(ROUNDUP('High Level Dashboard'!$C$17,0))))) + IFERROR(-PMT('High Level Dashboard'!$C$16,'High Level Dashboard'!$C$18-'High Level Dashboard'!$C$17+1, (_xlfn.XLOOKUP('High Level Dashboard'!H$64-(ROUNDUP('High Level Dashboard'!$C$18,0))+1,'High Level Dashboard'!$B$64:$AV$64,'High Level Dashboard'!$B$112:$AV$112,""))*('High Level Dashboard'!$C$18-(ROUNDDOWN('High Level Dashboard'!$C$18,0)))),0) + IFERROR(-PMT('High Level Dashboard'!$C$16,'High Level Dashboard'!$C$18-'High Level Dashboard'!$C$17+1, (_xlfn.XLOOKUP('High Level Dashboard'!H$64-(ROUNDDOWN('High Level Dashboard'!$C$17,0)),'High Level Dashboard'!$B$64:$AV$64,'High Level Dashboard'!$B$112:$AV$112,"")*('High Level Dashboard'!$C$17-ROUNDDOWN('High Level Dashboard'!$C$17,0)))),0) + (((SUMIFS('High Level Dashboard'!$B$112:$AV$112,'High Level Dashboard'!$B$64:$AV$64,">"&'High Level Dashboard'!H$64-ROUNDDOWN('High Level Dashboard'!$C$17,0),'High Level Dashboard'!$B$64:$AV$64,"<="&'High Level Dashboard'!H$64)+(IFERROR(SUMIF('High Level Dashboard'!$B$64:$AV$64,ROUNDDOWN('High Level Dashboard'!H$64-'High Level Dashboard'!$C$17,0)+1,'High Level Dashboard'!$B$112:$AV$112)*(1-('High Level Dashboard'!$C$17-ROUNDDOWN('High Level Dashboard'!$C$17,0))),"")))*'High Level Dashboard'!$C$16) )) -> 3.4860809 | J109: ='High Level Dashboard'!$C$54*'High Level Dashboard'!$C$15* (-PMT('High Level Dashboard'!$C$16,'High Level Dashboard'!$C$18-'High Level Dashboard'!$C$17+1, SUMIFS('High Level Dashboard'!$B$112:$AV$112,'High Level Dashboard'!$B$64:$AV$64,">="&('High Level Dashboard'!I$64-(ROUNDDOWN('High Level Dashboard'!$C$18,0))+1),'High Level Dashboard'!$B$64:$AV$64,"<="&('High Level Dashboard'!I$64-(ROUNDUP('High Level Dashboard'!$C$17,0))))) + IFERROR(-PMT('High Level Dashboard'!$C$16,'High Level Dashboard'!$C$18-'High Level Dashboard'!$C$17+1, (_xlfn.XLOOKUP('High Level Dashboard'!I$64-(ROUNDUP('High Level Dashboard'!$C$18,0))+1,'High Level Dashboard'!$B$64:$AV$64,'High Level Dashboard'!$B$112:$AV$112,""))*('High Level Dashboard'!$C$18-(ROUNDDOWN('High Level Dashboard'!$C$18,0)))),0) + IFERROR(-PMT('High Level Dashboard'!$C$16,'High Level Dashboard'!$C$18-'High Level Dashboard'!$C$17+1, (_xlfn.XLOOKUP('High Level Dashboard'!I$64-(ROUNDDOWN('High Level Dashboard'!$C$17,0)),'High Level Dashboard'!$B$64:$AV$64,'High Level Dashboard'!$B$112:$AV$112,"")*('High Level Dashboard'!$C$17-ROUNDDOWN('High Level Dashboard'!$C$17,0)))),0) + (((SUMIFS('High Level Dashboard'!$B$112:$AV$112,'High Level Dashboard'!$B$64:$AV$64,">"&'High Level Dashboard'!I$64-ROUNDDOWN('High Level Dashboard'!$C$17,0),'High Level Dashboard'!$B$64:$AV$64,"<="&'High Level Dashboard'!I$64)+(IFERROR(SUMIF('High Level Dashboard'!$B$64:$AV$64,ROUNDDOWN('High Level Dashboard'!I$64-'High Level Dashboard'!$C$17,0)+1,'High Level Dashboard'!$B$112:$AV$112)*(1-('High Level Dashboard'!$C$17-ROUNDDOWN('High Level Dashboard'!$C$17,0))),"")))*'High Level Dashboard'!$C$16) )) -> 3.9184562 | ... AV109: ='High Level Dashboard'!$C$54*'High Level Dashboard'!$C$15* (-PMT('High Level Dashboard'!$C$16,'High Level Dashboard'!$C$18-'High Level Dashboard'!$C$17+1, SUMIFS('High Level Dashboard'!$B$112:$AV$112,'High Level Dashboard'!$B$64:$AV$64,">="&('High Level Dashboard'!AU$64-(ROUNDDOWN('High Level Dashboard'!$C$18,0))+1),'High Level Dashboard'!$B$64:$AV$64,"<="&('High Level Dashboard'!AU$64-(ROUNDUP('High Level Dashboard'!$C$17,0))))) + IFERROR(-PMT('High Level Dashboard'!$C$16,'High Level Dashboard'!$C$18-'High Level Dashboard'!$C$17+1, (_xlfn.XLOOKUP('High Level Dashboard'!AU$64-(ROUNDUP('High Level Dashboard'!$C$18,0))+1,'High Level Dashboard'!$B$64:$AV$64,'High Level Dashboard'!$B$112:$AV$112,""))*('High Level Dashboard'!$C$18-(ROUNDDOWN('High Level Dashboard'!$C$18,0)))),0) + IFERROR(-PMT('High Level Dashboard'!$C$16,'High Level Dashboard'!$C$18-'High Level Dashboard'!$C$17+1, (_xlfn.XLOOKUP('High Level Dashboard'!AU$64-(ROUNDDOWN('High Level Dashboard'!$C$17,0)),'High Level Dashboard'!$B$64:$AV$64,'High Level Dashboard'!$B$112:$AV$112,"")*('High Level Dashboard'!$C$17-ROUNDDOWN('High Level Dashboard'!$C$17,0)))),0) + (((SUMIFS('High Level Dashboard'!$B$112:$AV$112,'High Level Dashboard'!$B$64:$AV$64,">"&'High Level Dashboard'!AU$64-ROUNDDOWN('High Level Dashboard'!$C$17,0),'High Level Dashboard'!$B$64:$AV$64,"<="&'High Level Dashboard'!AU$64)+(IFERROR(SUMIF('High Level Dashboard'!$B$64:$AV$64,ROUNDDOWN('High Level Dashboard'!AU$64-'High Level Dashboard'!$C$17,0)+1,'High Level Dashboard'!$B$112:$AV$112)*(1-('High Level Dashboard'!$C$17-ROUNDDOWN('High Level Dashboard'!$C$17,0))),"")))*'High Level Dashboard'!$C$16) )) -> 57.354448
